Workbook
Name Slicer_company_size: #N/A
Name Slicer_experience_level: #N/A
Name Slicer_region: #N/A
Name Slicer_remote_category: #N/A

Sheet Salary_Calculator
A1: Experience Level: | B1: EN
A2: Company Size: | B2: M
A3: Remote Work: | B3: 100
A4: Region: | B4: North America
A6: Estimated Salary: | B6: =AVERAGEIFS(DS_Salaries!$G:G, DS_Salaries!$B:$B, B1,DS_Salaries!$K:$K, B2, DS_Salaries!$O:$O, B4) -> 75600

Sheet Salary_Bands
A1: Salary Bands | B1: Count
A2: <$50k | B2: =B4 -> 155
A3: $50k-$100k | B3: =COUNTIFS(DS_Salaries!G:G, ">=50000", DS_Salaries!G:G, "<=100000") -> 188
A4: $100k-$150k | B4: =COUNTIFS(DS_Salaries!G:G, ">=100000", DS_Salaries!G:G, "<=150000") -> 155

Sheet PT_Experience
A1: Average Salary by Experience Level
A3: Row Labels | B3: Average of salary_in_usd | C3: Count of salary_in_usd
A4: EN | B4: 62305.885 | C4: 87
A5: EX | B5: 199392.04 | C5: 26
A6: MI | B6: 88612.058 | C6: 206
A7: SE | B7: 138374.88 | C7: 243
A8: Grand Total | B8: 111181.47 | C8: 562

Sheet PT_CompanySize
A1: Salary by Company Size
A3: Row Labels | B3: Average of salary_in_usd | C3: Count of salary_in_usd | D3: Sum of salary_in_usd
A4: L | B4: 118213.88 | C4: 193 | D4: 22815279
A5: M | B5: 115576.57 | C5: 288 | D5: 33286053
A6: S | B6: 78798.185 | C6: 81 | D6: 6382653
A7: Grand Total | B7: 111181.47 | C7: 562 | D7: 62483985

Sheet PT_Region
A1: Salary by Region
A3: Row Labels | B3: Average of salary_in_usd | C3: Count of salary_in_usd
A4: Asia | B4: 45495.973 | C4: 37
A5: Europe | B5: 70329.511 | C5: 141
A6: North America | B6: 140178.43 | C6: 348
A7: Oceania | B7: 112282 | C7: 4
A8: Other | B8: 56861.481 | C8: 27
A9: South America | B9: 23538 | C9: 5
A10: (blank)
A11: Grand Total | B11: 111181.47 | C11: 562

Sheet PT_Remote
A1: Salary by Remote Category
A3: Row Labels | B3: Average of salary_in_usd | C3: Count of salary_in_usd
A4: Fully Remote | B4: 121101.63 | C4: 345
A5: Hybrid | B5: 80721.898 | C5: 98
A6: On-site | B6: 107505.67 | C6: 119
A7: Grand Total | B7: 111181.47 | C7: 562

Sheet Dashboard
G1: COMPENSATION ANALYTICS DASHBOARD
I2: KPI
I3: Total Records | K3: =Summary_Stats!C4 -> 562
I4: Average Salary | K4: =Summary_Stats!C5 -> 111181.47
I5: Median Salary | K5: =Summary_Stats!C6 -> 100000
I6: Max Salary | K6: =Summary_Stats!C8 -> 600000
I7: Salary Range | K7: =Summary_Stats!C8 - Summary_Stats!C7 -> 594591

Sheet PT_CrossTab
A1: Cross-Tabulation (Experience × Company Size)
A3: Average of salary_in_usd | B3: Column Labels
A4: Row Labels | B4: L | C4: M | D4: S | E4: Grand Total
A5: EN | B5: 72813.241 | C5: 51919.103 | D5: 62185.31 | E5: 62305.885
A6: EX | B6: 221942.18 | C6: 178241.75 | D6: 201309.33 | E6: 199392.04
A7: MI | B7: 96903.31 | C7: 91488.874 | D7: 52694.926 | E7: 88612.058
A8: SE | B8: 146702.22 | C8: 137829.31 | D8: 116026.73 | E8: 138374.88
A9: Grand Total | B9: 118213.88 | C9: 115576.57 | D9: 78798.185 | E9: 111181.47

Sheet PT_SalaryTrends
A3: Row Labels | B3: Average of salary_in_usd
A4: 2020 | B4: 95813
A5: 2021 | B5: 100786.23
A6: 2022 | B6: 123089.1
A7: Grand Total | B7: 111181.47

Sheet DS_Salaries
A1: work_year | B1: experience_level | C1: employment_type | D1: job_title | E1: salary | F1: salary_currency | G1: salary_in_usd | H1: employee_residence | I1: remote_ratio | J1: company_location | K1: company_size | L1: experience_level_numeric | M1: company_size_numeric | N1: remote_category | O1: region | P1: salary_band
A2: 2020 | B2: MI | C2: FT | D2: Data Scientist | E2: 70000 | F2: EUR | G2: 79833 | H2: DE | I2: 0 | J2: DE | K2: L | L2: 2 | M2: 3 | N2: On-site | O2: Europe | P2: Mid (50k-100k)
A3: 2020 | B3: SE | C3: FT | D3: Machine Learning Scientist | E3: 260000 | F3: USD | G3: 260000 | H3: JP | I3: 0 | J3: JP | K3: S | L3: 3 | M3: 1 | N3: On-site | O3: Asia | P3: Executive (>150k)
A4: 2020 | B4: SE | C4: FT | D4: Big Data Engineer | E4: 85000 | F4: GBP | G4: 109024 | H4: GB | I4: 50 | J4: GB | K4: M | L4: 3 | M4: 2 | N4: Hybrid | O4: Europe | P4: Senior (100k-150k)
A5: 2020 | B5: MI | C5: FT | D5: Product Data Analyst | E5: 20000 | F5: USD | G5: 20000 | H5: HN | I5: 0 | J5: HN | K5: S | L5: 2 | M5: 1 | N5: On-site | O5: Other | P5: Entry (<50k)
A6: 2020 | B6: SE | C6: FT | D6: Machine Learning Engineer | E6: 150000 | F6: USD | G6: 150000 | H6: US | I6: 50 | J6: US | K6: L | L6: 3 | M6: 3 | N6: Hybrid | O6: North America | P6: Executive (>150k)
A7: 2020 | B7: EN | C7: FT | D7: Data Analyst | E7: 72000 | F7: USD | G7: 72000 | H7: US | I7: 100 | J7: US | K7: L | L7: 1 | M7: 3 | N7: Fully Remote | O7: North America | P7: Mid (50k-100k)
A8: 2020 | B8: SE | C8: FT | D8: Lead Data Scientist | E8: 190000 | F8: USD | G8: 190000 | H8: US | I8: 100 | J8: US | K8: S | L8: 3 | M8: 1 | N8: Fully Remote | O8: North America | P8: Executive (>150k)
A9: 2020 | B9: MI | C9: FT | D9: Data Scientist | E9: 11000000 | F9: HUF | G9: 35735 | H9: HU | I9: 50 | J9: HU | K9: L | L9: 2 | M9: 3 | N9: Hybrid | O9: Other | P9: Entry (<50k)
A10: 2020 | B10: MI | C10: FT | D10: Business Data Analyst | E10: 135000 | F10: USD | G10: 135000 | H10: US | I10: 100 | J10: US | K10: L | L10: 2 | M10: 3 | N10: Fully Remote | O10: North America | P10: Senior (100k-150k)
A11: 2020 | B11: SE | C11: FT | D11: Lead Data Engineer | E11: 125000 | F11: USD | G11: 125000 | H11: NZ | I11: 50 | J11: NZ | K11: S | L11: 3 | M11: 1 | N11: Hybrid | O11: Oceania | P11: Senior (100k-150k)
A12: 2020 | B12: EN | C12: FT | D12: Data Scientist | E12: 45000 | F12: EUR | G12: 51321 | H12: FR | I12: 0 | J12: FR | K12: S | L12: 1 | M12: 1 | N12: On-site | O12: Europe | P12: Mid (50k-100k)
A13: 2020 | B13: MI | C13: FT | D13: Data Scientist | E13: 3000000 | F13: INR | G13: 40481 | H13: IN | I13: 0 | J13: IN | K13: L | L13: 2 | M13: 3 | N13: On-site | O13: Asia | P13: Entry (<50k)
... A563: 2022 | B563: MI | C563: FT | D563: AI Scientist | E563: 200000 | F563: USD | G563: 200000 | H563: IN | I563: 100 | J563: US | K563: L | L563: 2 | M563: 3 | N563: Fully Remote | O563: North America | P563: Executive (>150k)

Sheet SO_Survey
A1: ResponseId | B1: MainBranch | C1: Age | D1: EdLevel | E1: Employment | F1: EmploymentAddl | G1: WorkExp | H1: LearnCodeChoose | I1: LearnCode | J1: LearnCodeAI | K1: AILearnHow | L1: YearsCode | M1: DevType | N1: OrgSize | O1: ICorPM | P1: RemoteWork | Q1: PurchaseInfluence | R1: TechEndorseIntro | S1: TechEndorse_1 | T1: TechEndorse_2 | U1: TechEndorse_3 | V1: TechEndorse_4 | W1: TechEndorse_5 | X1: TechEndorse_6 | Y1: TechEndorse_7 | Z1: TechEndorse_8 | AA1: TechEndorse_9 | AB1: TechEndorse_13 | AC1: TechEndorse_13_TEXT | AD1: TechOppose_1 | AE1: TechOppose_2 | AF1: TechOppose_3 | AG1: TechOppose_5 | AH1: TechOppose_7 | AI1: TechOppose_9 | AJ1: TechOppose_11 | AK1: TechOppose_13 | AL1: TechOppose_16 | AM1: TechOppose_15 | AN1: TechOppose_15_TEXT | AO1: Industry | AP1: JobSatPoints_1 | AQ1: JobSatPoints_2 | AR1: JobSatPoints_3 | AS1: JobSatPoints_4 | AT1: JobSatPoints_5 | AU1: JobSatPoints_6 | AV1: JobSatPoints_7 | AW1: JobSatPoints_8 | AX1: JobSatPoints_9 | AY1: JobSatPoints_10 | AZ1: JobSatPoints_11 | BA1: JobSatPoints_13 | BB1: JobSatPoints_14 | BC1: JobSatPoints_15 | BD1: JobSatPoints_16 | BE1: JobSatPoints_15_TEXT | BF1: AIThreat | BG1: NewRole | BH1: ToolCountWork | BI1: ToolCountPersonal | BJ1: Country | BK1: Currency | BL1: CompTotal | BM1: LanguageChoice | BN1: LanguageHaveWorkedWith | BO1: LanguageWantToWorkWith | BP1: LanguageAdmired | BQ1: LanguagesHaveEntry | BR1: LanguagesWantEntry | BS1: DatabaseChoice | BT1: DatabaseHaveWorkedWith | BU1: DatabaseWantToWorkWith | BV1: DatabaseAdmired | BW1: DatabaseHaveEntry | BX1: DatabaseWantEntry | BY1: PlatformChoice | BZ1: PlatformHaveWorkedWith | CA1: PlatformWantToWorkWith | CB1: PlatformAdmired | CC1: PlatformHaveEntry | CD1: PlatformWantEntry | CE1: WebframeChoice | CF1: WebframeHaveWorkedWith | CG1: WebframeWantToWorkWith | CH1: WebframeAdmired | CI1: WebframeHaveEntry | CJ1: WebframeWantEntry | CK1: DevEnvsChoice | CL1: DevEnvsHaveWorkedWith | CM1: DevEnvsWantToWorkWith | CN1: DevEnvsAdmired | CO1: DevEnvHaveEntry | CP1: DevEnvWantEntry | CQ1: SOTagsHaveWorkedWith | CR1: SOTagsWantToWorkWith | CS1: SOTagsAdmired | CT1: SOTagsHaveEntry | CU1: SOTagsWant Entry | CV1: OpSysPersonal use | CW1: OpSysProfessional use | CX1: OfficeStackAsyncHaveWorkedWith | CY1: OfficeStackAsyncWantToWorkWith | CZ1: OfficeStackAsyncAdmired | DA1: OfficeStackHaveEntry | DB1: OfficeStackWantEntry | DC1: CommPlatformHaveWorkedWith | DD1: CommPlatformWantToWorkWith | DE1: CommPlatformAdmired | DF1: CommPlatformHaveEntr | DG1: CommPlatformWantEntr | DH1: AIModelsChoice | DI1: AIModelsHaveWorkedWith | DJ1: AIModelsWantToWorkWith | DK1: AIModelsAdmired | DL1: AIModelsHaveEntry | DM1: AIModelsWantEntry | DN1: SOAccount | DO1: SOVisitFreq | DP1: SODuration | DQ1: SOPartFreq | DR1: SO_Dev_Content | DS1: SO_Actions_1 | DT1: SO_Actions_16 | DU1: SO_Actions_3 | DV1: SO_Actions_4 | DW1: SO_Actions_5 | DX1: SO_Actions_6 | DY1: SO_Actions_9 | DZ1: SO_Actions_7 | EA1: SO_Actions_10 | EB1: SO_Actions_15 | EC1: SO_Actions_15_TEXT | ED1: SOComm | EE1: SOFriction | EF1: AISelect | EG1: AISent | EH1: AIAcc | EI1: AIComplex | EJ1: AIToolCurrently partially AI | EK1: AIToolDon't plan to use AI for this task | EL1: AIToolPlan to partially use AI | EM1: AIToolPlan to mostly use AI | EN1: AIToolCurrently mostly AI | EO1: AIFrustration | EP1: AIExplain | EQ1: AIAgents | ER1: AIAgentChange | ES1: AIAgent_Uses | ET1: AgentUsesGeneral | EU1: AIAgentImpactSomewhat agree | EV1: AIAgentImpactNeutral | EW1: AIAgentImpactSomewhat disagree | EX1: AIAgentImpactStrongly agree | EY1: AIAgentImpactStrongly disagree | EZ1: AIAgentChallengesNeutral | FA1: AIAgentChallengesSomewhat disagree | FB1: AIAgentChallengesStrongly agree | FC1: AIAgentChallengesSomewhat agree | FD1: AIAgentChallengesStrongly disagree | FE1: AIAgentKnowledge | FF1: AIAgentKnowWrite | FG1: AIAgentOrchestration | FH1: AIAgentOrchWrite | FI1: AIAgentObserveSecure | FJ1: AIAgentObsWrite | FK1: AIAgentExternal | FL1: AIAgentExtWrite | FM1: AIHuman | FN1: AIOpen | FO1: ConvertedCompYearly | FP1: JobSat
A2: 9 | B2: I am a developer by profession | C2: 25-34 years old | D2: Bachelor’s degree (B.A., B.S., B.Eng., etc.) | E2: Employed | F2: Caring for dependents (children, elderly, etc.);Volunteering (regularly) | G2: 9 | H2: Yes, I am not new to coding but am learning new coding techniques or programming language | I2: Online Courses or Certification (includes all media types);Other online resources (e.g. standard search, forum, online community);Books / Physical media;Videos (not associated with specific online course or certification);Stack Overflow or Stack Exchange;Technical documentation (is generated for/by the tool or system);AI CodeGen tools or AI-enabled apps;Blogs or podcasts | J2: Yes, I learned how to use AI-enabled tools for my personal curiosity and/or hobbies | K2: Technical documentation (is generated for/by the tool or system);Videos (not associated with specific online course or certification);Other online resources (e.g. standard search, forum, online community);Blogs or podcasts | L2: 15 | M2: Data engineer | N2: 5,000 to 9,999 employees | O2: Individual contributor | P2: Remote | Q2: Yes, I influenced the purchase of a tool that more than five colleagues use but it is not a substantial addition to the tech stack | R2: Personal Project | S2: 5 | T2: 7 | U2: 13 | V2: 4 | W2: 9 | X2: 8 | Y2: 12 | Z2: 2 | AA2: 11 | AB2: 14 | AD2: 11 | AE2: 13 | AF2: 10 | AG2: 1 | AH2: 5 | AI2: 9 | AJ2: 7 | AK2: 8 | AL2: 2 | AM2: 15 | AO2: Banking/Financial Services | AP2: 1 | AQ2: 2 | AR2: 4 | AS2: 5 | AT2: 6 | AU2: 7 | AV2: 8 | AW2: 9 | AX2: 10 | AY2: 11 | AZ2: 12 | BA2: 13 | BB2: 14 | BC2: 15 | BD2: 3 | BF2: No | BG2: I have transitioned into a new career and/or industry voluntarily | BJ2: Ukraine | BK2: USD United States dollar | BL2: 70000 | BN2: Java;Python;Scala | BO2: Scala | BP2: Scala | BT2: Cassandra;Databricks SQL;DuckDB;Dynamodb;MariaDB;Microsoft SQL Server;MySQL;PostgreSQL;Snowflake;Amazon Redshift | BU2: Dynamodb;MySQL;PostgreSQL | BV2: Dynamodb;MySQL;PostgreSQL | BZ2: Amazon Web Services (AWS);Datadog;Docker;Microsoft Azure;Splunk | CA2: Amazon Web Services (AWS);Datadog;Microsoft Azure | CB2: Amazon Web Services (AWS);Datadog;Microsoft Azure | CF2: FastAPI;Spring Boot | CL2: IntelliJ IDEA;Notepad++;PyCharm;Visual Studio Code | DS2: 1 | DU2: 4 | DV2: 5 | DW2: 6 | DX2: 7 | DY2: 8 | DZ2: 9 | EA2: 11 | EB2: 15 | EF2: Yes, I use AI tools monthly or infrequently | EG2: Indifferent | EH2: Neither trust nor distrust | EI2: Neither good or bad at handling complex tasks | ES2: Software engineering;Data and analytics | FO2: 70000 | FP2: 8
A3: 17 | B3: I am not primarily a developer, but I write code sometimes as part of my work/studies | C3: 65 years or older | D3: Some college/university study without earning a degree | E3: Retired | F3: None of the above | G3: 20 | H3: No, I am not new to coding and did not learn new coding techniques or programming languages | J3: No, I didn't spend time learning in the past year | L3: 40 | M3: Financial analyst or engineer | R3: Personal Project | S3: 7 | T3: 12 | U3: 2 | V3: 11 | W3: 5 | X3: 10 | Y3: 6 | Z3: 9 | AA3: 3 | AB3: 14 | AC3: usefullness | AD3: 4 | AE3: 10 | AF3: 5 | AG3: 1 | AH3: 12 | AI3: 13 | AJ3: 3 | AK3: 2 | AL3: 11 | AM3: 15 | BI3: 1 | BJ3: Australia | BK3: AUD Australian dollar | BL3: 25000 | BM3: Yes | BQ3: MQL4 | BR3: MQL5 | BS3: No | BY3: No | CE3: No | CK3: No | CT3: None of these | CU3: Not listed | CV3: Windows | CW3: Windows | DA3: No | DB3: No | DH3: No | DN3: No | DO3: Less than once per month or monthly | DP3: I don't use Stack Overflow | DQ3: I have never participated in Q&A on Stack Overflow | DR3: Other (write in): | DS3: 11 | DU3: 5 | DV3: 2 | DW3: 7 | DX3: 8 | DY3: 4 | DZ3: 3 | EA3: 6 | EB3: 15 | EC3: I don't use stsck overflow | ED3: No, not at all | EE3: I don't use AI or AI-enabled tools | EF3: No, and I don't plan to | EG3: Very unfavorable | EH3: Highly distrust | EI3: I don't use AI tools for complex tasks / I don't know | EK3: Learning about a codebase;Project planning;Writing code;Documenting code;Debugging or fixing code;Testing code;Committing and reviewing code;Deployment and monitoring;Predictive analytics;Search for answers;Generating content or synthetic data;Creating or maintaining documentation;Learning new concepts or technologies;Other (write in): | EO3: I don’t use AI tools regularly | EP3: No | EQ3: No, and I don't plan to | ER3: No, but my development work has significantly changed due to non-AI factors | FB3: I am concerned about the accuracy of the information provided by AI agents.;Integrating AI agents with my existing tools and workflows can be difficult.;It takes significant time and effort to learn how to use AI agents effectively.;The cost of using certain AI agent platforms is a barrier.;I have concerns about the security and privacy of data when using AI agents.;My company's IT and/or InfoSec teams have strict rules that do not allow me to use AI agent tools or platforms | FM3: Other (please specify): | FN3: All the ones that INTELLIGENT programmers currently use | FO3: 16252
A4: 34 | B4: I am a developer by profession | C4: 45-54 years old | D4: Bachelor’s degree (B.A., B.S., B.Eng., etc.) | E4: Employed | F4: None of the above | G4: 24 | H4: Yes, I am not new to coding but am learning new coding techniques or programming language | I4: Stack Overflow or Stack Exchange;Technical documentation (is generated for/by the tool or system);AI CodeGen tools or AI-enabled apps | J4: No, I didn't spend time learning in the past year | L4: 26 | M4: Data engineer | N4: 5,000 to 9,999 employees | O4: Individual contributor | P4: Hybrid (some remote, leans heavy to in-person) | Q4: Yes, I influenced the purchase of a substantial addition to the tech stack | R4: Work | S4: 10 | T4: 5 | U4: 4 | V4: 7 | W4: 2 | X4: 11 | Y4: 8 | Z4: 3 | AA4: 1 | AB4: 14 | AD4: 12 | AE4: 2 | AF4: 5 | AG4: 1 | AH4: 9 | AI4: 8 | AJ4: 3 | AK4: 4 | AL4: 14 | AM4: 15 | AO4: Software Development | AP4: 3 | AQ4: 4 | AR4: 11 | AS4: 14 | AT4: 13 | AU4: 8 | AV4: 12 | AW4: 1 | AX4: 6 | AY4: 7 | AZ4: 2 | BA4: 9 | BB4: 10 | BC4: 15 | BD4: 5 | BF4: No | BG4: I have neither consider or transitioned into a new career or industry | BH4: 3 | BI4: 0 | BJ4: United States of America | BK4: USD United States dollar | BL4: 175000 | BM4: Yes | BN4: C#;Python;SQL | BS4: Yes | BT4: Microsoft SQL Server | BY4: Yes | BZ4: Amazon Web Services (AWS);Microsoft Azure;Terraform | CE4: Yes | CF4: ASP.NET;ASP.NET Core | CK4: Yes | CL4: Visual Studio;Visual Studio Code | CQ4: Amazon Bedrock | CV4: Windows | CW4: Windows;Windows Subsystem for Linux (WSL);Linux (non-WSL) | CX4: Azure Devops;Jira | DC4: Stack Overflow;Stack Exchange | DH4: No | DN4: Yes | DO4: A few times per week | DP4: Between 10 and 15 years | DQ4: A few times per month or weekly | DS4: 6 | DU4: 8 | DV4: 12 | DW4: 7 | DX4: 4 | DY4: 5 | DZ4: 2 | EA4: 10 | EB4: 15 | ED4: Yes, somewhat | EE4: Rarely, almost never | EF4: No, and I don't plan to | EG4: Indifferent | EH4: Neither trust nor distrust | EI4: Bad at handling complex tasks | EK4: Learning about a codebase;Project planning;Writing code;Documenting code;Debugging or fixing code;Testing code;Committing and reviewing code;Deployment and monitoring;Predictive analytics;Search for answers;Generating content or synthetic data;Creating or maintaining documentation;Learning new concepts or technologies;Other (write in): | EO4: I don’t use AI tools regularly | EP4: no | EQ4: No, and I don't plan to | ER4: Not at all or minimally | EZ4: I am concerned about the accuracy of the information provided by AI agents.;Integrating AI agents with my existing tools and workflows can be difficult.;It takes significant time and effort to learn how to use AI agents effectively.;The cost of using certain AI agent platforms is a barrier.;I have concerns about the security and privacy of data when using AI agents.;My company's IT and/or InfoSec teams have strict rules that do not allow me to use AI agent tools or platforms;Write in the most significant challenge if not listed above: | FN4: business logic | FO4: 175000 | FP4: 8
A5: 46 | B5: I am a developer by profession | C5: 45-54 years old | D5: Professional degree (JD, MD, Ph.D, Ed.D, etc.) | E5: Employed | F5: None of the above | G5: 20 | H5: No, I am not new to coding and did not learn new coding techniques or programming languages | J5: No, I learned something that was not related to AI or AI enablement as required for my job or to benefit my career | L5: 23 | M5: AI/ML engineer | N5: 20 to 99 employees | O5: Individual contributor | P5: Hybrid (some in-person, leans heavy to flexibility) | Q5: No | R5: Work | S5: 11 | T5: 2 | U5: 6 | V5: 10 | W5: 7 | X5: 3 | Y5: 12 | Z5: 5 | AA5: 4 | AB5: 14 | AD5: 13 | AE5: 3 | AF5: 6 | AG5: 5 | AH5: 1 | AI5: 4 | AJ5: 9 | AK5: 2 | AL5: 14 | AM5: 15 | AO5: Software Development | AP5: 5 | AQ5: 1 | AR5: 10 | AS5: 14 | AT5: 12 | AU5: 3 | AV5: 4 | AW5: 11 | AX5: 2 | AY5: 6 | AZ5: 7 | BA5: 13 | BB5: 9 | BC5: 15 | BD5: 8 | BF5: No | BG5: I have neither consider or transitioned into a new career or industry | BJ5: Hungary | BK5: HUF Hungarian forint | BL5: 28000000 | BM5: Yes | BN5: Java;MATLAB;OCaml;Python;Scala | BO5: OCaml;Python;Scala | BP5: OCaml;Python;Scala | BS5: Yes | BT5: PostgreSQL;SQLite | BU5: PostgreSQL;SQLite | BV5: PostgreSQL;SQLite | BY5: Yes | BZ5: Docker;Maven (build tool) | CA5: Docker;Poetry | CB5: Docker | CE5: Yes | CF5: FastAPI | CG5: FastAPI | CH5: FastAPI | CK5: Yes | CL5: IntelliJ IDEA;Jupyter Notebook/JupyterLab;Nano;PyCharm;Visual Studio Code | CM5: IntelliJ IDEA;Jupyter Notebook/JupyterLab;Nano;PyCharm;Visual Studio Code | CN5: IntelliJ IDEA;Jupyter Notebook/JupyterLab;Nano;PyCharm;Visual Studio Code | CQ5: Polars | CR5: Polars | CS5: Polars | CV5: Ubuntu | CW5: Ubuntu | CX5: GitHub;GitLab | CY5: GitHub;GitLab | CZ5: GitHub;GitLab | DC5: Stack Overflow;GitHub (public projects, not private repos);Slack (public channels, not work);YouTube;LinkedIn | DD5: Stack Overflow;GitHub (public projects, not private repos);Slack (public channels, not work);YouTube;LinkedIn | DE5: Stack Overflow;GitHub (public projects, not private repos);Slack (public channels, not work);YouTube;LinkedIn | DH5: No | DN5: Yes | DO5: Daily or almost daily | DP5: Between 10 and 15 years | DQ5: Infrequently, less than once per year | DR5: Job board | DS5: 1 | DU5: 2 | DV5: 8 | DW5: 13 | DX5: 9 | DY5: 14 | DZ5: 7 | EA5: 11 | EB5: 15 | ED5: Neutral | EE5: I don't use AI or AI-enabled tools | EF5: No, and I don't plan to | EG5: Very unfavorable | EH5: Highly distrust | EI5: Bad at handling complex tasks | EJ5: Learning about a codebase | EK5: Project planning;Writing code;Debugging or fixing code;Committing and reviewing code;Deployment and monitoring;Predictive analytics | EL5: Testing code;Generating content or synthetic data;Learning new concepts or technologies | EM5: Documenting code;Search for answers;Creating or maintaining documentation | EO5: AI solutions that are almost right, but not quite;Debugging AI-generated code is more time-consuming;I don’t use AI tools regularly | EP5: No. | EQ5: No, and I don't plan to | ER5: Not at all or minimally | EZ5: Integrating AI agents with my existing tools and workflows can be difficult.;The cost of using certain AI agent platforms is a barrier.;My company's IT and/or InfoSec teams have strict rules that do not allow me to use AI agent tools or platforms | FB5: I have concerns about the security and privacy of data when using AI agents. | FC5: I am concerned about the accuracy of the information provided by AI agents.;It takes significant time and effort to learn how to use AI agents effectively. | FM5: When I want to fully understand something;When I want to learn best practices | FO5: 80966 | FP5: 8
A6: 69 | B6: I am not primarily a developer, but I write code sometimes as part of my work/studies | C6: 45-54 years old | D6: Bachelor’s degree (B.A., B.S., B.Eng., etc.) | E6: Independent contractor, freelancer, or self-employed | F6: Caring for dependents (children, elderly, etc.);Engaged in paid work (20-29 hours per week) | G6: 31 | H6: Yes, I am not new to coding but am learning new coding techniques or programming language | I6: Online Courses or Certification (includes all media types);Other online resources (e.g. standard search, forum, online community);Books / Physical media;Videos (not associated with specific online course or certification);Technical documentation (is generated for/by the tool or system);School (i.e., University, College, etc) | J6: Yes, I learned how to use AI-enabled tools for my personal curiosity and/or hobbies | K6: Videos (not associated with specific online course or certification);Stack Overflow or Stack Exchange | L6: 20 | M6: Data engineer | N6: Just me - I am a freelancer, sole proprietor, etc. | O6: Individual contributor | P6: Hybrid (some remote, leans heavy to in-person) | Q6: Yes, I influenced the purchase of a tool that more than five colleagues use but it is not a substantial addition to the tech stack | R6: Work | AO6: Computer Systems Design and Services | BF6: No | BG6: I have strongly considered changing my career and/or the industry I work in | BH6: 15 | BI6: 15 | BJ6: France | BK6: EUR European Euro | BL6: 150000 | BM6: Yes | BN6: JavaScript;Python;R;SQL;TypeScript;VBA | BS6: Yes | BT6: MariaDB;Microsoft SQL Server;MySQL | BY6: Yes | BZ6: Docker;Kubernetes;Microsoft Azure;Podman;Terraform | CE6: No | CK6: Yes | CL6: Eclipse;Notepad++;Sublime Text;Visual Studio Code | CV6: Windows;Ubuntu;Windows Subsystem for Linux (WSL);Linux (non-WSL) | CW6: Windows | CX6: Azure Devops;Confluence;GitHub;Google Workspace;Jira | DC6: Stack Overflow;Discord;GitHub (public projects, not private repos);Slack (public channels, not work);YouTube;LinkedIn | DH6: No | DN6: Yes | DO6: A few times per month or weekly | DP6: Between 1 and 3 years | DQ6: I have never participated in Q&A on Stack Overflow | ED6: Yes, somewhat | EF6: Yes, I use AI tools monthly or infrequently | EG6: Indifferent | EH6: Somewhat trust | EI6: Bad at handling complex tasks | EK6: Project planning;Committing and reviewing code;Creating or maintaining documentation;Learning new concepts or technologies;Other (write in): | EL6: Learning about a codebase;Writing code;Documenting code;Debugging or fixing code;Testing code;Deployment and monitoring;Predictive analytics;Search for answers;Generating content or synthetic data | EO6: I don’t use AI tools regularly | EQ6: No, but I plan to | ER6: Not at all or minimally | EZ6: My company's IT and/or InfoSec teams have strict rules that do not allow me to use AI agent tools or platforms | FB6: It takes significant time and effort to learn how to use AI agents effectively.;The cost of using certain AI agent platforms is a barrier.;I have concerns about the security and privacy of data when using AI agents. | FC6: I am concerned about the accuracy of the information provided by AI agents.;Integrating AI agents with my existing tools and workflows can be difficult. | FM6: When I’m stuck and can’t explain the problem | FN6: Integration | FO6: 174022
A7: 86 | B7: I am a developer by profession | C7: 35-44 years old | D7: Master’s degree (M.A., M.S., M.Eng., MBA, etc.) | E7: Employed | F7: None of the above | G7: 15 | H7: Yes, I am not new to coding but am learning new coding techniques or programming language | I7: Other online resources (e.g. standard search, forum, online community);Stack Overflow or Stack Exchange;Technical documentation (is generated for/by the tool or system);Games or coding challenges | J7: Yes, I learned how to use AI-enabled tools for my personal curiosity and/or hobbies | K7: Videos (not associated with specific online course or certification);Other online resources (e.g. standard search, forum, online community);Colleague or on-the-job training;Stack Overflow or Stack Exchange | L7: 20 | M7: Developer, AI apps or physical AI | N7: 5,000 to 9,999 employees | O7: Individual contributor | P7: Remote | Q7: Yes, I influenced the purchase of a substantial addition to the tech stack | R7: Work | S7: 7 | T7: 1 | U7: 4 | V7: 11 | W7: 3 | X7: 2 | Y7: 9 | Z7: 5 | AA7: 6 | AB7: 13 | AD7: 10 | AE7: 3 | AF7: 2 | AG7: 5 | AH7: 4 | AI7: 7 | AJ7: 8 | AK7: 1 | AL7: 14 | AM7: 15 | AO7: Software Development | AP7: 4 | AQ7: 3 | AR7: 8 | AS7: 11 | AT7: 12 | AU7: 6 | AV7: 7 | AW7: 13 | AX7: 10 | AY7: 9 | AZ7: 1 | BA7: 14 | BB7: 5 | BC7: 15 | BD7: 2 | BF7: No | BG7: I have neither consider or transitioned into a new career or industry | BH7: 3 | BI7: 4 | BJ7: Italy | BK7: EUR European Euro | BL7: 120000 | BM7: Yes | BN7: C;C++;Python;Rust | BO7: Go | BQ7: CUDA | BR7: warp | BS7: No | BY7: Yes | BZ7: Amazon Web Services (AWS);Poetry | CA7: Amazon Web Services (AWS) | CB7: Amazon Web Services (AWS) | CE7: No | CK7: Yes | CL7: Claude Code;Vim;Visual Studio Code | CM7: Visual Studio Code | CN7: Visual Studio Code | CQ7: c++23 | CV7: Windows;MacOS;Ubuntu | CW7: Ubuntu | CX7: Confluence;GitHub;GitLab;Google Colab | CY7: GitHub;GitLab | CZ7: GitHub;GitLab | DC7: Stack Overflow;Discord | DD7: Stack Overflow | DE7: Stack Overflow | DH7: Yes | DI7: DeepSeek (R- Reasoning models);openAI Reasoning models;X Grok models | DJ7: DeepSeek (R- Reasoning models);openAI Reasoning models | DK7: DeepSeek (R- Reasoning models);openAI Reasoning models | DN7: Yes | DO7: A few times per week | DP7: Between 10 and 15 years | DQ7: Less than once per month or monthly | DR7: Long-form articles;Lists of recommendations (tools, frameworks, technologies, etc.);Direct messaging of users;Job board | DS7: 4 | DU7: 9 | DV7: 1 | DW7: 2 | DX7: 7 | DY7: 3 | DZ7: 11 | EA7: 13 | EB7: 15 | ED7: Yes, definitely | EE7: Rarely, almost never | EF7: Yes, I use AI tools daily | EG7: Very favorable | EH7: Somewhat trust | EI7: Bad at handling complex tasks | EJ7: Writing code;Debugging or fixing code;Testing code;Committing and reviewing code | EL7: Learning about a codebase | EM7: Project planning;Deployment and monitoring;Predictive analytics;Learning new concepts or technologies | EN7: Documenting code;Search for answers;Generating content or synthetic data;Creating or maintaining documentation | EO7: AI solutions that are almost right, but not quite;Debugging AI-generated code is more time-consuming | EP7: No. Higher level reasoning including factoring in business constraints, architecture nonsense, management decisions and a general 'feeling' of robustness or performance that I've developer over the years in professional work will probably not be replaced by AI in my lifetime. | EQ7: Yes, I use AI agents at work daily | ER7: Yes, somewhat | ES7: Software engineering;Robotics | ET7: Multi-platform search enablement;Vector databases for AI applications | EU7: AI agents have increased my productivity.;AI agents have accelerated my learning about new technologies or codebases.;AI agents have helped me solve complex problems more effectively.;AI agents have reduced the time spent on specific development tasks.;AI agents have improved collaboration within my team. | EV7: AI agents have improved the quality of my code. | EX7: AI agents have helped me automate repetitive tasks. | EZ7: I am concerned about the accuracy of the information provided by AI agents.;The cost of using certain AI agent platforms is a barrier. | FA7: Integrating AI agents with my existing tools and workflows can be difficult. | FD7: It takes significant time and effort to learn how to use AI agents effectively.;I have concerns about the security and privacy of data when using AI agents.;My company's IT and/or InfoSec teams have strict rules that do not allow me to use AI agent tools or platforms | FE7: Milvus | FG7: Ollama;LangChain | FK7: ChatGPT;Claude Code;GitHub Copilot;Google Gemini;Microsoft Copilot;Perplexity | FL7: codeium, windsurf | FM7: When I want to fully understand something;When I want to compare different solutions | FN7: architectural planning of a big software. That is not going to be replaced for a variety of reasons (some I wrote in the answer before) | FO7: 139218 | FP7: 7
A8: 96 | B8: I am a developer by profession | C8: 45-54 years old | D8: Professional degree (JD, MD, Ph.D, Ed.D, etc.) | E8: Employed | F8: None of the above | G8: 33 | H8: No, I am not new to coding and did not learn new coding techniques or programming languages | J8: No, I didn't spend time learning in the past year | L8: 42 | M8: Developer, AI apps or physical AI | N8: 1,000 to 4,999 employees | O8: Individual contributor | P8: Remote | Q8: No | R8: Work | S8: 11 | T8: 6 | U8: 5 | V8: 4 | W8: 10 | X8: 1 | Y8: 12 | Z8: 7 | AA8: 2 | AB8: 14 | AD8: 14 | AE8: 8 | AF8: 6 | AG8: 7 | AH8: 3 | AI8: 1 | AJ8: 5 | AK8: 13 | AL8: 9 | AM8: 15 | AO8: Manufacturing | AP8: 13 | AQ8: 1 | AR8: 10 | AS8: 11 | AT8: 4 | AU8: 6 | AV8: 5 | AW8: 8 | AX8: 7 | AY8: 14 | AZ8: 9 | BA8: 2 | BB8: 3 | BC8: 15 | BD8: 12 | BF8: No | BG8: I have somewhat considered changing my career and/or the industry I work in | BH8: 5 | BI8: 5 | BJ8: Belgium | BK8: EUR European Euro | BL8: 144000 | BM8: Yes | BN8: C;C++;Lua;Python;SQL | BO8: C++;Python;Rust | BP8: C++;Python | BQ8: VimScript | BR8: VimScript | BS8: Yes | BT8: Oracle;SQLite | BU8: MariaDB;MySQL;PostgreSQL;SQLite | BV8: SQLite | BY8: Yes | BZ8: Amazon Web Services (AWS);Docker;Kubernetes | CE8: No | CK8: No | CV8: Windows;Ubuntu;Windows Subsystem for Linux (WSL) | CW8: Windows;Windows Subsystem for Linux (WSL) | CX8: Azure Devops;Confluence;GitHub;GitLab;Jira;Markdown File;Stack Overflow for Teams | CY8: GitHub;Markdown File | CZ8: GitHub;Markdown File | DC8: Stack Overflow;Stack Exchange;GitHub (public projects, not private repos);LinkedIn | DD8: Stack Overflow;Stack Exchange;GitHub (public projects, not private repos) | DE8: Stack Overflow;Stack Exchange;GitHub (public projects, not private repos) | DH8: No | DN8: Yes | DO8: Multiple times per day | DP8: Between 5 and 10 years | DQ8: Daily or almost daily | DR8: Long-form articles;Lists of recommendations (tools, frameworks, technologies, etc.) | DS8: 13 | DU8: 8 | DV8: 9 | DW8: 11 | DX8: 1 | DY8: 4 | DZ8: 3 | EA8: 7 | EB8: 15 | ED8: Yes, definitely | EE8: I don't use AI or AI-enabled tools | EF8: No, and I don't plan to | EG8: Unfavorable | EH8: Somewhat distrust | EI8: Bad at handling complex tasks | EK8: Learning about a codebase;Project planning;Writing code;Documenting code;Debugging or fixing code;Testing code;Committing and reviewing code;Deployment and monitoring;Creating or maintaining documentation | EL8: Predictive analytics;Search for answers;Generating content or synthetic data;Learning new concepts or technologies | EO8: I don’t use AI tools regularly | EP8: No | EQ8: No, and I don't plan to | ER8: Not at all or minimally | FB8: I have concerns about the security and privacy of data when using AI agents.;My company's IT and/or InfoSec teams have strict rules that do not allow me to use AI agent tools or platforms | FC8: I am concerned about the accuracy of the information provided by AI agents.;Integrating AI agents with my existing tools and workflows can be difficult.;It takes significant time and effort to learn how to use AI agents effectively.;The cost of using certain AI agent platforms is a barrier. | FM8: When I don’t trust AI’s answers;When I want to fully understand something;When I have ethical or security concerns about code | FN8: Analysis of the problem. Creation of logic and algorhytm. | FO8: 167061 | FP8: 8
A9: 120 | B9: I am a developer by profession | C9: 25-34 years old | D9: Master’s degree (M.A., M.S., M.Eng., MBA, etc.) | E9: Employed | F9: None of the above | G9: 4 | H9: Yes, I am not new to coding but am learning new coding techniques or programming language | I9: Technical documentation (is generated for/by the tool or system);AI CodeGen tools or AI-enabled apps | J9: Yes, I learned how to use AI-enabled tools required for my job or to benefit my career | L9: 10 | M9: Data engineer | N9: 1,000 to 4,999 employees | O9: Individual contributor | P9: Hybrid (some in-person, leans heavy to flexibility) | Q9: No | R9: Personal Project | S9: 10 | T9: 12 | U9: 7 | V9: 4 | W9: 3 | X9: 11 | Y9: 8 | Z9: 5 | AA9: 13 | AB9: 14 | AD9: 9 | AE9: 11 | AF9: 4 | AG9: 13 | AH9: 12 | AI9: 6 | AJ9: 1 | AK9: 10 | AL9: 14 | AM9: 15 | AO9: Software Development | AP9: 3 | AQ9: 4 | AR9: 6 | AS9: 2 | AT9: 7 | AU9: 9 | AV9: 8 | AW9: 12 | AX9: 10 | AY9: 1 | AZ9: 14 | BA9: 11 | BB9: 13 | BC9: 15 | BD9: 5 | BF9: No | BG9: I have transitioned into a new career and/or industry voluntarily | BJ9: Spain | BK9: EUR European Euro | BL9: 36000 | BM9: Yes | BN9: HTML/CSS;JavaScript;PHP;Python;SQL;TypeScript | BO9: HTML/CSS;JavaScript;Python;SQL | BP9: HTML/CSS;JavaScript;Python;SQL | BS9: Yes | BT9: MySQL;Oracle;PostgreSQL;Clickhouse | BU9: MySQL;Oracle;PostgreSQL;Clickhouse | BV9: MySQL;Oracle;PostgreSQL;Clickhouse | BY9: Yes | BZ9: Amazon Web Services (AWS);Ansible;Docker | CA9: Docker | CB9: Docker | CE9: Yes | CF9: FastAPI;Flask;React | CG9: FastAPI;Flask | CH9: FastAPI;Flask | CK9: Yes | CL9: Visual Studio Code | CM9: Visual Studio Code | CN9: Visual Studio Code | CV9: Windows;Android | CW9: MacOS | CX9: Confluence;Jira | CY9: Confluence;Jira | CZ9: Confluence;Jira | DA9: Bitbucket | DB9: Bitbucket | DC9: Stack Overflow;LinkedIn;Medium | DD9: Stack Overflow;LinkedIn;Medium | DE9: Stack Overflow;LinkedIn;Medium | DH9: Yes | DI9: openAI GPT (chatbot models) | DJ9: openAI GPT (chatbot models) | DK9: openAI GPT (chatbot models) | DN9: No | DO9: Less than once every 2 - 3 months | DP9: Between 3 and 5 years | DQ9: I have never participated in Q&A on Stack Overflow | EF9: Yes, I use AI tools daily | EG9: Very favorable | EH9: Somewhat trust | EI9: Good, but not great at handling complex tasks | EJ9: Documenting code;Learning new concepts or technologies | EK9: Project planning;Debugging or fixing code;Testing code;Committing and reviewing code;Deployment and monitoring;Generating content or synthetic data;Other (write in): | EL9: Predictive analytics;Creating or maintaining documentation | EN9: Learning about a codebase;Writing code;Search for answers | EO9: AI solutions that are almost right, but not quite;I haven’t encountered any problems | EP9: Yes | EQ9: No, but I plan to | ER9: Yes, to a great extent | FA9: It takes significant time and effort to learn how to use AI agents effectively.;I have concerns about the security and privacy of data when using AI agents. | FC9: I am concerned about the accuracy of the information provided by AI agents. | FD9: Integrating AI agents with my existing tools and workflows can be difficult.;The cost of using certain AI agent platforms is a barrier.;My company's IT and/or InfoSec teams have strict rules that do not allow me to use AI agent tools or platforms | FM9: When I want to learn best practices;When I want to compare different solutions;When I have ethical or security concerns about code;When I need help fixing complex or unfamiliar code | FN9: Soft skills and business knowledge | FO9: 41765 | FP9: 8
A10: 139 | B10: I am a developer by profession | C10: 25-34 years old | D10: Master’s degree (M.A., M.S., M.Eng., MBA, etc.) | E10: Employed | F10: None of the above | G10: 1 | H10: No, I am not new to coding and did not learn new coding techniques or programming languages | J10: No, I didn't spend time learning in the past year | L10: 8 | M10: AI/ML engineer | N10: 5,000 to 9,999 employees | O10: Individual contributor | P10: Your choice (very flexible, you can come in when you want or just as needed) | Q10: No | R10: Work | AO10: Computer Systems Design and Services | BF10: No | BG10: I have neither consider or transitioned into a new career or industry | BJ10: Norway | BK10: NOK Norwegian krone | BL10: 668000 | BM10: Yes | BN10: Bash/Shell (all shells);Go;Java;JavaScript;Python;SQL | BO10: Bash/Shell (all shells);Go;Python;Swift | BP10: Bash/Shell (all shells);Go;Python | BS10: Yes | BT10: Databricks SQL;DuckDB;MongoDB;MySQL | BU10: DuckDB | BV10: DuckDB | BY10: Yes | BZ10: Amazon Web Services (AWS);Docker;Homebrew;Microsoft Azure;Pip;Poetry;Terraform | CA10: Amazon Web Services (AWS);Docker;Homebrew;Kubernetes;Pip;Poetry;Vercel | CB10: Amazon Web Services (AWS);Docker;Homebrew;Pip;Poetry | CE10: No | CK10: Yes | CL10: IntelliJ IDEA;Jupyter Notebook/JupyterLab;PyCharm;Visual Studio Code;Xcode;Zed | CM10: IntelliJ IDEA;PyCharm;Zed | CN10: IntelliJ IDEA;PyCharm;Zed | CQ10: Large Language Model;Amazon Bedrock;RAG | CR10: Polars;Large Language Model;RAG;Microsoft Fabric;Google Gemini | CS10: Large Language Model;RAG | CV10: MacOS;iOS | CW10: MacOS;iOS | CX10: Confluence;GitHub;Google Colab;Google Workspace;Jira;Markdown File;Notion;Obsidian | CY10: GitHub;Google Workspace | CZ10: GitHub;Google Workspace | DC10: Reddit;GitHub (public projects, not private repos);Bluesky;Kaggle;YouTube;Twitch;LinkedIn | DD10: Reddit;GitHub (public projects, not private repos);Bluesky;YouTube;Twitch | DE10: Reddit;GitHub (public projects, not private repos);Bluesky;YouTube;Twitch | DH10: Yes | DI10: Amazon Titan models;Anthropic: Claude Sonnet;Meta Llama (all models);openAI GPT (chatbot models) | DJ10: Gemini (Flash general purpose models);Gemini (Pro Reasoning models);Mistral AI models;openAI Image generating models;openAI Reasoning models | DN10: Yes | DO10: Less than once every 2 - 3 months | DP10: Between 5 and 10 years | DQ10: I have never participated in Q&A on Stack Overflow | ED10: No, not at all | EE10: Less than half of the time | EF10: Yes, I use AI tools daily | EG10: Favorable | EH10: Somewhat trust | EI10: Neither good or bad at handling complex tasks | EJ10: Documenting code;Search for answers;Creating or maintaining documentation;Learning new concepts or technologies | EK10: Learning about a codebase;Committing and reviewing code;Deployment and monitoring;Predictive analytics;Generating content or synthetic data;Other (write in): | EL10: Project planning;Writing code;Debugging or fixing code;Testing code | EO10: AI solutions that are almost right, but not quite;Debugging AI-generated code is more time-consuming;I’ve become less confident in my own problem-solving | EP10: No | EQ10: No, and I don't plan to | ER10: Yes, somewhat | FB10: I am concerned about the accuracy of the information provided by AI agents.;I have concerns about the security and privacy of data when using AI agents. | FC10: Integrating AI agents with my existing tools and workflows can be difficult.;The cost of using certain AI agent platforms is a barrier. | FD10: It takes significant time and effort to learn how to use AI agents effectively.;My company's IT and/or InfoSec teams have strict rules that do not allow me to use AI agent tools or platforms | FM10: When I don’t trust AI’s answers;When I want to fully understand something;When I want to learn best practices;When I have ethical or security concerns about code;When I’m stuck and can’t explain the problem;When I need help fixing complex or unfamiliar code;When I need quick help troubleshooting | FO10: 66017 | FP10: 8
A11: 181 | B11: I am not primarily a developer, but I write code sometimes as part of my work/studies | C11: 25-34 years old | D11: Professional degree (JD, MD, Ph.D, Ed.D, etc.) | E11: Employed | F11: None of the above | G11: 2 | H11: No, I am not new to coding and did not learn new coding techniques or programming languages | J11: No, I didn't spend time learning in the past year | L11: 10 | M11: Applied scientist | N11: 100 to 499 employees | O11: Individual contributor | P11: In-person | Q11: No | R11: Work | S11: 12 | T11: 9 | U11: 8 | V11: 11 | W11: 2 | X11: 10 | Y11: 1 | Z11: 7 | AA11: 4 | AB11: 14 | AD11: 14 | AE11: 3 | AF11: 10 | AG11: 8 | AH11: 7 | AI11: 11 | AJ11: 2 | AK11: 4 | AL11: 9 | AM11: 15 | AO11: Energy | BF11: No | BG11: I have somewhat considered changing my career and/or the industry I work in | BH11: 1 | BI11: 2 | BJ11: Iran, Islamic Republic of... | BK11: USD United States dollar | BL11: 6000 | BM11: Yes | BN11: MATLAB | BO11: Python | BS11: No | BY11: No | CE11: No | CK11: Yes | CL11: Notepad++;Visual Studio;Visual Studio Code | CM11: Visual Studio;Visual Studio Code;Zed | CN11: Visual Studio;Visual Studio Code | CV11: Windows;Android;Windows Subsystem for Linux (WSL) | CW11: Windows | DC11: Stack Overflow;GitHub (public projects, not private repos);Bluesky;X;YouTube;Medium | DD11: Stack Overflow;GitHub (public projects, not private repos);Bluesky;YouTube;Medium | DE11: Stack Overflow;GitHub (public projects, not private repos);Bluesky;YouTube;Medium | DH11: No | DN11: Yes | DO11: A few times per month or weekly | DP11: Between 10 and 15 years | DQ11: Infrequently, less than once per year | DR11: Long-form articles;Lists of recommendations (tools, frameworks, technologies, etc.);Chat (bot/AI) | ED11: Yes, definitely | EE11: Less than half of the time | EF11: Yes, I use AI tools daily | EG11: Very favorable | EH11: Somewhat trust | EI11: Good, but not great at handling complex tasks | EJ11: Writing code;Debugging or fixing code;Committing and reviewing code;Predictive analytics;Learning new concepts or technologies | EL11: Learning about a codebase;Project planning | EM11: Documenting code;Testing code;Deployment and monitoring;Generating content or synthetic data;Creating or maintaining documentation | EN11: Search for answers | EO11: I haven’t encountered any problems | EP11: no | EQ11: No, but I plan to | ER11: Yes, somewhat | FA11: I am concerned about the accuracy of the information provided by AI agents.;It takes significant time and effort to learn how to use AI agents effectively. | FB11: My company's IT and/or InfoSec teams have strict rules that do not allow me to use AI agent tools or platforms | FC11: The cost of using certain AI agent platforms is a barrier.;I have concerns about the security and privacy of data when using AI agents. | FD11: Integrating AI agents with my existing tools and workflows can be difficult. | FM11: I don’t think I’ll need help from people anymore | FN11: mathematical insight | FO11: 6000
A12: 224 | B12: I am not primarily a developer, but I write code sometimes as part of my work/studies | C12: 35-44 years old | D12: Master’s degree (M.A., M.S., M.Eng., MBA, etc.) | E12: Employed | F12: Caring for dependents (children, elderly, etc.) | G12: 20 | H12: Yes, I am not new to coding but am learning new coding techniques or programming language | I12: Other online resources (e.g. standard search, forum, online community);Stack Overflow or Stack Exchange;Technical documentation (is generated for/by the tool or system);Blogs or podcasts;Games or coding challenges | J12: No, I learned something that was not related to AI or AI enablement for my personal curiosity and/or hobbies | L12: 20 | M12: Data or business analyst | N12: 100 to 499 employees | O12: People manager | P12: Hybrid (some remote, leans heavy to in-person) | Q12: Yes, I influenced the purchase of a tool that more than five colleagues use but it is not a substantial addition to the tech stack | R12: Work | S12: 13 | T12: 4 | U12: 6 | V12: 10 | W12: 5 | X12: 1 | Y12: 3 | Z12: 7 | AA12: 2 | AB12: 14 | AD12: 14 | AE12: 5 | AF12: 7 | AG12: 9 | AH12: 3 | AI12: 6 | AJ12: 1 | AK12: 2 | AL12: 13 | AM12: 15 | AO12: Software Development | BF12: No | BG12: I have somewhat considered changing my career and/or the industry I work in | BH12: 5 | BI12: 3 | BJ12: Finland | BK12: EUR European Euro | BL12: 85000 | BM12: Yes | BN12: HTML/CSS;JavaScript;PHP;Python;R;SQL;TypeScript | BO12: Lua;PowerShell;Python;R;SQL;TypeScript | BP12: Python;R;SQL;TypeScript | BS12: Yes | BT12: DuckDB;MariaDB;MySQL;Redis;Snowflake;SQLite;Amazon Redshift | BU12: Databricks SQL;DuckDB;MariaDB;Snowflake;SQLite | BV12: DuckDB;MariaDB;Snowflake;SQLite | BY12: Yes | BZ12: APT;Cloudflare;Composer;Docker;npm;Pip;Vite | CA12: Bun | CD12: ruff, uv | CE12: Yes | CF12: Astro;Laravel;Node.js | CG12: Astro;FastAPI;Laravel | CH12: Astro;Laravel | CI12: Eleventy | CJ12: Eleventy | CK12: Yes | CL12: Nano;Visual Studio Code | CM12: Visual Studio Code | CN12: Visual Studio Code | CO12: DataGrip, micro | CV12: MacOS | CW12: Windows | CX12: Confluence;GitHub;GitLab;Jira;Markdown File;Miro;Obsidian;Wikis | CY12: GitLab;Markdown File;Obsidian;Trello | CZ12: GitLab;Markdown File;Obsidian | DC12: Stack Overflow;Discord;Reddit;GitHub (public projects, not private repos);Bluesky | DF12: lobste.rs | DH12: No | DN12: Yes | DO12: A few times per week | DP12: More than 15 years, or since Stack Overflow started in 2008 | DQ12: Infrequently, less than once per year | DR12: Long-form articles;Coding challenges;Logic games/puzzles | DS12: 1 | DU12: 5 | DV12: 13 | DW12: 10 | DX12: 2 | DY12: 12 | DZ12: 3 | EA12: 14 | EB12: 15 | ED12: Neutral | EE12: I don't use AI or AI-enabled tools | EF12: No, and I don't plan to | EG12: Very unfavorable | EH12: Somewhat distrust | EI12: I don't use AI tools for complex tasks / I don't know | EK12: Learning about a codebase;Project planning;Writing code;Documenting code;Debugging or fixing code;Testing code;Committing and reviewing code;Deployment and monitoring;Predictive analytics;Search for answers;Generating content or synthetic data;Creating or maintaining documentation;Learning new concepts or technologies | EO12: AI solutions that are almost right, but not quite;I don’t use AI tools regularly | EP12: Fuck no. | EQ12: No, and I don't plan to | ER12: No, but my development work has significantly changed due to non-AI factors | EZ12: Integrating AI agents with my existing tools and workflows can be difficult.;It takes significant time and effort to learn how to use AI agents effectively.;The cost of using certain AI agent platforms is a barrier. | FB12: I am concerned about the accuracy of the information provided by AI agents.;My company's IT and/or InfoSec teams have strict rules that do not allow me to use AI agent tools or platforms;Write in the most significant challenge if not listed above: | FC12: I have concerns about the security and privacy of data when using AI agents. | FM12: When I don’t trust AI’s answers;When I want to fully understand something;When I want to learn best practices;When I want to compare different solutions;When I have ethical or security concerns about code;When I’m stuck and can’t explain the problem;When I need help fixing complex or unfamiliar code;When I need quick help troubleshooting | FN12: Everything | FO12: 98612
A13: 237 | B13: I am not primarily a developer, but I write code sometimes as part of my work/studies | C13: 25-34 years old | D13: Bachelor’s degree (B.A., B.S., B.Eng., etc.) | E13: Independent contractor, freelancer, or self-employed | F13: Engaged in paid work (less than 10 hours per week) | G13: 9 | H13: No, I am not new to coding and did not learn new coding techniques or programming languages | J13: Yes, I learned how to use AI-enabled tools for my personal curiosity and/or hobbies | K13: AI CodeGen tools or AI-enabled apps;Other online resources (e.g. standard search, forum, online community);Books / Physical media | L13: 10 | M13: Data scientist | N13: Just me - I am a freelancer, sole proprietor, etc. | O13: Individual contributor | P13: Remote | Q13: Yes, I influenced the purchase of a substantial addition to the tech stack | R13: Work | S13: 4 | T13: 3 | U13: 1 | V13: 6 | W13: 10 | X13: 12 | Y13: 11 | Z13: 9 | AA13: 7 | AB13: 14 | AD13: 6 | AE13: 7 | AF13: 1 | AG13: 11 | AH13: 4 | AI13: 12 | AJ13: 13 | AK13: 8 | AL13: 5 | AM13: 15 | AO13: Software Development | BF13: No | BG13: I have transitioned into a new career and/or industry voluntarily | BH13: 10 | BI13: 10 | BJ13: Switzerland | BK13: CHF Swiss franc | BL13: 50000 | BM13: Yes | BN13: C++;HTML/CSS;JavaScript;Python;Rust | BS13: Yes | BT13: PostgreSQL | BY13: Yes | BZ13: Amazon Web Services (AWS);Cargo;Datadog;Docker;Vite;Webpack | CE13: Yes | CF13: React | CK13: Yes | CL13: IntelliJ IDEA;PyCharm;RustRover;WebStorm | CQ13: Polars;Large Language Model;Amazon Bedrock | CV13: Windows | CW13: Windows;Debian | CX13: Jira | DH13: No | DN13: Yes | DO13: Less than once every 2 - 3 months | DP13: Between 5 and 10 years | DQ13: Less than once every 2 - 3 months | DR13: Chat (bot/AI) | DS13: 14 | DU13: 2 | DV13: 7 | DW13: 4 | DX13: 6 | DY13: 9 | DZ13: 10 | EA13: 5 | EB13: 15 | EC13: It's a crazy amount of time to rank 15 answers, guys | ED13: No, not really | EE13: Rarely, almost never | EF13: Yes, I use AI tools daily | EG13: Very favorable | EH13: Highly trust | EI13: Very well at handling complex tasks | EL13: Deployment and monitoring;Generating content or synthetic data | EN13: Learning about a codebase;Project planning;Writing code;Documenting code;Debugging or fixing code;Testing code;Committing and reviewing code;Predictive analytics;Search for answers;Creating or maintaining documentation;Learning new concepts or technologies | EO13: AI solutions that are almost right, but not quite;I haven’t encountered any problems | EP13: Yes, of course | EQ13: No, but I plan to | ER13: Yes, to a great extent | EZ13: I have concerns about the security and privacy of data when using AI agents. | FC13: I am concerned about the accuracy of the information provided by AI agents. | FD13: Integrating AI agents with my existing tools and workflows can be difficult.;It takes significant time and effort to learn how to use AI agents effectively.;The cost of using certain AI agent platforms is a barrier.;My company's IT and/or InfoSec teams have strict rules that do not allow me to use AI agent tools or platforms;Write in the most significant challenge if not listed above: | FM13: When I don’t trust AI’s answers;When I want to fully understand something;When I want to learn best practices;When I want to compare different solutions;When I have ethical or security concerns about code | FN13: Being capable of writing code and understanding it deeply. Not only the syntax, but also how to parallelize code,... I don't think the skills/requirements from employees will change | FO13: 61996
A14: 243 | B14: I am a developer by profession | C14: 25-34 years old | D14: Master’s degree (M.A., M.S., M.Eng., MBA, etc.) | E14: Employed | F14: Engaged in paid work (20-29 hours per week) | G14: 6 | H14: Yes, I am not new to coding but am learning new coding techniques or programming language | I14: Other online resources (e.g. standard search, forum, online community);AI CodeGen tools or AI-enabled apps | J14: Yes, I learned how to use AI-enabled tools for my personal curiosity and/or hobbies | K14: Other online resources (e.g. standard search, forum, online community);Blogs or podcasts | L14: 10 | M14: Data engineer | N14: 20 to 99 employees | O14: Individual contributor | P14: Your choice (very flexible, you can come in when you want or just as needed) | Q14: No | R14: Work | S14: 13 | T14: 3 | U14: 2 | V14: 1 | W14: 4 | X14: 8 | Y14: 12 | Z14: 6 | AA14: 7 | AB14: 11 | AD14: 13 | AE14: 3 | AF14: 5 | AG14: 7 | AH14: 6 | AI14: 1 | AJ14: 8 | AK14: 9 | AL14: 14 | AM14: 11 | AO14: Software Development | BF14: No | BG14: I have neither consider or transitioned into a new career or industry | BH14: 5 | BI14: 5 | BJ14: United Kingdom of Great Britain and Northern Ireland | BK14: GBP Pound sterling | BL14: 67000 | BM14: Yes | BN14: Bash/Shell (all shells);C#;HTML/CSS;Java;JavaScript;PowerShell;Python;Rust;Scala;SQL | BO14: C#;Go;HTML/CSS;PowerShell;Python;SQL | BP14: C#;HTML/CSS;PowerShell;Python;SQL | BS14: Yes | BT14: DuckDB;Dynamodb;Microsoft SQL Server;MongoDB;MySQL;PostgreSQL;SQLite | BU14: DuckDB;PostgreSQL;SQLite | BV14: DuckDB;PostgreSQL;SQLite | BY14: Yes | BZ14: Amazon Web Services (AWS);Digital Ocean;Docker;Google Cloud;npm;Pip;Terraform;Yarn | CA14: Amazon Web Services (AWS);Pip;Terraform;Yarn | CB14: Amazon Web Services (AWS);Pip;Terraform;Yarn | CE14: Yes | CF14: Django;Express;Flask;Next.js;Node.js;React | CG14: Django;Express;Flask | CH14: Django;Express;Flask | CK14: Yes | CL14: Notepad++;Visual Studio Code | CM14: Notepad++;Visual Studio Code | CN14: Notepad++;Visual Studio Code | CQ14: Polars;Large Language Model;Amazon Bedrock;RAG;Google Gemini | CR14: Polars;Large Language Model;Amazon Bedrock;RAG;Google Gemini | CS14: Polars;Large Language Model;Amazon Bedrock;RAG;Google Gemini | CV14: Windows;Ubuntu;Android;Debian | CW14: MacOS;Windows Subsystem for Linux (WSL);iOS | CX14: Confluence;GitHub;Google Colab;Jira;Obsidian;Wikis | CY14: GitHub;Obsidian;Wikis | CZ14: GitHub;Obsidian;Wikis | DC14: Stack Overflow;Stack Exchange;Discord;Reddit;Hacker News;GitHub (public projects, not private repos);Slack (public channels, not work);X;YouTube;Twitch;LinkedIn;Substack;Medium | DD14: Hacker News;GitHub (public projects, not private repos);YouTube;Substack | DE14: Hacker News;GitHub (public projects, not private repos);YouTube;Substack | DH14: Yes | DI14: DeepSeek (V- General purpose models);Meta Llama (all models);Mistral AI models;openAI GPT (chatbot models);openAI Image generating models;openAI Reasoning models | DJ14: Mistral AI models;openAI GPT (chatbot models);openAI Image generating models;openAI Reasoning models | DK14: Mistral AI models;openAI GPT (chatbot models);openAI Image generating models;openAI Reasoning models | DN14: No | DO14: A few times per month or weekly | DP14: Between 5 and 10 years | DQ14: I have never participated in Q&A on Stack Overflow | ED14: No, not at all | EE14: Less than half of the time | EF14: Yes, I use AI tools daily | EG14: Very favorable | EH14: Highly distrust | EI14: Bad at handling complex tasks | EJ14: Search for answers;Generating content or synthetic data;Creating or maintaining documentation | EK14: Learning about a codebase;Testing code;Committing and reviewing code;Deployment and monitoring;Predictive analytics | EL14: Project planning;Debugging or fixing code | EM14: Writing code;Documenting code | EN14: Learning new concepts or technologies | EO14: AI solutions that are almost right, but not quite;Debugging AI-generated code is more time-consuming | EP14: Nope | EQ14: No, and I don't plan to | ER14: Yes, somewhat | EZ14: My company's IT and/or InfoSec teams have strict rules that do not allow me to use AI agent tools or platforms | FA14: Integrating AI agents with my existing tools and workflows can be difficult. | FB14: I am concerned about the accuracy of the information provided by AI agents.;The cost of using certain AI agent platforms is a barrier.;I have concerns about the security and privacy of data when using AI agents. | FD14: It takes significant time and effort to learn how to use AI agents effectively. | FM14: When I don’t trust AI’s answers;When I want to fully understand something;When I want to learn best practices;When I want to compare different solutions;When I have ethical or security concerns about code;When I’m stuck and can’t explain the problem;When I need help fixing complex or unfamiliar code | FN14: The main ones that we still use now and have done for the past several decades. | FO14: 91215
A15: 249 | B15: I code primarily as a hobby | C15: 25-34 years old | D15: Master’s degree (M.A., M.S., M.Eng., MBA, etc.) | E15: Employed | F15: Caring for dependents (children, elderly, etc.) | G15: 10 | H15: No, I am not new to coding and did not learn new coding techniques or programming languages | J15: Yes, I learned how to use AI-enabled tools required for my job or to benefit my career | K15: Online Courses or Certification (includes all media types);Stack Overflow or Stack Exchange;School (i.e., University, College, etc) | L15: 12 | M15: AI/ML engineer | N15: 5,000 to 9,999 employees | O15: People manager | P15: Hybrid (some remote, leans heavy to in-person) | Q15: Yes, I influenced the purchase of a substantial addition to the tech stack | R15: Work | S15: 3 | T15: 8 | U15: 11 | V15: 7 | W15: 2 | X15: 4 | Y15: 12 | Z15: 9 | AA15: 6 | AB15: 14 | AO15: Healthcare | BF15: No | BG15: I have transitioned into a new career and/or industry voluntarily | BH15: 15 | BI15: 4 | BJ15: Belgium | BK15: EUR European Euro | BL15: 130000 | BM15: Yes | BN15: Assembly;C#;Delphi;Erlang;Groovy;HTML/CSS;Java;JavaScript;Kotlin;Lisp;Lua;MATLAB;MicroPython;OCaml;Perl;PHP;PowerShell;SQL;Swift;TypeScript;VBA;Zig;Mojo | BO15: Ada;Bash/Shell (all shells);C;C++;COBOL;Dart;Elixir;F#;Fortran;GDScript;Go;Prolog;Python;R;Ruby;Rust;Scala;Visual Basic (.Net);Gleam | BS15: Yes | BT15: BigQuery;Cassandra;Cloud Firestore;Cosmos DB;Databricks SQL;Datomic;DuckDB;Dynamodb;Elasticsearch;Firebase Realtime Database;H2;IBM DB2;InfluxDB;MariaDB;Microsoft Access;Microsoft SQL Server;MongoDB;MySQL;Neo4J;Oracle;PostgreSQL;Redis;Snowflake;SQLite;Supabase;Clickhouse;Cockroachdb;Amazon Redshift;Pocketbase;Valkey | BY15: No | CE15: No | CK15: No | CQ15: c++23;Tailwind CSS 4;Polars;hostinger;Odoo;Large Language Model;SwiftData;Amazon Bedrock;Pydantic;RAG;Microsoft Fabric;Google Gemini;Shadcn/ui;Delphi 12+ Athens | CV15: Windows;MacOS;Ubuntu;Android;Windows Subsystem for Linux (WSL);iOS;Debian;Linux (non-WSL);Arch;iPadOS;Red Hat;Fedora;ChromeOS;Pop!_OS;NixOS | CX15: Airtable;Azure Devops | DH15: No | DN15: Yes | DO15: A few times per month or weekly | DP15: Less than one year | DQ15: A few times per month or weekly | DR15: Direct messaging of users | DS15: 3 | DU15: 13 | DV15: 5 | DW15: 10 | DX15: 6 | DY15: 11 | DZ15: 14 | EA15: 12 | EB15: 15 | ED15: Yes, somewhat | EE15: Rarely, almost never | EF15: Yes, I use AI tools daily | EG15: Very favorable | EH15: Highly trust | EI15: Very well at handling complex tasks | EN15: Learning about a codebase;Project planning;Writing code;Documenting code;Debugging or fixing code;Testing code;Committing and reviewing code;Deployment and monitoring;Predictive analytics;Search for answers;Generating content or synthetic data;Creating or maintaining documentation;Learning new concepts or technologies | EO15: AI solutions that are almost right, but not quite | EP15: yes | EQ15: Yes, I use AI agents at work daily | ER15: Yes, to a great extent | ES15: Software engineering;Business process automation;IT operations;Data and analytics;Customer service support;Robotics | ET15: Agent/multi-agent orchestration;Personalized agent creation | EX15: AI agents have increased my productivity.;AI agents have helped me automate repetitive tasks.;AI agents have improved the quality of my code.;AI agents have accelerated my learning about new technologies or codebases.;AI agents have helped me solve complex problems more effectively.;AI agents have reduced the time spent on specific development tasks.;AI agents have improved collaboration within my team.;Write in the most significant benefit if not listed above. | FB15: I am concerned about the accuracy of the information provided by AI agents.;Integrating AI agents with my existing tools and workflows can be difficult.;It takes significant time and effort to learn how to use AI agents effectively.;The cost of using certain AI agent platforms is a barrier.;I have concerns about the security and privacy of data when using AI agents.;My company's IT and/or InfoSec teams have strict rules that do not allow me to use AI agent tools or platforms;Write in the most significant challenge if not listed above: | FE15: Neo4j;ChromaDB;Weaviate | FG15: Vertex AI;IBM watsonx.ai;Amazon Bedrock Agents;Martian;phidata | FI15: Galileo;Honeycomb | FK15: AgentGPT;Bolt.new;Amazon Codewhisperer | FM15: When I want to compare different solutions;When I need help fixing complex or unfamiliar code | FN15: AI | FO15: 150819
A16: 251 | B16: I am a developer by profession | C16: 25-34 years old | D16: Some college/university study without earning a degree | E16: Employed | F16: None of the above | G16: 8 | H16: Yes, I am not new to coding but am learning new coding techniques or programming language | I16: Online Courses or Certification (includes all media types);Other online resources (e.g. standard search, forum, online community);Stack Overflow or Stack Exchange;Technical documentation (is generated for/by the tool or system) | J16: No, I learned something that was not related to AI or AI enablement as required for my job or to benefit my career | L16: 10 | M16: Data or business analyst | N16: 100 to 499 employees | O16: Individual contributor | P16: In-person | Q16: No | R16: Work | S16: 13 | T16: 7 | U16: 4 | V16: 6 | W16: 1 | X16: 8 | Y16: 9 | Z16: 3 | AA16: 2 | AB16: 14 | AD16: 14 | AE16: 6 | AF16: 7 | AG16: 4 | AH16: 5 | AI16: 2 | AJ16: 1 | AK16: 3 | AL16: 9 | AM16: 15 | AO16: Manufacturing | AP16: 2 | AQ16: 1 | AR16: 12 | AS16: 13 | AT16: 11 | AU16: 5 | AV16: 6 | AW16: 4 | AX16: 7 | AY16: 8 | AZ16: 3 | BA16: 9 | BB16: 10 | BC16: 15 | BD16: 14 | BF16: No | BG16: I have somewhat considered changing my career and/or the industry I work in | BH16: 5 | BI16: 0 | BJ16: United States of America | BK16: USD United States dollar | BL16: 60000 | BM16: Yes | BN16: Python;SQL;VBA | BO16: Python;R;SQL;VBA | BP16: Python;SQL;VBA | BQ16: M | BR16: M | BS16: Yes | BT16: Microsoft Access | BU16: PostgreSQL | BW16: Progress OpenEdge | BY16: Yes | BZ16: Microsoft Azure;Pip | CA16: Microsoft Azure;Pip | CB16: Microsoft Azure;Pip | CE16: No | CK16: No | CV16: Windows | CW16: Windows | CX16: Jira | DC16: Stack Overflow;Stack Exchange;Reddit | DD16: Stack Overflow;Stack Exchange | DE16: Stack Overflow;Stack Exchange | DH16: No | DN16: Yes | DO16: Daily or almost daily | DP16: Between 5 and 10 years | DQ16: A few times per month or weekly | DS16: 5 | DU16: 9 | DV16: 8 | DW16: 11 | DX16: 3 | DY16: 2 | DZ16: 1 | EA16: 12 | EB16: 15 | ED16: Neutral | EE16: Rarely, almost never | EF16: No, but I plan to soon | EG16: Indifferent | EH16: Somewhat distrust | EI16: I don't use AI tools for complex tasks / I don't know | EK16: Learning about a codebase;Project planning;Writing code;Debugging or fixing code;Testing code;Committing and reviewing code;Deployment and monitoring;Search for answers;Generating content or synthetic data | EL16: Documenting code;Predictive analytics;Creating or maintaining documentation;Learning new concepts or technologies | EO16: I don’t use AI tools regularly | EP16: No, it is not nor do I plan to use Vibe Coding | EQ16: No, but I plan to | ER16: Not at all or minimally | EZ16: Integrating AI agents with my existing tools and workflows can be difficult.;It takes significant time and effort to learn how to use AI agents effectively.;The cost of using certain AI agent platforms is a barrier. | FB16: I am concerned about the accuracy of the information provided by AI agents. | FC16: I have concerns about the security and privacy of data when using AI agents. | FD16: My company's IT and/or InfoSec teams have strict rules that do not allow me to use AI agent tools or platforms | FM16: When I don’t trust AI’s answers;When I want to fully understand something;When I want to learn best practices;When I have ethical or security concerns about code;When I need help fixing complex or unfamiliar code | FO16: 60000 | FP16: 6
A17: 262 | B17: I am not primarily a developer, but I write code sometimes as part of my work/studies | C17: 25-34 years old | D17: Master’s degree (M.A., M.S., M.Eng., MBA, etc.) | E17: Employed | F17: Caring for dependents (children, elderly, etc.) | G17: 10 | H17: No, I am not new to coding and did not learn new coding techniques or programming languages | J17: Yes, I learned how to use AI-enabled tools for my personal curiosity and/or hobbies | K17: Technical documentation (is generated for/by the tool or system);Online Courses or Certification (includes all media types);Blogs or podcasts;Stack Overflow or Stack Exchange | L17: 18 | M17: Applied scientist | N17: 1,000 to 4,999 employees | O17: Individual contributor | P17: Hybrid (some remote, leans heavy to in-person) | Q17: No | R17: Work | S17: 13 | T17: 7 | U17: 5 | V17: 8 | W17: 1 | X17: 9 | Y17: 11 | Z17: 4 | AA17: 2 | AB17: 14 | AD17: 9 | AE17: 6 | AF17: 13 | AG17: 3 | AH17: 2 | AI17: 4 | AJ17: 7 | AK17: 1 | AL17: 12 | AM17: 15 | AO17: Healthcare | BF17: I'm not sure | BG17: I have neither consider or transitioned into a new career or industry | BH17: 4 | BI17: 2 | BJ17: Sweden | BK17: EUR European Euro | BL17: 72000 | BM17: Yes | BN17: MATLAB;Python;R | BO17: GDScript;MATLAB;Python;R | BP17: MATLAB;Python;R | BS17: No | BY17: No | CE17: No | CK17: Yes | CP17: Copilot | CQ17: Google Gemini | CR17: Google Gemini | CS17: Google Gemini | CV17: Windows;Android | CW17: Windows | CX17: Confluence;GitHub;Google Colab;Miro | CY17: GitHub;Google Colab | CZ17: GitHub;Google Colab | DC17: Stack Overflow;Stack Exchange;Reddit;YouTube;LinkedIn | DD17: Stack Overflow;Stack Exchange;Reddit;YouTube;LinkedIn | DE17: Stack Overflow;Stack Exchange;Reddit;YouTube;LinkedIn | DH17: No | DN17: Yes | DO17: Daily or almost daily | DP17: Between 3 and 5 years | DQ17: A few times per month or weekly | DR17: Long-form articles | DS17: 4 | DU17: 14 | DV17: 1 | DW17: 7 | DX17: 9 | DY17: 5 | DZ17: 8 | EA17: 13 | EB17: 15 | ED17: Yes, definitely | EE17: Rarely, almost never | EF17: Yes, I use AI tools weekly | EG17: Favorable | EH17: Somewhat distrust | EI17: Bad at handling complex tasks | EJ17: Learning about a codebase;Writing code;Documenting code;Debugging or fixing code;Committing and reviewing code;Search for answers;Generating content or synthetic data;Creating or maintaining documentation;Learning new concepts or technologies | EK17: Project planning;Testing code;Deployment and monitoring;Predictive analytics | EO17: AI solutions that are almost right, but not quite | EP17: No, i use ai to generate code snippets that i review | EQ17: No, but I plan to | ER17: Yes, somewhat | FB17: I am concerned about the accuracy of the information provided by AI agents. | FC17: I have concerns about the security and privacy of data when using AI agents. | FD17: Integrating AI agents with my existing tools and workflows can be difficult.;It takes significant time and effort to learn how to use AI agents effectively.;The cost of using certain AI agent platforms is a barrier.;My company's IT and/or InfoSec teams have strict rules that do not allow me to use AI agent tools or platforms | FM17: When I don’t trust AI’s answers;When I have ethical or security concerns about code | FN17: The problems we now solve by writing code ourselves can be solved by having an AI that writes code. Code is a tool to an end: providing a service, learning new stuff about real world, making decisions. We use code (and will use AI in five years) to make decisions, but making decisions will ultimately be down to humans | FO17: 83531
A18: 316 | B18: I am not primarily a developer, but I write code sometimes as part of my work/studies | C18: 45-54 years old | D18: Bachelor’s degree (B.A., B.S., B.Eng., etc.) | E18: Not employed | F18: Caring for dependents (children, elderly, etc.);Attending school (part-time) | G18: 27 | H18: No, I am not new to coding and did not learn new coding techniques or programming languages | J18: Yes, I learned how to use AI-enabled tools required for my job or to benefit my career | K18: Videos (not associated with specific online course or certification);Other online resources (e.g. standard search, forum, online community);Online Courses or Certification (includes all media types);Games or coding challenges;Books / Physical media;School (i.e., University, College, etc) | L18: 42 | M18: Data or business analyst | R18: Work | S18: 10 | T18: 6 | U18: 4 | V18: 8 | W18: 3 | X18: 9 | Y18: 13 | Z18: 2 | AA18: 1 | AB18: 14 | AD18: 11 | AE18: 3 | AF18: 9 | AG18: 10 | AH18: 1 | AI18: 13 | AJ18: 2 | AK18: 5 | AL18: 7 | AM18: 15 | BF18: Yes | BG18: I have strongly considered changing my career and/or the industry I work in | BH18: 5 | BI18: 8 | BJ18: United States of America | BK18: USD United States dollar | BL18: 125000 | BM18: Yes | BN18: Python;R;SQL | BS18: Yes | BT18: BigQuery;Microsoft SQL Server | BU18: DuckDB;Snowflake | BY18: Yes | BZ18: Google Cloud | CA18: Amazon Web Services (AWS);Digital Ocean;Docker;Microsoft Azure | CE18: No | CK18: Yes | CL18: Jupyter Notebook/JupyterLab;PyCharm;Visual Studio Code | CM18: Cursor | CQ18: Microsoft Fabric;Google Gemini | CR18: Polars | CV18: MacOS;Ubuntu;Windows Subsystem for Linux (WSL);Linux (non-WSL);ChromeOS | CW18: Windows | CX18: GitHub;Google Colab;Google Workspace;Markdown File | DC18: Stack Overflow;Discord;Reddit;GitHub (public projects, not private repos);Slack (public channels, not work);Bluesky;Kaggle;YouTube;LinkedIn;Substack;Medium | DH18: No | DN18: Yes | DO18: A few times per month or weekly | DP18: Between 5 and 10 years | DQ18: I have never participated in Q&A on Stack Overflow | DR18: Videos;Coding challenges;Logic games/puzzles;Lists of recommendations (tools, frameworks, technologies, etc.) | ED18: No, not really | EE18: Rarely, almost never | EF18: Yes, I use AI tools daily | EG18: Very favorable | EH18: Somewhat trust | EI18: Good, but not great at handling complex tasks | EJ18: Learning about a codebase;Writing code;Documenting code;Search for answers;Creating or maintaining documentation;Learning new concepts or technologies | EK18: Generating content or synthetic data | EL18: Project planning;Debugging or fixing code;Testing code;Committing and reviewing code;Deployment and monitoring;Predictive analytics | EO18: AI solutions that are almost right, but not quite | EP18: No, definitely not. | EQ18: No, and I don't plan to | ER18: Yes, somewhat | EZ18: Integrating AI agents with my existing tools and workflows can be difficult.;The cost of using certain AI agent platforms is a barrier.;My company's IT and/or InfoSec teams have strict rules that do not allow me to use AI agent tools or platforms | FA18: It takes significant time and effort to learn how to use AI agents effectively. | FB18: I am concerned about the accuracy of the information provided by AI agents.;I have concerns about the security and privacy of data when using AI agents. | FM18: When I want to fully understand something;When I want to learn best practices;When I have ethical or security concerns about code;When I’m stuck and can’t explain the problem;When I need help fixing complex or unfamiliar code | FN18: Learning to effectively use AI tools. | FO18: 125000
A19: 325 | B19: I am a developer by profession | C19: 45-54 years old | D19: Master’s degree (M.A., M.S., M.Eng., MBA, etc.) | E19: Employed | F19: Volunteering (regularly) | G19: 28 | H19: Yes, I am not new to coding but am learning new coding techniques or programming language | I19: Other online resources (e.g. standard search, forum, online community);Stack Overflow or Stack Exchange;Technical documentation (is generated for/by the tool or system);AI CodeGen tools or AI-enabled apps;Colleague or on-the-job training | J19: Yes, I learned how to use AI-enabled tools required for my job or to benefit my career | K19: AI CodeGen tools or AI-enabled apps;Colleague or on-the-job training | L19: 29 | M19: Developer, AI apps or physical AI | N19: 5,000 to 9,999 employees | O19: Individual contributor | P19: Hybrid (some in-person, leans heavy to flexibility) | Q19: Yes, I endorsed a tool that was ultimately not purchased or used at my organization | R19: Work | AO19: Banking/Financial Services | BF19: No | BG19: I have neither consider or transitioned into a new career or industry | BH19: 4 | BI19: 3 | BJ19: Germany | BK19: EUR European Euro | BL19: 103000 | BM19: Yes | BN19: Bash/Shell (all shells);Groovy;Python;SQL | BO19: Bash/Shell (all shells);Python;SQL | BP19: Bash/Shell (all shells);Python;SQL | BS19: Yes | BT19: PostgreSQL;Redis;SQLite | BU19: PostgreSQL;Redis | BV19: PostgreSQL;Redis | BY19: Yes | BZ19: Docker;Homebrew;Kubernetes;Pip;Podman;Poetry;Prometheus | CA19: Docker;Homebrew;Kubernetes;Pip;Podman;Poetry;Prometheus | CB19: Docker;Homebrew;Kubernetes;Pip;Podman;Poetry;Prometheus | CE19: Yes | CF19: FastAPI | CG19: FastAPI | CH19: FastAPI | CK19: Yes | CL19: Jupyter Notebook/JupyterLab;Nano;Notepad++;PyCharm;Vim | CM19: Jupyter Notebook/JupyterLab;PyCharm;Vim | CN19: Jupyter Notebook/JupyterLab;PyCharm;Vim | CV19: Windows | CW19: MacOS;Ubuntu;iOS;Debian;Linux (non-WSL);Red Hat;Fedora | CX19: Confluence;Jira | DC19: Stack Overflow | DH19: Yes | DI19: openAI GPT (chatbot models);openAI Reasoning models;X Grok models | DJ19: openAI GPT (chatbot models);openAI Reasoning models;X Grok models | DK19: openAI GPT (chatbot models);openAI Reasoning models;X Grok models | DN19: Yes | DO19: Daily or almost daily | DP19: Between 5 and 10 years | DQ19: I have never participated in Q&A on Stack Overflow | DR19: Chat (bot/AI) | DS19: 2 | DU19: 9 | DV19: 8 | DW19: 13 | DX19: 3 | DY19: 1 | DZ19: 6 | EA19: 5 | EB19: 15 | ED19: Yes, somewhat | EE19: Less than half of the time | EF19: Yes, I use AI tools daily | EG19: Very favorable | EH19: Neither trust nor distrust | EI19: Neither good or bad at handling complex tasks | EJ19: Writing code;Documenting code;Testing code;Predictive analytics;Creating or maintaining documentation | EK19: Project planning;Deployment and monitoring | EL19: Learning about a codebase;Committing and reviewing code;Learning new concepts or technologies | EN19: Debugging or fixing code;Search for answers;Generating content or synthetic data | EO19: AI solutions that are almost right, but not quite;I’ve become less confident in my own problem-solving | EQ19: No, but I plan to | ER19: Not at all or minimally | EZ19: It takes significant time and effort to learn how to use AI agents effectively.;I have concerns about the security and privacy of data when using AI agents.;My company's IT and/or InfoSec teams have strict rules that do not allow me to use AI agent tools or platforms | FA19: The cost of using certain AI agent platforms is a barrier. | FC19: I am concerned about the accuracy of the information provided by AI agents.;Integrating AI agents with my existing tools and workflows can be difficult. | FM19: When I don’t trust AI’s answers;When I want to fully understand something;When I’m stuck and can’t explain the problem;When I need help fixing complex or unfamiliar code | FO19: 119495 | FP19: 6
A20: 338 | B20: I am not primarily a developer, but I write code sometimes as part of my work/studies | C20: 35-44 years old | D20: Professional degree (JD, MD, Ph.D, Ed.D, etc.) | E20: Employed | F20: Caring for dependents (children, elderly, etc.);Volunteering (regularly) | G20: 16 | H20: Yes, I am not new to coding but am learning new coding techniques or programming language | I20: Technical documentation (is generated for/by the tool or system);AI CodeGen tools or AI-enabled apps | J20: Yes, I learned how to use AI-enabled tools for my personal curiosity and/or hobbies | K20: AI CodeGen tools or AI-enabled apps;Technical documentation (is generated for/by the tool or system);Colleague or on-the-job training;Online Courses or Certification (includes all media types) | L20: 25 | M20: Applied scientist | N20: 1,000 to 4,999 employees | O20: People manager | P20: Hybrid (some remote, leans heavy to in-person) | Q20: Yes, I influenced the purchase of a tool that more than five colleagues use but it is not a substantial addition to the tech stack | R20: Work | S20: 12 | T20: 2 | U20: 5 | V20: 3 | W20: 4 | X20: 8 | Y20: 11 | Z20: 1 | AA20: 7 | AB20: 13 | AD20: 13 | AE20: 1 | AF20: 14 | AG20: 9 | AH20: 3 | AI20: 8 | AJ20: 2 | AK20: 10 | AL20: 15 | AM20: 4 | AN20: AI nonsense | AO20: Software Development | BF20: I'm not sure | BG20: I have neither consider or transitioned into a new career or industry | BH20: 2 | BI20: 5 | BJ20: Serbia | BK20: RSD Serbian dinar | BL20: 15000000 | BM20: Yes | BN20: Bash/Shell (all shells);C;HTML/CSS;Java;Kotlin;Python;Ruby;Rust;SQL | BO20: Bash/Shell (all shells);HTML/CSS;Python;Rust;SQL | BP20: Bash/Shell (all shells);HTML/CSS;Python;Rust;SQL | BS20: Yes | BT20: Elasticsearch;PostgreSQL;SQLite;Clickhouse | BU20: Elasticsearch;PostgreSQL;SQLite;Clickhouse | BV20: Elasticsearch;PostgreSQL;SQLite;Clickhouse | BW20: Athena | BY20: Yes | BZ20: Amazon Web Services (AWS);APT;Cargo;Cloudflare;Docker;Google Cloud;Kubernetes;Make;Maven (build tool);Netlify;npm;Pip;Podman;Poetry;Yandex Cloud | CA20: Cloudflare;Docker;Make;Maven (build tool);Netlify;Podman;Yandex Cloud | CB20: Cloudflare;Docker;Make;Maven (build tool);Netlify;Podman;Yandex Cloud | CE20: Yes | CF20: FastAPI;Next.js;Node.js;WordPress | CG20: FastAPI;Ruby on Rails | CH20: FastAPI | CI20: Jekyll | CJ20: Jekyll | CK20: Yes | CL20: Cursor;IntelliJ IDEA;Jupyter Notebook/JupyterLab;PhpStorm;PyCharm;Rider;RustRover;Sublime Text;Vim;Visual Studio Code;VSCodium;Zed | CM20: Cursor;IntelliJ IDEA;Jupyter Notebook/JupyterLab;PyCharm;RustRover;Sublime Text;Vim;Zed | CN20: Cursor;IntelliJ IDEA;Jupyter Notebook/JupyterLab;PyCharm;RustRover;Sublime Text;Vim;Zed | CQ20: Polars;Large Language Model;RAG;Google Gemini | CR20: Polars;Large Language Model;RAG;Google Gemini | CS20: Polars;Large Language Model;RAG;Google Gemini | CV20: MacOS;Linux (non-WSL) | CW20: MacOS;Ubuntu;Debian;Linux (non-WSL) | CX20: GitHub;Markdown File;Miro;Notion;Trello;YouTrack | CY20: GitHub;Markdown File;Miro;Trello | CZ20: GitHub;Markdown File;Miro;Trello | DC20: Reddit;Hacker News;GitHub (public projects, not private repos);Slack (public channels, not work);X;YouTube;LinkedIn;Substack;Medium | DD20: Reddit;Hacker News;GitHub (public projects, not private repos);X;YouTube;LinkedIn;Substack;Medium | DE20: Reddit;Hacker News;GitHub (public projects, not private repos);X;YouTube;LinkedIn;Substack;Medium | DH20: Yes | DI20: Alibaba Cloud Qwen models;Anthropic: Claude Sonnet;Gemini (Flash general purpose models);Gemini (Pro Reasoning models);Meta Llama (all models);Mistral AI models;openAI GPT (chatbot models);openAI Reasoning models | DJ20: Alibaba Cloud Qwen models;Anthropic: Claude Sonnet;Gemini (Flash general purpose models);Gemini (Pro Reasoning models);Meta Llama (all models);Mistral AI models;openAI GPT (chatbot models);openAI Reasoning models | DK20: Alibaba Cloud Qwen models;Anthropic: Claude Sonnet;Gemini (Flash general purpose models);Gemini (Pro Reasoning models);Meta Llama (all models);Mistral AI models;openAI GPT (chatbot models);openAI Reasoning models | DL20: Mellum | DM20: Mellum | DN20: No | DO20: Less than once per month or monthly | DP20: I don't use Stack Overflow | DQ20: I have never participated in Q&A on Stack Overflow | DR20: Direct messaging of users;Job board | DS20: 2 | DU20: 8 | DV20: 10 | DW20: 9 | DX20: 12 | DY20: 5 | DZ20: 4 | EA20: 7 | EB20: 15 | ED20: No, not at all | EE20: Rarely, almost never | EF20: Yes, I use AI tools daily | EG20: Very favorable | EH20: Somewhat trust | EI20: Very poor at handling complex tasks | EJ20: Documenting code;Predictive analytics;Creating or maintaining documentation;Learning new concepts or technologies | EK20: Learning about a codebase;Project planning;Deployment and monitoring | EL20: Debugging or fixing code;Committing and reviewing code | EM20: Testing code;Search for answers | EN20: Writing code;Generating content or synthetic data | EO20: AI solutions that are almost right, but not quite;Debugging AI-generated code is more time-consuming | EP20: kind of | EQ20: No, but I plan to | ER20: Yes, somewhat | EZ20: It takes significant time and effort to learn how to use AI agents effectively. | FB20: I am concerned about the accuracy of the information provided by AI agents.;Write in the most significant challenge if not listed above: | FC20: Integrating AI agents with my existing tools and workflows can be difficult.;The cost of using certain AI agent platforms is a barrier.;I have concerns about the security and privacy of data when using AI agents. | FD20: My company's IT and/or InfoSec teams have strict rules that do not allow me to use AI agent tools or platforms | FM20: When I don’t trust AI’s answers;When I want to fully understand something;When I want to learn best practices;When I want to compare different solutions;When I’m stuck and can’t explain the problem | FN20: being human | FO20: 148496
A21: 347 | B21: I am a developer by profession | C21: 35-44 years old | D21: Bachelor’s degree (B.A., B.S., B.Eng., etc.) | E21: Employed | F21: Caring for dependents (children, elderly, etc.) | G21: 15 | H21: Yes, I am not new to coding but am learning new coding techniques or programming language | I21: Online Courses or Certification (includes all media types);Other online resources (e.g. standard search, forum, online community);Books / Physical media | J21: Yes, I learned how to use AI-enabled tools required for my job or to benefit my career | K21: Videos (not associated with specific online course or certification);Online Courses or Certification (includes all media types);Blogs or podcasts;Books / Physical media | L21: 18 | M21: AI/ML engineer | N21: 5,000 to 9,999 employees | O21: People manager | P21: Hybrid (some in-person, leans heavy to flexibility) | Q21: Yes, I endorsed a tool that was open-source and is currently used by more than just myself but no purchase was made | R21: Work | S21: 12 | T21: 7 | U21: 3 | V21: 6 | W21: 1 | X21: 11 | Y21: 8 | Z21: 4 | AA21: 9 | AB21: 14 | AD21: 11 | AE21: 5 | AF21: 7 | AG21: 13 | AH21: 2 | AI21: 1 | AJ21: 3 | AK21: 10 | AL21: 12 | AM21: 15 | AO21: Other: | AP21: 5 | AQ21: 7 | AR21: 9 | AS21: 10 | AT21: 11 | AU21: 6 | AV21: 3 | AW21: 4 | AX21: 12 | AY21: 2 | AZ21: 1 | BA21: 13 | BB21: 14 | BC21: 15 | BD21: 8 | BF21: No | BG21: I have somewhat considered changing my career and/or the industry I work in | BH21: 1 | BI21: 1 | BJ21: South Africa | BK21: ZAR South African rand | BL21: 3800000 | BM21: Yes | BN21: Bash/Shell (all shells);C;Python;R;Rust;SQL | BO21: Bash/Shell (all shells);Rust;SQL | BP21: Bash/Shell (all shells);Rust;SQL | BS21: Yes | BT21: DuckDB;MySQL;PostgreSQL | BU21: DuckDB;MySQL;PostgreSQL | BV21: DuckDB;MySQL;PostgreSQL | BY21: Yes | BZ21: Cargo;Docker;Homebrew;Make;Ninja;npm;Pip;Poetry | CA21: Cargo;Docker;Homebrew;Make;Ninja;npm;Pip | CB21: Cargo;Docker;Homebrew;Make;Ninja;npm;Pip | CC21: uv | CD21: uv | CE21: No | CK21: Yes | CL21: Neovim;Visual Studio Code | CM21: Neovim | CN21: Neovim | CQ21: RAG | CR21: RAG | CS21: RAG | CV21: MacOS | CW21: MacOS | CX21: Confluence;GitHub;GitLab;Markdown File;Miro;Trello;Wikis | CY21: GitHub;Markdown File | CZ21: GitHub;Markdown File | DC21: Bluesky;YouTube;LinkedIn | DD21: Bluesky;YouTube;LinkedIn | DE21: Bluesky;YouTube;LinkedIn | DH21: No | DN21: Yes | DO21: Less than once per month or monthly | DP21: Between 5 and 10 years | DQ21: Infrequently, less than once per year | DR21: Long-form articles;Videos;Coding challenges | DS21: 1 | DU21: 11 | DV21: 12 | DW21: 5 | DX21: 10 | DY21: 7 | DZ21: 2 | EA21: 8 | EB21: 15 | ED21: No, not really | EE21: Less than half of the time | EF21: Yes, I use AI tools daily | EG21: Very favorable | EH21: Neither trust nor distrust | EI21: Good, but not great at handling complex tasks | EJ21: Learning about a codebase;Project planning;Documenting code;Debugging or fixing code;Testing code;Committing and reviewing code;Deployment and monitoring;Predictive analytics;Search for answers;Generating content or synthetic data;Creating or maintaining documentation;Learning new concepts or technologies | EK21: Writing code | EO21: Debugging AI-generated code is more time-consuming | EP21: Yes, but only for throw-away scripts | EQ21: Yes, I use AI agents at work daily | ER21: Yes, to a great extent | ES21: Business process automation;Decision intelligence;Data and analytics;Customer service support | ET21: Vector databases for AI applications;Integration with external agents and APIs | EU21: AI agents have increased my productivity.;AI agents have helped me automate repetitive tasks.;AI agents have improved the quality of my code.;AI agents have accelerated my learning about new technologies or codebases.;AI agents have helped me solve complex problems more effectively.;AI agents have reduced the time spent on specific development tasks. | EV21: AI agents have improved collaboration within my team. | FA21: It takes significant time and effort to learn how to use AI agents effectively.;The cost of using certain AI agent platforms is a barrier. | FB21: I have concerns about the security and privacy of data when using AI agents. | FC21: I am concerned about the accuracy of the information provided by AI agents.;Integrating AI agents with my existing tools and workflows can be difficult. | FD21: My company's IT and/or InfoSec teams have strict rules that do not allow me to use AI agent tools or platforms | FE21: pgvector | FG21: LangChain;LangGraph | FI21: LangSmith | FK21: ChatGPT;Perplexity | FM21: When I don’t trust AI’s answers;When I have ethical or security concerns about code;When I’m stuck and can’t explain the problem | FN21: judgement | FO21: 214240 | FP21: 10
A22: 364 | B22: I am a developer by profession | C22: 18-24 years old | D22: Bachelor’s degree (B.A., B.S., B.Eng., etc.) | E22: Employed | F22: Volunteering (regularly);Engaged in paid work (less than 10 hours per week) | G22: 3 | H22: Yes, I am not new to coding but am learning new coding techniques or programming language | I22: Technical documentation (is generated for/by the tool or system);Coding Bootcamp | J22: No, I learned something that was not related to AI or AI enablement as required for my job or to benefit my career | L22: 3 | M22: Data engineer | N22: 20 to 99 employees | O22: Individual contributor | P22: In-person | Q22: No | R22: Work | S22: 8 | T22: 5 | U22: 12 | V22: 9 | W22: 1 | X22: 11 | Y22: 7 | Z22: 6 | AA22: 2 | AB22: 14 | AD22: 12 | AE22: 3 | AF22: 14 | AG22: 2 | AH22: 8 | AI22: 11 | AJ22: 6 | AK22: 9 | AL22: 7 | AM22: 15 | AO22: Fintech | AP22: 6 | AQ22: 5 | AR22: 8 | AS22: 3 | AT22: 9 | AU22: 10 | AV22: 13 | AW22: 11 | AX22: 12 | AY22: 14 | AZ22: 1 | BA22: 4 | BB22: 7 | BC22: 15 | BD22: 2 | BF22: No | BG22: I have neither consider or transitioned into a new career or industry | BH22: 10 | BI22: 7 | BJ22: India | BK22: INR Indian rupee | BL22: 800000 | BM22: Yes | BN22: C++;Go;Python;Rust | BO22: C++;Go;Python;Rust | BP22: C++;Go;Python;Rust | BS22: Yes | BT22: DuckDB;Microsoft SQL Server;MongoDB;MySQL;Oracle;PostgreSQL;Redis;Clickhouse | BU22: MySQL;Oracle;PostgreSQL;Redis;Clickhouse;Cockroachdb | BV22: MySQL;Oracle;PostgreSQL;Redis;Clickhouse | BY22: No | CE22: Yes | CF22: Django;FastAPI;Flask | CG22: Django;FastAPI;Flask | CH22: Django;FastAPI;Flask | CK22: No | CV22: Windows;Ubuntu | CW22: Windows Subsystem for Linux (WSL);iOS | CX22: Azure Devops | CY22: Azure Devops;Google Workspace | CZ22: Azure Devops | DH22: Yes | DN22: Yes | DO22: Daily or almost daily | DP22: Between 3 and 5 years | DQ22: A few times per month or weekly | DR22: Coding challenges | DS22: 14 | DU22: 13 | DV22: 8 | DW22: 1 | DX22: 12 | DY22: 9 | DZ22: 5 | EA22: 3 | EB22: 15 | ED22: Yes, definitely | EE22: About half of the time | EF22: Yes, I use AI tools weekly | EG22: Favorable | EH22: Highly distrust | EI22: Bad at handling complex tasks | EJ22: Learning about a codebase;Debugging or fixing code;Search for answers;Creating or maintaining documentation | EK22: Writing code;Learning new concepts or technologies | EL22: Deployment and monitoring;Generating content or synthetic data | EM22: Committing and reviewing code | EN22: Project planning;Documenting code;Testing code;Predictive analytics | EO22: I don’t use AI tools regularly;I haven’t encountered any problems | EQ22: No, and I don't plan to | ER22: No, but my development work has significantly changed due to non-AI factors | EZ22: I am concerned about the accuracy of the information provided by AI agents.;Integrating AI agents with my existing tools and workflows can be difficult.;It takes significant time and effort to learn how to use AI agents effectively.;The cost of using certain AI agent platforms is a barrier.;I have concerns about the security and privacy of data when using AI agents.;My company's IT and/or InfoSec teams have strict rules that do not allow me to use AI agent tools or platforms;Write in the most significant challenge if not listed above: | FM22: When I don’t trust AI’s answers;When I want to compare different solutions | FN22: 190 | FO22: 9299 | FP22: 1
A23: 369 | B23: I used to be a developer by profession, but no longer am | C23: 55-64 years old | D23: Some college/university study without earning a degree | E23: Employed | F23: None of the above | G23: 40 | H23: No, I am not new to coding and did not learn new coding techniques or programming languages | J23: No, I learned something that was not related to AI or AI enablement for my personal curiosity and/or hobbies | L23: 40 | M23: Support engineer or analyst | N23: 10,000 or more employees | O23: Individual contributor | P23: Remote | Q23: Yes, I influenced the purchase of a substantial addition to the tech stack | R23: Work | S23: 8 | T23: 7 | U23: 6 | V23: 12 | W23: 1 | X23: 13 | Y23: 10 | Z23: 2 | AA23: 3 | AB23: 5 | AC23: US-based | AD23: 15 | AE23: 8 | AF23: 11 | AG23: 9 | AH23: 10 | AI23: 2 | AJ23: 1 | AK23: 7 | AL23: 4 | AM23: 6 | AN23: Non-US-based | AO23: Banking/Financial Services | BF23: No | BG23: I have neither consider or transitioned into a new career or industry | BH23: 20 | BI23: 4 | BJ23: United States of America | BK23: USD United States dollar | BL23: 162000 | BM23: Yes | BN23: Assembly;Bash/Shell (all shells);C;C#;Java;PowerShell;SQL | BO23: Assembly;C;C#;PowerShell | BP23: Assembly;C;C#;PowerShell | BS23: Yes | BT23: IBM DB2;Microsoft SQL Server;MongoDB;MySQL;Oracle;Redis;SQLite;Cockroachdb | BU23: Microsoft SQL Server;Redis | BV23: Microsoft SQL Server;Redis | BW23: Sybase | BY23: Yes | BZ23: Ansible;Kubernetes;Microsoft Azure;MSBuild;NuGet;Splunk | CA23: Microsoft Azure;MSBuild;NuGet;Splunk | CB23: Microsoft Azure;MSBuild;NuGet;Splunk | CE23: Yes | CF23: ASP.NET;ASP.NET Core;Blazor | CG23: ASP.NET Core;Blazor | CH23: ASP.NET Core;Blazor | CK23: Yes | CL23: Eclipse;Notepad++;Visual Studio | CM23: Notepad++;Visual Studio | CN23: Notepad++;Visual Studio | CV23: Windows;Android;Windows Subsystem for Linux (WSL);Debian | CW23: Windows;Linux (non-WSL);Red Hat | CX23: GitHub;Jira | CY23: GitHub | CZ23: GitHub | DC23: Stack Overflow;Stack Exchange;GitHub (public projects, not private repos);X;Substack | DD23: Stack Overflow;Stack Exchange;GitHub (public projects, not private repos);X;Substack | DE23: Stack Overflow;Stack Exchange;GitHub (public projects, not private repos);X;Substack | DH23: No | DN23: Yes | DO23: A few times per week | DP23: More than 15 years, or since Stack Overflow started in 2008 | DQ23: Less than once per month or monthly | DS23: 9 | DU23: 4 | DV23: 1 | DW23: 2 | DX23: 3 | DY23: 5 | DZ23: 6 | EA23: 13 | EB23: 15 | ED23: No, not really | EE23: Rarely, almost never | EF23: No, and I don't plan to | EG23: Very unfavorable | EH23: Somewhat distrust | EI23: Very poor at handling complex tasks | EJ23: Search for answers;Learning new concepts or technologies | EK23: Learning about a codebase;Project planning;Writing code;Documenting code;Debugging or fixing code;Testing code;Committing and reviewing code;Deployment and monitoring;Predictive analytics;Generating content or synthetic data;Creating or maintaining documentation | EN23: Other (write in): | EO23: AI solutions that are almost right, but not quite;I don’t use AI tools regularly;Other (write in): | EP23: lol no | EQ23: Yes, I use AI agents at work daily | ER23: Not at all or minimally | ES23: IT operations | ET23: Other specific task (write in): | EW23: AI agents have accelerated my learning about new technologies or codebases. | EY23: AI agents have increased my productivity.;AI agents have helped me automate repetitive tasks.;AI agents have improved the quality of my code.;AI agents have helped me solve complex problems more effectively.;AI agents have reduced the time spent on specific development tasks.;AI agents have improved collaboration within my team. | EZ23: It takes significant time and effort to learn how to use AI agents effectively. | FB23: I am concerned about the accuracy of the information provided by AI agents.;I have concerns about the security and privacy of data when using AI agents.;Write in the most significant challenge if not listed above: | FC23: Integrating AI agents with my existing tools and workflows can be difficult.;The cost of using certain AI agent platforms is a barrier.;My company's IT and/or InfoSec teams have strict rules that do not allow me to use AI agent tools or platforms | FE23: Redis | FJ23: Splunk ML, Dynatrace Davis | FK23: GitHub Copilot;OpenHands (formerly OpenDevin) | FL23: xAI Grok | FM23: When I don’t trust AI’s answers | FN23: Interaction with the business and understanding requirements. | FO23: 162000
A24: 412 | B24: I am not primarily a developer, but I write code sometimes as part of my work/studies | C24: 45-54 years old | D24: Master’s degree (M.A., M.S., M.Eng., MBA, etc.) | E24: Independent contractor, freelancer, or self-employed | F24: Caring for dependents (children, elderly, etc.);Volunteering (regularly) | G24: 33 | H24: No, I am not new to coding and did not learn new coding techniques or programming languages | J24: Yes, I learned how to use AI-enabled tools for my personal curiosity and/or hobbies | K24: AI CodeGen tools or AI-enabled apps;Technical documentation (is generated for/by the tool or system);Other online resources (e.g. standard search, forum, online community);Blogs or podcasts;Other (please specify):;Books / Physical media | L24: 35 | M24: Data scientist | Q24: Yes, I endorsed a tool that was open-source and is currently used by more than just myself but no purchase was made | R24: Work | S24: 14 | T24: 4 | U24: 5 | V24: 11 | W24: 8 | X24: 6 | Y24: 9 | Z24: 10 | AA24: 3 | AB24: 13 | AD24: 15 | AE24: 8 | AF24: 7 | AG24: 10 | AH24: 4 | AI24: 5 | AJ24: 3 | AK24: 9 | AL24: 1 | AM24: 14 | AO24: Software Development | BF24: No | BG24: I have neither consider or transitioned into a new career or industry | BH24: 10 | BI24: 5 | BJ24: Argentina | BK24: ARS Argentine peso | BL24: 84000000 | BM24: Yes | BN24: Bash/Shell (all shells);HTML/CSS;R;SQL | BO24: Bash/Shell (all shells);HTML/CSS;R;SQL | BP24: Bash/Shell (all shells);HTML/CSS;R;SQL | BS24: No | BY24: Yes | BZ24: Cloudflare;Google Cloud;Netlify | CA24: Netlify | CB24: Netlify | CC24: R-Universe, CRAN | CD24: R-Universe, CRAN | CE24: Yes | CI24: Hugo, Quarto | CJ24: Hugo, Quarto | CK24: Yes | CL24: Visual Studio Code | CO24: Positron, RStudio | CP24: Positron, RStudio | CQ24: Large Language Model | CR24: Large Language Model | CS24: Large Language Model | CT24: GitHub Copilot | CU24: GitHub Copilot | CV24: MacOS;iOS;iPadOS | CW24: Windows;MacOS;Android;iOS | CX24: Airtable;GitHub;GitLab;Markdown File | CY24: Airtable;GitHub;GitLab;Markdown File | CZ24: Airtable;GitHub;GitLab;Markdown File | DC24: GitHub (public projects, not private repos);Slack (public channels, not work);Bluesky;YouTube;LinkedIn;Company-sponsored forums | DD24: GitHub (public projects, not private repos);Slack (public channels, not work);Bluesky;YouTube;LinkedIn;Company-sponsored forums | DE24: GitHub (public projects, not private repos);Slack (public channels, not work);Bluesky;YouTube;LinkedIn;Company-sponsored forums | DF24: Mastodon, Instagram | DG24: Mastodon, Instagram | DH24: Yes | DI24: Anthropic: Claude Sonnet;openAI GPT (chatbot models) | DJ24: Anthropic: Claude Sonnet | DK24: Anthropic: Claude Sonnet | DN24: Yes | DO24: Less than once every 2 - 3 months | DP24: Between 3 and 5 years | DQ24: Infrequently, less than once per year | DR24: Other (write in): | DS24: 2 | DU24: 4 | DV24: 1 | DW24: 8 | DX24: 11 | DY24: 7 | DZ24: 5 | EA24: 10 | EB24: 15 | ED24: No, not at all | EE24: About half of the time | EF24: Yes, I use AI tools monthly or infrequently | EG24: Unfavorable | EH24: Highly distrust | EI24: Bad at handling complex tasks | EJ24: Testing code | EK24: Learning about a codebase;Project planning;Debugging or fixing code;Deployment and monitoring;Predictive analytics;Generating content or synthetic data;Learning new concepts or technologies | EL24: Writing code;Documenting code;Committing and reviewing code;Search for answers;Creating or maintaining documentation | EO24: AI solutions that are almost right, but not quite;Debugging AI-generated code is more time-consuming;I don’t use AI tools regularly | EP24: No | EQ24: No, but I plan to | ER24: No, but my development work has changed somewhat due to non-AI factors | FB24: I am concerned about the accuracy of the information provided by AI agents.;The cost of using certain AI agent platforms is a barrier.;I have concerns about the security and privacy of data when using AI agents.;Write in the most significant challenge if not listed above: | FC24: Integrating AI agents with my existing tools and workflows can be difficult.;It takes significant time and effort to learn how to use AI agents effectively.;My company's IT and/or InfoSec teams have strict rules that do not allow me to use AI agent tools or platforms | FM24: When I don’t trust AI’s answers;When I want to fully understand something;When I want to learn best practices;When I want to compare different solutions;When I have ethical or security concerns about code;When I’m stuck and can’t explain the problem;When I need help fixing complex or unfamiliar code;When I need quick help troubleshooting;Other (please specify):;I don’t think I’ll need help from people anymore | FN24: Read code to fix the AI code.
A25: Understand and discuss the implications of the software we create and how it affects people's lives." | B25: 71657.0
A26: 442 | B26: I am a developer by profession | C26: 25-34 years old | D26: Master’s degree (M.A., M.S., M.Eng., MBA, etc.) | E26: Employed | F26: None of the above | G26: 9 | H26: No, I am not new to coding and did not learn new coding techniques or programming languages | J26: Yes, I learned how to use AI-enabled tools for my personal curiosity and/or hobbies | K26: AI CodeGen tools or AI-enabled apps | L26: 12 | M26: Data scientist | N26: 10,000 or more employees | O26: People manager | P26: Hybrid (some remote, leans heavy to in-person) | Q26: No | R26: Work | S26: 7 | T26: 1 | U26: 2 | V26: 11 | W26: 6 | X26: 8 | Y26: 10 | Z26: 4 | AA26: 3 | AB26: 14 | AD26: 10 | AE26: 8 | AF26: 5 | AG26: 6 | AH26: 1 | AI26: 3 | AJ26: 2 | AK26: 7 | AL26: 13 | AM26: 15 | AO26: Software Development | AP26: 7 | AQ26: 2 | AR26: 6 | AS26: 14 | AT26: 12 | AU26: 11 | AV26: 13 | AW26: 9 | AX26: 8 | AY26: 10 | AZ26: 1 | BA26: 3 | BB26: 4 | BC26: 15 | BD26: 5 | BF26: No | BG26: I have neither consider or transitioned into a new career or industry | BH26: 6 | BI26: 6 | BJ26: United States of America | BK26: USD United States dollar | BL26: 330000 | BM26: Yes | BN26: Bash/Shell (all shells);C#;HTML/CSS;JavaScript;PowerShell;Python;R;SQL;TypeScript | BO26: Bash/Shell (all shells);C#;HTML/CSS;JavaScript;PowerShell;Python;SQL;TypeScript | BP26: Bash/Shell (all shells);C#;HTML/CSS;JavaScript;PowerShell;Python;SQL;TypeScript | BS26: Yes | BT26: Databricks SQL;PostgreSQL;Snowflake;SQLite | BU26: PostgreSQL;Snowflake;SQLite | BV26: PostgreSQL;Snowflake;SQLite | BY26: Yes | BZ26: Amazon Web Services (AWS);Docker;Firebase;Pip | CA26: Amazon Web Services (AWS);Docker;Firebase;Pip | CB26: Amazon Web Services (AWS);Docker;Firebase;Pip | CE26: Yes | CF26: Django;FastAPI;Flask;Next.js;Node.js;React | CG26: Django;FastAPI;Flask;Next.js;Node.js;React | CH26: Django;FastAPI;Flask;Next.js;Node.js;React | CK26: Yes | CL26: Jupyter Notebook/JupyterLab;Visual Studio Code | CM26: Jupyter Notebook/JupyterLab;Visual Studio Code | CN26: Jupyter Notebook/JupyterLab;Visual Studio Code | CQ26: Large Language Model;Amazon Bedrock;RAG | CR26: Large Language Model;Amazon Bedrock;RAG | CS26: Large Language Model;Amazon Bedrock;RAG | CV26: Windows;Ubuntu;Windows Subsystem for Linux (WSL) | CW26: MacOS | CX26: Confluence;GitHub;Google Workspace;Jira;Miro;Monday.com | CY26: GitHub;Google Workspace;Miro;Monday.com | CZ26: GitHub;Google Workspace;Miro;Monday.com | DC26: Stack Overflow;Reddit;GitHub (public projects, not private repos) | DD26: Stack Overflow;Reddit;GitHub (public projects, not private repos) | DE26: Stack Overflow;Reddit;GitHub (public projects, not private repos) | DH26: Yes | DI26: openAI GPT (chatbot models) | DJ26: openAI GPT (chatbot models) | DK26: openAI GPT (chatbot models) | DN26: Yes | DO26: A few times per week | DP26: Between 3 and 5 years | DQ26: I have never participated in Q&A on Stack Overflow | DR26: Lists of recommendations (tools, frameworks, technologies, etc.);Direct messaging of users;Job board | DS26: 7 | DU26: 13 | DV26: 11 | DW26: 14 | DX26: 6 | DY26: 9 | DZ26: 3 | EA26: 1 | EB26: 15 | ED26: Yes, somewhat | EE26: Less than half of the time | EF26: Yes, I use AI tools daily | EG26: Favorable | EH26: Somewhat trust | EI26: Good, but not great at handling complex tasks | EJ26: Writing code;Documenting code;Debugging or fixing code;Testing code;Committing and reviewing code;Search for answers;Creating or maintaining documentation;Learning new concepts or technologies | EN26: Learning about a codebase;Project planning;Deployment and monitoring;Predictive analytics;Generating content or synthetic data | EO26: AI solutions that are almost right, but not quite | EP26: Fuck no. | EQ26: No, but I plan to | ER26: Not at all or minimally | EZ26: My company's IT and/or InfoSec teams have strict rules that do not allow me to use AI agent tools or platforms | FB26: The cost of using certain AI agent platforms is a barrier. | FC26: I am concerned about the accuracy of the information provided by AI agents.;Integrating AI agents with my existing tools and workflows can be difficult.;It takes significant time and effort to learn how to use AI agents effectively.;I have concerns about the security and privacy of data when using AI agents. | FM26: When I don’t trust AI’s answers;When I want to fully understand something;When I need help fixing complex or unfamiliar code;When I need quick help troubleshooting | FN26: Same skills as today. | FO26: 330000 | FP26: 10
A27: 460 | B27: I am not primarily a developer, but I write code sometimes as part of my work/studies | C27: 45-54 years old | D27: Some college/university study without earning a degree | E27: Employed | F27: Volunteering (regularly);Engaged in paid work (less than 10 hours per week) | G27: 15 | H27: Yes, I am not new to coding but am learning new coding techniques or programming language | I27: Online Courses or Certification (includes all media types);Other online resources (e.g. standard search, forum, online community);Books / Physical media;Technical documentation (is generated for/by the tool or system) | J27: Yes, I learned how to use AI-enabled tools for my personal curiosity and/or hobbies | K27: Other online resources (e.g. standard search, forum, online community) | L27: 38 | M27: Data or business analyst | N27: 20 to 99 employees | O27: People manager | P27: Remote | Q27: Yes, I influenced the purchase of a substantial addition to the tech stack | R27: Work | S27: 13 | T27: 10 | U27: 6 | V27: 3 | W27: 8 | X27: 1 | Y27: 5 | Z27: 9 | AA27: 4 | AB27: 14 | AD27: 13 | AE27: 10 | AF27: 7 | AG27: 4 | AH27: 5 | AI27: 2 | AJ27: 1 | AK27: 6 | AL27: 3 | AM27: 15 | AO27: Software Development | BF27: No | BG27: I have transitioned into a new career and/or industry voluntarily | BH27: 10 | BI27: 4 | BJ27: Italy | BK27: EUR European Euro | BL27: 43000 | BM27: Yes | BN27: Assembly;Bash/Shell (all shells);Go;HTML/CSS;JavaScript;PHP;PowerShell;Python;Rust | BO27: Bash/Shell (all shells);Go;HTML/CSS;JavaScript;Python;Rust | BP27: Bash/Shell (all shells);Go;HTML/CSS;JavaScript;Python;Rust | BS27: No | BY27: Yes | BZ27: Amazon Web Services (AWS);Cargo;Chocolatey;Cloudflare;Composer;Digital Ocean;Docker;Google Cloud;Gradle;Kubernetes;npm;Pip;Yarn | CA27: Cargo;Chocolatey;Digital Ocean;Docker;npm;Pip;Yarn | CB27: Cargo;Chocolatey;Digital Ocean;Docker;npm;Pip;Yarn | CE27: Yes | CF27: Node.js;WordPress | CG27: Node.js | CH27: Node.js | CI27: Framework7, Neutralino.js | CJ27: Framework7, Neutralino.js | CK27: Yes | CL27: Android Studio;Claude Code;PyCharm;Sublime Text | CO27: Phoenix | CP27: Phoenix | CQ27: Odoo | CR27: Odoo | CS27: Odoo | CV27: Linux (non-WSL) | CW27: Windows;Linux (non-WSL) | DA27: Odoo | DB27: Odoo | DC27: Discord;Hacker News;GitHub (public projects, not private repos);LinkedIn | DD27: Discord;Hacker News;GitHub (public projects, not private repos);LinkedIn | DE27: Discord;Hacker News;GitHub (public projects, not private repos);LinkedIn | DH27: Yes | DN27: Yes | DO27: Infrequently, less than once per year | DP27: Between 10 and 15 years | DQ27: A few times per month or weekly | DS27: 5 | DU27: 4 | DV27: 9 | DW27: 1 | DX27: 2 | DY27: 6 | DZ27: 12 | EA27: 8 | EB27: 15 | ED27: Neutral | EE27: Rarely, almost never | EF27: Yes, I use AI tools weekly | EG27: Favorable | EH27: Highly distrust | EI27: Neither good or bad at handling complex tasks | EJ27: Generating content or synthetic data | EK27: Learning about a codebase;Committing and reviewing code;Deployment and monitoring;Search for answers;Learning new concepts or technologies | EL27: Project planning;Writing code;Documenting code;Debugging or fixing code;Testing code;Predictive analytics;Creating or maintaining documentation | EO27: Debugging AI-generated code is more time-consuming | EP27: No. | EQ27: Yes, I use AI agents at work weekly | ER27: Yes, somewhat | ES27: Data and analytics;Customer service support;Marketing | ET27: Language processing;Personalized agent creation | EU27: AI agents have helped me automate repetitive tasks.;AI agents have improved collaboration within my team. | EV27: AI agents have increased my productivity.;AI agents have reduced the time spent on specific development tasks. | EW27: AI agents have helped me solve complex problems more effectively. | EY27: AI agents have improved the quality of my code.;AI agents have accelerated my learning about new technologies or codebases. | FB27: I am concerned about the accuracy of the information provided by AI agents.;I have concerns about the security and privacy of data when using AI agents.;Write in the most significant challenge if not listed above: | FC27: Integrating AI agents with my existing tools and workflows can be difficult.;It takes significant time and effort to learn how to use AI agents effectively.;The cost of using certain AI agent platforms is a barrier.;My company's IT and/or InfoSec teams have strict rules that do not allow me to use AI agent tools or platforms | FE27: GitHub MCP Server | FG27: Ollama;Zapier | FI27: Honeycomb | FK27: ChatGPT;Claude Code;GitHub Copilot;Google Gemini | FM27: When I don’t trust AI’s answers;When I have ethical or security concerns about code | FN27: Soft skill, ethics, general understanding of complex problems, math, physics, English, other languages | FO27: 49886
A28: 465 | B28: I am not primarily a developer, but I write code sometimes as part of my work/studies | C28: 35-44 years old | D28: Master’s degree (M.A., M.S., M.Eng., MBA, etc.) | E28: Employed | F28: Engaged in paid work (less than 10 hours per week) | G28: 20 | H28: Yes, I am not new to coding but am learning new coding techniques or programming language | I28: Technical documentation (is generated for/by the tool or system);AI CodeGen tools or AI-enabled apps;Blogs or podcasts | J28: Yes, I learned how to use AI-enabled tools required for my job or to benefit my career | K28: Other (please specify): | L28: 9 | M28: Data or business analyst | N28: 100 to 499 employees | O28: Individual contributor | P28: Remote | Q28: No | R28: Work | S28: 13 | T28: 8 | U28: 6 | V28: 10 | W28: 1 | X28: 7 | Y28: 3 | Z28: 11 | AA28: 9 | AB28: 14 | AD28: 7 | AE28: 9 | AF28: 6 | AG28: 11 | AH28: 12 | AI28: 3 | AJ28: 5 | AK28: 4 | AL28: 2 | AM28: 15 | AO28: Internet, Telecomm or Information Services | BF28: Yes | BG28: I have strongly considered changing my career and/or the industry I work in | BH28: 7 | BJ28: United States of America | BK28: USD United States dollar | BL28: 160000 | BM28: Yes | BN28: R;SQL | BO28: Python;R;SQL | BP28: R;SQL | BS28: Yes | BT28: BigQuery;Databricks SQL;Snowflake | BU28: Databricks SQL;Elasticsearch;Redis;Snowflake | BV28: Databricks SQL;Snowflake | BZ28: Cloudflare;Docker;Google Cloud | CA28: Cloudflare;Docker;Google Cloud;Splunk;Vercel | CB28: Cloudflare;Docker;Google Cloud | CF28: Svelte | CG28: Svelte | CH28: Svelte | CK28: Yes | CL28: Cursor;Visual Studio Code | CM28: Cursor;Lovable.dev;Visual Studio Code;Windsurf | CN28: Cursor;Visual Studio Code | CQ28: Large Language Model;Google Gemini | CR28: Large Language Model;RAG;Google Gemini | CS28: Large Language Model;Google Gemini | CV28: MacOS | CW28: MacOS | CX28: GitHub;Google Colab;Google Workspace;Markdown File;Monday.com;Obsidian;Stack Overflow for Teams | CY28: GitHub;Google Colab;Google Workspace;Markdown File;Notion;Obsidian | CZ28: GitHub;Google Colab;Google Workspace;Markdown File;Obsidian | DC28: Stack Overflow;Reddit;GitHub (public projects, not private repos);Slack (public channels, not work);Kaggle;YouTube | DD28: Stack Overflow;Discord;Reddit;Dev.to;GitHub (public projects, not private repos);Slack (public channels, not work);Kaggle;YouTube;Substack | DE28: Stack Overflow;Reddit;GitHub (public projects, not private repos);Slack (public channels, not work);Kaggle;YouTube | DH28: Yes | DI28: Amazon Titan models;Gemini (Flash general purpose models);Gemini (Pro Reasoning models);openAI GPT (chatbot models);openAI Image generating models | DJ28: Amazon Titan models;DeepSeek (R- Reasoning models);DeepSeek (V- General purpose models);Gemini (Flash general purpose models);Mistral AI models;openAI GPT (chatbot models);openAI Image generating models;openAI Reasoning models | DK28: Amazon Titan models;Gemini (Flash general purpose models);openAI GPT (chatbot models);openAI Image generating models | DN28: Yes | DO28: A few times per month or weekly | DP28: Between 5 and 10 years | DQ28: Infrequently, less than once per year | DR28: Message Boards;Videos;Lists of recommendations (tools, frameworks, technologies, etc.);Day-in-the-life profiles/interviews with experts | DS28: 2 | DU28: 12 | DV28: 1 | DW28: 8 | DX28: 13 | DY28: 6 | DZ28: 3 | EA28: 14 | EB28: 15 | ED28: No, not really | EE28: About half of the time | EF28: Yes, I use AI tools daily | EG28: Favorable | EH28: Neither trust nor distrust | EI28: Neither good or bad at handling complex tasks | EJ28: Project planning;Writing code;Search for answers;Learning new concepts or technologies | EK28: Testing code;Deployment and monitoring;Generating content or synthetic data;Creating or maintaining documentation | EL28: Learning about a codebase;Documenting code;Committing and reviewing code;Predictive analytics | EN28: Debugging or fixing code | EO28: Debugging AI-generated code is more time-consuming;I’ve become less confident in my own problem-solving | EQ28: No, but I plan to | ER28: Not at all or minimally | EZ28: Integrating AI agents with my existing tools and workflows can be difficult.;It takes significant time and effort to learn how to use AI agents effectively.;The cost of using certain AI agent platforms is a barrier. | FC28: I am concerned about the accuracy of the information provided by AI agents.;I have concerns about the security and privacy of data when using AI agents.;My company's IT and/or InfoSec teams have strict rules that do not allow me to use AI agent tools or platforms | FM28: When I want to learn best practices;When I want to compare different solutions | FO28: 160000
A29: 490 | B29: I am a developer by profession | C29: 45-54 years old | D29: Bachelor’s degree (B.A., B.S., B.Eng., etc.) | E29: Independent contractor, freelancer, or self-employed | G29: 31 | H29: Yes, I am not new to coding but am learning new coding techniques or programming language | I29: Online Courses or Certification (includes all media types);Other online resources (e.g. standard search, forum, online community);Books / Physical media;Videos (not associated with specific online course or certification);Stack Overflow or Stack Exchange;Technical documentation (is generated for/by the tool or system);AI CodeGen tools or AI-enabled apps;Blogs or podcasts;School (i.e., University, College, etc) | J29: Yes, I learned how to use AI-enabled tools required for my job or to benefit my career | K29: AI CodeGen tools or AI-enabled apps;Technical documentation (is generated for/by the tool or system);Videos (not associated with specific online course or certification);Other online resources (e.g. standard search, forum, online community);Blogs or podcasts;Books / Physical media;School (i.e., University, College, etc) | L29: 31 | M29: AI/ML engineer | Q29: Yes, I influenced the purchase of a tool that more than five colleagues use but it is not a substantial addition to the tech stack | R29: Work | S29: 2 | T29: 3 | U29: 1 | V29: 10 | W29: 4 | X29: 13 | Y29: 12 | Z29: 11 | AA29: 5 | AB29: 14 | AD29: 7 | AE29: 3 | AF29: 8 | AG29: 6 | AH29: 5 | AI29: 1 | AJ29: 10 | AK29: 13 | AL29: 11 | AM29: 15 | AO29: Software Development | AP29: 1 | AQ29: 7 | AR29: 8 | AS29: 12 | AT29: 14 | AU29: 6 | AV29: 3 | AW29: 9 | AX29: 5 | AY29: 4 | AZ29: 2 | BA29: 10 | BB29: 11 | BC29: 15 | BD29: 13 | BF29: I'm not sure | BG29: I have somewhat considered changing my career and/or the industry I work in | BH29: 15 | BI29: 10 | BJ29: Hungary | BK29: EUR European Euro | BL29: 65000 | BM29: Yes | BN29: Bash/Shell (all shells);C#;HTML/CSS;JavaScript;PowerShell;Python;SQL;TypeScript | BO29: F#;Go;MATLAB;R | BS29: Yes | BT29: Microsoft SQL Server;MongoDB;SQLite | BY29: Yes | BZ29: Chocolatey;Docker;Google Cloud;Make;Microsoft Azure;MSBuild;npm;NuGet;Pip;Webpack | CA29: Amazon Web Services (AWS) | CE29: Yes | CF29: Angular;AngularJS;ASP.NET Core;FastAPI;Flask;jQuery;Node.js | CG29: Express;Laravel;React;Ruby on Rails;Vue.js | CK29: Yes | CL29: Jupyter Notebook/JupyterLab;Notepad++;PyCharm;Visual Studio;Visual Studio Code | CQ29: Large Language Model;RAG;Google Gemini | CR29: Tailwind CSS 4 | CV29: Windows;Android;Windows Subsystem for Linux (WSL) | CW29: Windows;Ubuntu;Android;Windows Subsystem for Linux (WSL);iOS | CX29: Azure Devops;Clickup;GitHub;Google Colab;Markdown File | DC29: Stack Overflow;Stack Exchange;Reddit;GitHub (public projects, not private repos);Kaggle;YouTube;LinkedIn;Substack;Medium | DH29: Yes | DI29: Anthropic: Claude Sonnet;DeepSeek (R- Reasoning models);DeepSeek (V- General purpose models);Gemini (Flash general purpose models);Meta Llama (all models);Microsoft Phi-4 models;Mistral AI models;openAI GPT (chatbot models);openAI Reasoning models;Perplexity Sonar models | DN29: Yes | DO29: A few times per week | DP29: Between 10 and 15 years | DQ29: Infrequently, less than once per year | DS29: 5 | DU29: 6 | DV29: 10 | DW29: 1 | DX29: 12 | DY29: 11 | DZ29: 2 | EA29: 14 | EB29: 15 | ED29: Yes, somewhat | EE29: Rarely, almost never | EF29: Yes, I use AI tools daily | EG29: Very favorable | EH29: Somewhat trust | EI29: Neither good or bad at handling complex tasks | EJ29: Writing code;Debugging or fixing code;Generating content or synthetic data | EK29: Deployment and monitoring | EM29: Project planning;Documenting code;Testing code;Committing and reviewing code;Creating or maintaining documentation | EN29: Learning about a codebase;Predictive analytics;Search for answers;Learning new concepts or technologies | EO29: AI solutions that are almost right, but not quite;I’ve become less confident in my own problem-solving | EP29: I have tried it, but I do not use it in my professional work. | EQ29: No, but I plan to | ER29: Yes, somewhat | EZ29: Integrating AI agents with my existing tools and workflows can be difficult.;It takes significant time and effort to learn how to use AI agents effectively. | FB29: The cost of using certain AI agent platforms is a barrier.;I have concerns about the security and privacy of data when using AI agents. | FC29: I am concerned about the accuracy of the information provided by AI agents. | FD29: My company's IT and/or InfoSec teams have strict rules that do not allow me to use AI agent tools or platforms | FM29: When I want to compare different solutions;When I have ethical or security concerns about code | FN29: Understanding how AI works, ability to develop and not only use AI tools. Data science skills are also key in my view. | FO29: 75410 | FP29: 9
A30: 501 | B30: I am a developer by profession | C30: 25-34 years old | D30: Bachelor’s degree (B.A., B.S., B.Eng., etc.) | E30: Employed | F30: Attending school (part-time) | G30: 4 | H30: Yes, I am not new to coding but am learning new coding techniques or programming language | I30: Online Courses or Certification (includes all media types);Books / Physical media;Videos (not associated with specific online course or certification) | J30: No, I learned something that was not related to AI or AI enablement for my personal curiosity and/or hobbies | L30: 8 | M30: Applied scientist | N30: 100 to 499 employees | O30: Individual contributor | P30: Remote | Q30: No | AO30: Energy | AP30: 12 | AQ30: 13 | AR30: 10 | AS30: 9 | AT30: 14 | AU30: 5 | AV30: 4 | AW30: 7 | AX30: 8 | AY30: 6 | AZ30: 1 | BA30: 2 | BB30: 3 | BC30: 15 | BD30: 11 | BF30: No | BG30: I have somewhat considered changing my career and/or the industry I work in | BH30: 3 | BJ30: Brazil | BK30: BRL Brazilian real | BL30: 98000 | BM30: Yes | BN30: C++;Python | BO30: Python;Rust | BP30: Python | BS30: No | BY30: No | CE30: No | CK30: No | CV30: Ubuntu;Android | CW30: Windows;Windows Subsystem for Linux (WSL) | CX30: GitHub;Jira;Markdown File | CY30: GitHub;Jira;Markdown File | CZ30: GitHub;Jira;Markdown File | DC30: LinkedIn | DH30: No | DN30: Yes | DO30: Less than once per month or monthly | DP30: Between 5 and 10 years | DQ30: Infrequently, less than once per year | ED30: No, not at all | EE30: Rarely, almost never | EF30: Yes, I use AI tools weekly | EG30: Favorable | EH30: Neither trust nor distrust | EI30: Neither good or bad at handling complex tasks | EJ30: Search for answers | EK30: Learning about a codebase;Project planning;Debugging or fixing code;Deployment and monitoring;Predictive analytics;Generating content or synthetic data | EL30: Documenting code;Testing code;Committing and reviewing code;Creating or maintaining documentation | EM30: Writing code;Learning new concepts or technologies | EO30: AI solutions that are almost right, but not quite;I haven’t encountered any problems | EQ30: No, and I don't plan to | ER30: Not at all or minimally | EZ30: It takes significant time and effort to learn how to use AI agents effectively.;My company's IT and/or InfoSec teams have strict rules that do not allow me to use AI agent tools or platforms | FB30: I have concerns about the security and privacy of data when using AI agents. | FC30: I am concerned about the accuracy of the information provided by AI agents.;Integrating AI agents with my existing tools and workflows can be difficult.;The cost of using certain AI agent platforms is a barrier. | FM30: When I don’t trust AI’s answers;When I want to fully understand something;When I want to learn best practices;When I have ethical or security concerns about code;When I need help fixing complex or unfamiliar code | FO30: 17840 | FP30: 4
A31: 512 | B31: I am a developer by profession | C31: 45-54 years old | D31: Master’s degree (M.A., M.S., M.Eng., MBA, etc.) | E31: Employed | F31: Engaged in paid work (less than 10 hours per week) | G31: 20 | H31: Yes, I am not new to coding but am learning new coding techniques or programming language | I31: Online Courses or Certification (includes all media types);Other online resources (e.g. standard search, forum, online community);Videos (not associated with specific online course or certification);AI CodeGen tools or AI-enabled apps | J31: Yes, I learned how to use AI-enabled tools for my personal curiosity and/or hobbies | K31: AI CodeGen tools or AI-enabled apps;Videos (not associated with specific online course or certification);Stack Overflow or Stack Exchange | L31: 24 | M31: Data or business analyst | N31: 5,000 to 9,999 employees | O31: Individual contributor | P31: Your choice (very flexible, you can come in when you want or just as needed) | Q31: No | R31: Work | S31: 13 | T31: 1 | U31: 2 | V31: 11 | W31: 4 | X31: 10 | Y31: 5 | Z31: 3 | AA31: 9 | AB31: 14 | AO31: Energy | BF31: I'm not sure | BG31: I have somewhat considered changing my career and/or the industry I work in | BI31: 10 | BJ31: United States of America | BK31: USD United States dollar | BL31: 200000 | BM31: Yes | BN31: Bash/Shell (all shells);HTML/CSS;Java;JavaScript;PHP;PowerShell;Python;R;SQL | BO31: TypeScript | BQ31: Julia | BS31: Yes | BT31: BigQuery;Dynamodb;MariaDB;Microsoft Access;Microsoft SQL Server;MongoDB;MySQL;SQLite | BU31: Databricks SQL;Elasticsearch;Firebase Realtime Database;PostgreSQL;Redis;Snowflake;Amazon Redshift | BW31: Amazon Aurora | BY31: Yes | BZ31: Amazon Web Services (AWS);Ansible;APT;Composer;Docker;Heroku;npm;Pip | CA31: Firebase;Google Cloud;Kubernetes;Microsoft Azure;Splunk;Terraform;Webpack | CE31: Yes | CF31: Django;Express;Flask;jQuery;Node.js;Vue.js;WordPress | CG31: Drupal;Laravel;React | CK31: Yes | CL31: Jupyter Notebook/JupyterLab;Nano;Notepad++;PyCharm;Sublime Text;Visual Studio Code | CV31: Ubuntu;Android;Windows Subsystem for Linux (WSL);Linux (non-WSL) | CW31: Windows;Ubuntu;Windows Subsystem for Linux (WSL) | CX31: GitHub;Trello | CY31: Jira | DC31: LinkedIn | DD31: YouTube;LinkedIn | DE31: LinkedIn | DH31: Yes | DI31: openAI GPT (chatbot models);openAI Image generating models | DN31: Yes | DO31: Less than once per month or monthly | DP31: More than 15 years, or since Stack Overflow started in 2008 | DQ31: Infrequently, less than once per year | ED31: No, not really | EE31: Rarely, almost never | EF31: Yes, I use AI tools daily | EG31: Favorable | EH31: Somewhat trust | EI31: Good, but not great at handling complex tasks | EJ31: Project planning;Writing code;Documenting code;Debugging or fixing code;Committing and reviewing code;Creating or maintaining documentation | EL31: Testing code;Deployment and monitoring | EM31: Generating content or synthetic data | EN31: Learning about a codebase;Predictive analytics;Search for answers;Learning new concepts or technologies | EO31: AI solutions that are almost right, but not quite | EP31: Yes. I regularly ask AI to to code modules or solutions and then I review and implement and then have a discussion with it to debug and tweak. | EQ31: Yes, I use AI agents at work daily | ER31: Yes, to a great extent | ES31: Software engineering;Business process automation;IT operations;Data and analytics | ET31: Integration with external agents and APIs | EU31: AI agents have increased my productivity.;AI agents have helped me automate repetitive tasks.;AI agents have improved the quality of my code. | EV31: AI agents have improved collaboration within my team. | EX31: AI agents have accelerated my learning about new technologies or codebases.;AI agents have helped me solve complex problems more effectively.;AI agents have reduced the time spent on specific development tasks. | FA31: Integrating AI agents with my existing tools and workflows can be difficult.;The cost of using certain AI agent platforms is a barrier. | FC31: I am concerned about the accuracy of the information provided by AI agents.;It takes significant time and effort to learn how to use AI agents effectively.;I have concerns about the security and privacy of data when using AI agents.;My company's IT and/or InfoSec teams have strict rules that do not allow me to use AI agent tools or platforms | FM31: When I don’t trust AI’s answers;When I have ethical or security concerns about code;When I’m stuck and can’t explain the problem | FN31: Business logic analysis and planning, database design, and complex UI development and design. | FO31: 200000 | FP31: 7
A32: 514 | B32: I am a developer by profession | C32: 45-54 years old | D32: Master’s degree (M.A., M.S., M.Eng., MBA, etc.) | E32: Employed | F32: None of the above | G32: 30 | H32: No, I am not new to coding and did not learn new coding techniques or programming languages | J32: No, I didn't spend time learning in the past year | L32: 35 | M32: AI/ML engineer | N32: 10,000 or more employees | O32: Individual contributor | P32: Your choice (very flexible, you can come in when you want or just as needed) | Q32: Yes, I endorsed a tool that was open-source and is currently used by more than just myself but no purchase was made | R32: Work | S32: 13 | T32: 4 | U32: 3 | V32: 12 | W32: 1 | X32: 5 | Y32: 9 | Z32: 6 | AA32: 10 | AB32: 14 | AO32: Energy | AP32: 1 | AQ32: 4 | AR32: 10 | AS32: 11 | AT32: 12 | AU32: 5 | AV32: 3 | AW32: 2 | AX32: 13 | AY32: 6 | AZ32: 8 | BA32: 14 | BB32: 9 | BC32: 15 | BD32: 7 | BF32: No | BG32: I have neither consider or transitioned into a new career or industry | BH32: 2 | BJ32: Brazil | BK32: BRL Brazilian real | BL32: 80000 | BM32: Yes | BN32: Bash/Shell (all shells);HTML/CSS;Java;JavaScript;Python | BO32: Rust | BS32: No | BY32: Yes | BZ32: Amazon Web Services (AWS);Cargo;Docker;Homebrew;Kubernetes;Make;Pip | CA32: Podman | CC32: Apptainer | CE32: No | CK32: Yes | CL32: Jupyter Notebook/JupyterLab;Nano;Sublime Text;Visual Studio Code | CM32: Neovim;Vim;VSCodium | CV32: MacOS | CW32: MacOS;Ubuntu;Red Hat | CX32: GitLab;Jira;Markdown File;Obsidian | CY32: Stack Overflow for Teams | DC32: Stack Overflow;Stack Exchange;Hacker News;GitHub (public projects, not private repos) | DH32: No | DN32: Yes | DO32: Daily or almost daily | DP32: More than 15 years, or since Stack Overflow started in 2008 | DQ32: Infrequently, less than once per year | DR32: Long-form articles | DS32: 12 | DU32: 8 | DV32: 1 | DW32: 4 | DX32: 9 | DY32: 6 | DZ32: 7 | EA32: 13 | EB32: 15 | ED32: Neutral | EE32: I don't use AI or AI-enabled tools | EF32: No, and I don't plan to | EG32: Unfavorable | EH32: Somewhat distrust | EI32: I don't use AI tools for complex tasks / I don't know | EK32: Writing code;Documenting code;Committing and reviewing code;Deployment and monitoring;Predictive analytics;Search for answers;Creating or maintaining documentation;Other (write in): | EO32: AI solutions that are almost right, but not quite;Debugging AI-generated code is more time-consuming;I don’t use AI tools regularly;I’ve become less confident in my own problem-solving | EP32: No | EQ32: No, and I don't plan to | ER32: Not at all or minimally | EZ32: Integrating AI agents with my existing tools and workflows can be difficult.;The cost of using certain AI agent platforms is a barrier.;My company's IT and/or InfoSec teams have strict rules that do not allow me to use AI agent tools or platforms | FB32: I have concerns about the security and privacy of data when using AI agents. | FC32: I am concerned about the accuracy of the information provided by AI agents.;It takes significant time and effort to learn how to use AI agents effectively. | FM32: When I don’t trust AI’s answers;When I want to fully understand something;When I want to learn best practices | FO32: 14563 | FP32: 5
A33: 517 | B33: I am not primarily a developer, but I write code sometimes as part of my work/studies | C33: 35-44 years old | D33: Master’s degree (M.A., M.S., M.Eng., MBA, etc.) | E33: Employed | F33: Caring for dependents (children, elderly, etc.) | G33: 18 | H33: Yes, I am not new to coding but am learning new coding techniques or programming language | I33: Online Courses or Certification (includes all media types);Other online resources (e.g. standard search, forum, online community);Stack Overflow or Stack Exchange;Colleague or on-the-job training | J33: No, I learned something that was not related to AI or AI enablement for my personal curiosity and/or hobbies | L33: 16 | M33: Financial analyst or engineer | N33: 1,000 to 4,999 employees | O33: Individual contributor | P33: Hybrid (some remote, leans heavy to in-person) | Q33: No | R33: Personal Project | S33: 9 | T33: 1 | U33: 2 | V33: 6 | W33: 8 | X33: 3 | Y33: 12 | Z33: 5 | AA33: 10 | AB33: 14 | AD33: 14 | AE33: 1 | AF33: 12 | AG33: 9 | AH33: 11 | AI33: 5 | AJ33: 3 | AK33: 4 | AL33: 8 | AM33: 15 | AO33: Banking/Financial Services | BF33: No | BG33: I have somewhat considered changing my career and/or the industry I work in | BH33: 4 | BI33: 10 | BJ33: Spain | BK33: EUR European Euro | BL33: 80000 | BM33: Yes | BN33: Bash/Shell (all shells);HTML/CSS;JavaScript;PowerShell;Python;R | BO33: HTML/CSS;PowerShell;R | BP33: HTML/CSS;PowerShell;R | BS33: Yes | BT33: BigQuery;Databricks SQL;Microsoft SQL Server;Oracle | BY33: Yes | BZ33: Chocolatey;Docker;Netlify;npm | CE33: Yes | CF33: Ruby on Rails | CI33: Jekyll | CK33: Yes | CL33: Jupyter Notebook/JupyterLab;Notepad++;PyCharm;Visual Studio Code | CO33: RStudio | CQ33: Tailwind CSS 4;Google Gemini | CV33: Windows;Ubuntu;iOS | CW33: Windows | CX33: Confluence;GitHub;Jira;Markdown File | CY33: GitHub;Markdown File | CZ33: GitHub;Markdown File | DC33: Stack Overflow;Stack Exchange;Discord;GitHub (public projects, not private repos);Slack (public channels, not work);Bluesky;X;YouTube;LinkedIn | DD33: Stack Overflow;Stack Exchange;GitHub (public projects, not private repos);X;YouTube;LinkedIn | DE33: Stack Overflow;Stack Exchange;GitHub (public projects, not private repos);X;YouTube;LinkedIn | DH33: No | DN33: Yes | DO33: Daily or almost daily | DP33: Between 3 and 5 years | DQ33: A few times per week | DR33: Chat (people);Videos;Lists of recommendations (tools, frameworks, technologies, etc.);Chat (bot/AI) | DS33: 3 | DU33: 7 | DV33: 11 | DW33: 10 | DX33: 1 | DY33: 2 | DZ33: 4 | EA33: 12 | EB33: 15 | ED33: Yes, definitely | EE33: About half of the time | EF33: Yes, I use AI tools weekly | EG33: Favorable | EH33: Neither trust nor distrust | EI33: Bad at handling complex tasks | EJ33: Learning about a codebase;Documenting code;Debugging or fixing code;Search for answers | EK33: Project planning;Writing code;Testing code;Deployment and monitoring;Predictive analytics;Generating content or synthetic data | EL33: Learning new concepts or technologies | EN33: Committing and reviewing code;Creating or maintaining documentation | EO33: AI solutions that are almost right, but not quite;Debugging AI-generated code is more time-consuming;I’ve become less confident in my own problem-solving;It’s hard to understand how or why the code works | EP33: No | EQ33: Yes, I use AI agents at work weekly | ER33: Not at all or minimally | ES33: Data and analytics | ET33: Language processing | EU33: AI agents have improved the quality of my code.;AI agents have accelerated my learning about new technologies or codebases. | EV33: AI agents have helped me automate repetitive tasks.;AI agents have improved collaboration within my team. | EW33: AI agents have helped me solve complex problems more effectively. | EX33: AI agents have increased my productivity.;AI agents have reduced the time spent on specific development tasks. | EZ33: Integrating AI agents with my existing tools and workflows can be difficult.;The cost of using certain AI agent platforms is a barrier. | FA33: It takes significant time and effort to learn how to use AI agents effectively. | FB33: I am concerned about the accuracy of the information provided by AI agents.;I have concerns about the security and privacy of data when using AI agents. | FC33: My company's IT and/or InfoSec teams have strict rules that do not allow me to use AI agent tools or platforms | FI33: Adversarial Robustness Toolbox (ART) | FK33: ChatGPT;Claude Code;GitHub Copilot;Google Gemini;Microsoft Copilot | FM33: When I want to fully understand something;When I want to learn best practices;When I want to compare different solutions;When I have ethical or security concerns about code;When I need help fixing complex or unfamiliar code;When I need quick help troubleshooting | FN33: Debugging | FO33: 92812
A34: 518 | B34: I am a developer by profession | C34: 35-44 years old | D34: Professional degree (JD, MD, Ph.D, Ed.D, etc.) | E34: Employed | F34: None of the above | G34: 4 | H34: No, I am not new to coding and did not learn new coding techniques or programming languages | J34: Yes, I learned how to use AI-enabled tools for my personal curiosity and/or hobbies | K34: Technical documentation (is generated for/by the tool or system);Other online resources (e.g. standard search, forum, online community);Blogs or podcasts;Stack Overflow or Stack Exchange | L34: 15 | M34: Applied scientist | N34: 100 to 499 employees | O34: Individual contributor | P34: Hybrid (some remote, leans heavy to in-person) | Q34: Yes, I influenced the purchase of a tool that more than five colleagues use but it is not a substantial addition to the tech stack | R34: Work | S34: 13 | T34: 3 | U34: 5 | V34: 10 | W34: 4 | X34: 1 | Y34: 9 | Z34: 2 | AA34: 6 | AB34: 14 | AD34: 14 | AE34: 3 | AF34: 4 | AG34: 6 | AH34: 1 | AI34: 11 | AJ34: 2 | AK34: 5 | AL34: 9 | AM34: 15 | AO34: Software Development | AP34: 8 | AQ34: 2 | AR34: 13 | AS34: 14 | AT34: 5 | AU34: 10 | AV34: 1 | AW34: 12 | AX34: 7 | AY34: 9 | AZ34: 3 | BA34: 11 | BB34: 6 | BC34: 15 | BD34: 4 | BF34: No | BG34: I have neither consider or transitioned into a new career or industry | BH34: 10 | BI34: 3 | BJ34: Denmark | BK34: DKK Danish krone | BL34: 708000 | BM34: Yes | BN34: Bash/Shell (all shells);F#;HTML/CSS;JavaScript;Lua;Python;R;Rust;TypeScript | BO34: Bash/Shell (all shells);HTML/CSS;Lua;Python;R;TypeScript | BP34: Bash/Shell (all shells);HTML/CSS;Lua;Python;R;TypeScript | BS34: No | BY34: No | CE34: Yes | CF34: FastAPI;Vue.js | CG34: FastAPI;Vue.js | CH34: FastAPI;Vue.js | CK34: Yes | CL34: Jupyter Notebook/JupyterLab;Neovim;Vim | CM34: Jupyter Notebook/JupyterLab;Neovim | CN34: Jupyter Notebook/JupyterLab;Neovim | CO34: GitHub Copilot | CP34: GitHub Copilot | CQ34: Large Language Model;RAG;Google Gemini | CR34: Large Language Model;RAG;Google Gemini | CS34: Large Language Model;RAG;Google Gemini | CV34: MacOS;iOS | CW34: MacOS;Ubuntu;iOS | CX34: Confluence;GitHub;Google Colab;Markdown File;Miro;Notion | CY34: GitHub;Markdown File | CZ34: GitHub;Markdown File | DC34: Stack Overflow;Stack Exchange;Discord;Reddit;Hacker News;GitHub (public projects, not private repos);Slack (public channels, not work);Bluesky;X;YouTube;LinkedIn | DD34: Stack Overflow;Stack Exchange;Reddit;GitHub (public projects, not private repos);Slack (public channels, not work);Bluesky;YouTube;LinkedIn | DE34: Stack Overflow;Stack Exchange;Reddit;GitHub (public projects, not private repos);Slack (public channels, not work);Bluesky;YouTube;LinkedIn | DH34: Yes | DI34: Alibaba Cloud Qwen models;Anthropic: Claude Sonnet;Cohere: Command A;Gemini (Flash general purpose models);Gemini (Pro Reasoning models);Meta Llama (all models);Microsoft Phi-4 models;Mistral AI models;openAI GPT (chatbot models);openAI Image generating models;openAI Reasoning models;X Grok models | DJ34: Gemini (Flash general purpose models);Gemini (Pro Reasoning models);Meta Llama (all models);openAI GPT (chatbot models);openAI Image generating models;openAI Reasoning models | DK34: Gemini (Flash general purpose models);Gemini (Pro Reasoning models);Meta Llama (all models);openAI GPT (chatbot models);openAI Image generating models;openAI Reasoning models | DN34: Yes | DO34: Multiple times per day | DP34: Between 5 and 10 years | DQ34: I have never participated in Q&A on Stack Overflow | DR34: Chat (bot/AI) | DS34: 9 | DU34: 6 | DV34: 13 | DW34: 3 | DX34: 4 | DY34: 12 | DZ34: 10 | EA34: 7 | EB34: 15 | ED34: Yes, somewhat | EE34: Rarely, almost never | EF34: Yes, I use AI tools daily | EG34: Very favorable | EH34: Somewhat distrust | EI34: I don't use AI tools for complex tasks / I don't know | EJ34: Writing code;Debugging or fixing code;Testing code;Committing and reviewing code;Search for answers;Learning new concepts or technologies | EL34: Learning about a codebase;Project planning;Deployment and monitoring | EM34: Creating or maintaining documentation | EN34: Documenting code;Predictive analytics;Generating content or synthetic data | EO34: AI solutions that are almost right, but not quite;Debugging AI-generated code is more time-consuming | EP34: No | EQ34: No, but I plan to | ER34: Not at all or minimally | EZ34: It takes significant time and effort to learn how to use AI agents effectively. | FC34: I am concerned about the accuracy of the information provided by AI agents.;The cost of using certain AI agent platforms is a barrier.;I have concerns about the security and privacy of data when using AI agents. | FD34: Integrating AI agents with my existing tools and workflows can be difficult.;My company's IT and/or InfoSec teams have strict rules that do not allow me to use AI agent tools or platforms | FM34: When I don’t trust AI’s answers;When I want to learn best practices;When I have ethical or security concerns about code;When I need help fixing complex or unfamiliar code | FN34: Being good reviewers, good architects | FO34: 110109
A35: 527 | B35: I am a developer by profession | C35: 35-44 years old | D35: Bachelor’s degree (B.A., B.S., B.Eng., etc.) | E35: Employed | F35: None of the above | G35: 18 | H35: Yes, I am not new to coding but am learning new coding techniques or programming language | I35: Videos (not associated with specific online course or certification);Technical documentation (is generated for/by the tool or system);AI CodeGen tools or AI-enabled apps | J35: Yes, I learned how to use AI-enabled tools for my personal curiosity and/or hobbies | K35: Technical documentation (is generated for/by the tool or system);Other online resources (e.g. standard search, forum, online community) | L35: 20 | M35: AI/ML engineer | N35: 1,000 to 4,999 employees | O35: Individual contributor | P35: Remote | Q35: Yes, I influenced the purchase of a substantial addition to the tech stack | R35: Work | S35: 13 | T35: 2 | U35: 1 | V35: 4 | W35: 6 | X35: 10 | Y35: 9 | Z35: 12 | AA35: 3 | AB35: 14 | AD35: 14 | AE35: 3 | AF35: 2 | AG35: 5 | AH35: 9 | AI35: 1 | AJ35: 8 | AK35: 7 | AL35: 12 | AM35: 15 | AO35: Software Development | AP35: 2 | AQ35: 3 | AR35: 5 | AS35: 6 | AT35: 9 | AU35: 7 | AV35: 10 | AW35: 8 | AX35: 11 | AY35: 12 | AZ35: 1 | BA35: 13 | BB35: 14 | BC35: 15 | BD35: 4 | BF35: Yes | BG35: I have neither consider or transitioned into a new career or industry | BH35: 16 | BI35: 20 | BJ35: Canada | BK35: CAD Canadian dollar | BL35: 150000 | BM35: Yes | BN35: Bash/Shell (all shells);C#;Go;HTML/CSS;JavaScript;PowerShell;Python;SQL;TypeScript | BO35: Mojo | BS35: Yes | BT35: DuckDB;Elasticsearch;MariaDB;Microsoft SQL Server;MySQL;PostgreSQL;Redis;Supabase | BU35: Snowflake;Valkey | BY35: Yes | BZ35: Amazon Web Services (AWS);Chocolatey;Digital Ocean;Docker;Netlify;npm;NuGet;Pip;Poetry;Supabase;Terraform;Vite | CA35: Kubernetes | CE35: Yes | CF35: Deno;React | CK35: Yes | CL35: IntelliJ IDEA;PyCharm;Rider;Vim;WebStorm | CM35: Cursor | CQ35: Polars;Large Language Model;Amazon Bedrock;RAG | CV35: MacOS;Ubuntu;iOS;NixOS | CW35: Windows | CX35: Confluence;GitHub;GitLab;Jira;Obsidian | DC35: Stack Overflow;Reddit;Hacker News;GitHub (public projects, not private repos);YouTube;Medium | DH35: Yes | DI35: openAI GPT (chatbot models) | DN35: Yes | DO35: A few times per week | DP35: Between 10 and 15 years | DQ35: Infrequently, less than once per year | DR35: Message Boards;Long-form articles;Coding challenges;Job board | ED35: No, not really | EE35: About half of the time | EF35: Yes, I use AI tools daily | EG35: Favorable | EH35: Somewhat distrust | EI35: Bad at handling complex tasks | EJ35: Generating content or synthetic data | EK35: Learning about a codebase;Debugging or fixing code;Committing and reviewing code;Deployment and monitoring;Predictive analytics;Search for answers;Learning new concepts or technologies | EL35: Project planning;Writing code;Testing code | EN35: Documenting code;Creating or maintaining documentation | EO35: AI solutions that are almost right, but not quite;Debugging AI-generated code is more time-consuming;I’ve become less confident in my own problem-solving | EP35: No | EQ35: Yes, I use AI agents at work weekly | ER35: Yes, somewhat | ES35: Software engineering | ET35: MCP servers | EU35: AI agents have accelerated my learning about new technologies or codebases.;AI agents have reduced the time spent on specific development tasks. | EV35: AI agents have helped me automate repetitive tasks. | EW35: AI agents have increased my productivity.;AI agents have helped me solve complex problems more effectively.;AI agents have improved collaboration within my team. | EY35: AI agents have improved the quality of my code. | EZ35: The cost of using certain AI agent platforms is a barrier. | FA35: Integrating AI agents with my existing tools and workflows can be difficult.;It takes significant time and effort to learn how to use AI agents effectively.;My company's IT and/or InfoSec teams have strict rules that do not allow me to use AI agent tools or platforms | FB35: I am concerned about the accuracy of the information provided by AI agents.;I have concerns about the security and privacy of data when using AI agents. | FK35: GitHub Copilot | FM35: When I don’t trust AI’s answers | FN35: The same skills as always | FO35: 109438 | FP35: 2
A36: 531 | B36: I am learning to code | C36: 25-34 years old | D36: Bachelor’s degree (B.A., B.S., B.Eng., etc.) | E36: Employed | F36: Caring for dependents (children, elderly, etc.) | G36: 10 | H36: Yes, I am not new to coding but am learning new coding techniques or programming language | I36: Other online resources (e.g. standard search, forum, online community);Books / Physical media;Videos (not associated with specific online course or certification);Stack Overflow or Stack Exchange;Technical documentation (is generated for/by the tool or system);AI CodeGen tools or AI-enabled apps | J36: Yes, I learned how to use AI-enabled tools for my personal curiosity and/or hobbies | K36: Technical documentation (is generated for/by the tool or system);Videos (not associated with specific online course or certification);Blogs or podcasts | L36: 10 | M36: Data engineer | N36: Just me - I am a freelancer, sole proprietor, etc. | O36: Individual contributor | P36: Remote | Q36: Yes, I influenced the purchase of a substantial addition to the tech stack | R36: Work | AO36: Fintech | BF36: No | BG36: I have transitioned into a new career and/or industry involuntarily | BH36: 20 | BI36: 20 | BJ36: United States of America | BK36: USD United States dollar | BL36: 250000 | DN36: Yes | DO36: Daily or almost daily | DP36: Between 10 and 15 years | DQ36: Less than once per month or monthly | FO36: 250000
A37: 545 | B37: I am a developer by profession | C37: 35-44 years old | D37: Professional degree (JD, MD, Ph.D, Ed.D, etc.) | E37: Employed | F37: Caring for dependents (children, elderly, etc.);Volunteering (regularly) | G37: 8 | H37: Yes, I am not new to coding but am learning new coding techniques or programming language | I37: Online Courses or Certification (includes all media types);Books / Physical media;Videos (not associated with specific online course or certification);Stack Overflow or Stack Exchange;Technical documentation (is generated for/by the tool or system);Blogs or podcasts | J37: Yes, I learned how to use AI-enabled tools for my personal curiosity and/or hobbies | K37: Technical documentation (is generated for/by the tool or system);Online Courses or Certification (includes all media types);Books / Physical media | L37: 20 | M37: Applied scientist | N37: Less than 20 employees | O37: Individual contributor | P37: Hybrid (some in-person, leans heavy to flexibility) | Q37: Yes, I influenced the purchase of a tool that more than five colleagues use but it is not a substantial addition to the tech stack | R37: Work | S37: 13 | T37: 10 | U37: 9 | V37: 6 | W37: 4 | X37: 1 | Y37: 2 | Z37: 11 | AA37: 5 | AB37: 14 | AD37: 14 | AE37: 3 | AF37: 11 | AG37: 8 | AH37: 6 | AI37: 2 | AJ37: 1 | AK37: 13 | AL37: 7 | AM37: 15 | AO37: Higher Education | AP37: 5 | AQ37: 2 | AR37: 11 | AS37: 6 | AT37: 3 | AU37: 4 | AV37: 13 | AW37: 12 | AX37: 10 | AY37: 9 | AZ37: 14 | BA37: 8 | BB37: 7 | BC37: 15 | BD37: 1 | BF37: No | BG37: I have strongly considered changing my career and/or the industry I work in | BJ37: United States of America | BK37: USD United States dollar | BL37: 90000 | BM37: Yes | BN37: Assembly;Bash/Shell (all shells);C;C++;Go;HTML/CSS;JavaScript;Lua;Python | BO37: C;C++;HTML/CSS;JavaScript;Lua;Python;TypeScript | BP37: C;C++;HTML/CSS;JavaScript;Lua;Python | BQ37: sage, julia | BS37: Yes | BT37: Microsoft SQL Server;MySQL;PostgreSQL;SQLite | BU37: Elasticsearch;Microsoft SQL Server;PostgreSQL;SQLite | BV37: Microsoft SQL Server;PostgreSQL;SQLite | BY37: Yes | BZ37: Cloudflare;Google Cloud;npm;Pip | CA37: Cloudflare;Google Cloud;Pip | CB37: Cloudflare;Google Cloud;Pip | CC37: cocalc | CD37: cocalc | CE37: Yes | CF37: Django;Flask;jQuery;Vue.js | CG37: Flask | CH37: Flask | CK37: Yes | CL37: Jupyter Notebook/JupyterLab;Vim | CM37: Jupyter Notebook/JupyterLab;Vim | CN37: Jupyter Notebook/JupyterLab;Vim | CQ37: c++23;Google Gemini | CR37: c++23 | CS37: c++23 | CV37: Ubuntu;Linux (non-WSL) | CW37: Ubuntu;Linux (non-WSL);Red Hat | CX37: GitHub;GitLab;Markdown File;Stack Overflow for Teams | CY37: GitHub;Markdown File | CZ37: GitHub;Markdown File | DC37: Stack Overflow;Stack Exchange;Reddit;Hacker News;GitHub (public projects, not private repos) | DD37: Stack Overflow;Stack Exchange;Reddit;Dev.to;Hacker News;GitHub (public projects, not private repos);Kaggle | DE37: Stack Overflow;Stack Exchange;Reddit;Hacker News;GitHub (public projects, not private repos) | DF37: zulip | DG37: zulip | DH37: Yes | DI37: Gemini (Flash general purpose models);Gemini (Pro Reasoning models);Mistral AI models | DJ37: Anthropic: Claude Sonnet;Gemini (Flash general purpose models);Gemini (Pro Reasoning models);Mistral AI models | DK37: Gemini (Flash general purpose models);Gemini (Pro Reasoning models);Mistral AI models | DN37: Yes | DO37: Daily or almost daily | DP37: Between 10 and 15 years | DQ37: Daily or almost daily | DR37: Job board | DS37: 3 | DU37: 11 | DV37: 1 | DW37: 6 | DX37: 5 | DY37: 9 | DZ37: 2 | EA37: 14 | EB37: 15 | ED37: Yes, definitely | EE37: Rarely, almost never | EF37: Yes, I use AI tools daily | EG37: Unfavorable | EH37: Highly distrust | EI37: Very poor at handling complex tasks | EJ37: Learning about a codebase;Writing code;Documenting code;Debugging or fixing code;Search for answers | EK37: Project planning;Testing code;Committing and reviewing code;Deployment and monitoring;Predictive analytics;Generating content or synthetic data;Creating or maintaining documentation | EL37: Learning new concepts or technologies | EO37: AI solutions that are almost right, but not quite;Debugging AI-generated code is more time-consuming | EP37: No | EQ37: No, and I don't plan to | ER37: Not at all or minimally | FA37: It takes significant time and effort to learn how to use AI agents effectively. | FB37: I am concerned about the accuracy of the information provided by AI agents.;The cost of using certain AI agent platforms is a barrier.;I have concerns about the security and privacy of data when using AI agents. | FC37: Integrating AI agents with my existing tools and workflows can be difficult.;My company's IT and/or InfoSec teams have strict rules that do not allow me to use AI agent tools or platforms | FM37: When I don’t trust AI’s answers;When I want to learn best practices;When I have ethical or security concerns about code;When I’m stuck and can’t explain the problem | FN37: Everything that is valuable now will remain valuable | FO37: 90000 | FP37: 7
A38: 548 | B38: I am a developer by profession | C38: 25-34 years old | D38: Master’s degree (M.A., M.S., M.Eng., MBA, etc.) | E38: Employed | F38: Volunteering (regularly);Attending school (part-time) | G38: 10 | H38: No, I am not new to coding and did not learn new coding techniques or programming languages | J38: Yes, I learned how to use AI-enabled tools for my personal curiosity and/or hobbies | K38: Other online resources (e.g. standard search, forum, online community);Colleague or on-the-job training | L38: 16 | M38: AI/ML engineer | N38: 10,000 or more employees | O38: Individual contributor | P38: Hybrid (some remote, leans heavy to in-person) | Q38: No | AO38: Other: | AP38: 11 | AQ38: 7 | AR38: 8 | AS38: 9 | AT38: 10 | AU38: 1 | AV38: 3 | AW38: 2 | AX38: 4 | AY38: 5 | AZ38: 6 | BA38: 13 | BB38: 14 | BC38: 15 | BD38: 12 | BF38: Yes | BG38: I have strongly considered changing my career and/or the industry I work in | BJ38: Canada | BK38: CAD Canadian dollar | BL38: 150000 | BM38: Yes | BN38: Python;SQL | BS38: No | BY38: Yes | BZ38: Amazon Web Services (AWS);Kubernetes;Pip;Poetry | CC38: uv | CD38: uv | CE38: Yes | CF38: FastAPI | CK38: Yes | CL38: Claude Code;Cline and/or Roo;Cursor;Jupyter Notebook/JupyterLab;Visual Studio Code | CV38: Windows;Fedora | CW38: MacOS | CX38: Azure Devops;GitHub;Lucid (includes Lucidchart);Notion;Obsidian | DC38: Stack Overflow;Stack Exchange | DH38: Yes | DI38: Anthropic: Claude Sonnet;Gemini (Flash general purpose models);Gemini (Pro Reasoning models);openAI GPT (chatbot models);openAI Reasoning models | DJ38: Anthropic: Claude Sonnet | DK38: Anthropic: Claude Sonnet | DN38: Yes | DO38: A few times per month or weekly | DP38: Between 10 and 15 years | DQ38: Infrequently, less than once per year | DS38: 7 | DU38: 8 | DV38: 1 | DW38: 5 | DX38: 4 | DY38: 6 | DZ38: 2 | EA38: 13 | EB38: 15 | ED38: Yes, somewhat | EE38: More than half the time | EF38: Yes, I use AI tools daily | EG38: Favorable | EH38: Somewhat distrust | EI38: Very poor at handling complex tasks | EJ38: Writing code;Debugging or fixing code;Testing code;Learning new concepts or technologies | EK38: Documenting code;Deployment and monitoring;Predictive analytics;Creating or maintaining documentation | EL38: Learning about a codebase;Project planning;Committing and reviewing code;Generating content or synthetic data | EN38: Search for answers | EO38: AI solutions that are almost right, but not quite;Debugging AI-generated code is more time-consuming;It’s hard to understand how or why the code works | EP38: No, LLMs are not reliable enough to trust their vibe yet. | EQ38: Yes, I use AI agents at work weekly | ER38: Yes, somewhat | ES38: Software engineering | EU38: AI agents have increased my productivity.;AI agents have helped me automate repetitive tasks. | EV38: AI agents have helped me solve complex problems more effectively. | EX38: AI agents have reduced the time spent on specific development tasks. | EY38: AI agents have improved the quality of my code.;AI agents have accelerated my learning about new technologies or codebases.;AI agents have improved collaboration within my team. | FB38: I am concerned about the accuracy of the information provided by AI agents. | FC38: Integrating AI agents with my existing tools and workflows can be difficult. | FD38: It takes significant time and effort to learn how to use AI agents effectively.;The cost of using certain AI agent platforms is a barrier.;I have concerns about the security and privacy of data when using AI agents.;My company's IT and/or InfoSec teams have strict rules that do not allow me to use AI agent tools or platforms | FG38: LangChain;LangGraph | FK38: ChatGPT;Claude Code;GitHub Copilot;Google Gemini;Microsoft Copilot;Perplexity | FL38: Cline | FM38: When I don’t trust AI’s answers;When I want to fully understand something;When I want to learn best practices;When I want to compare different solutions;When I have ethical or security concerns about code;When I’m stuck and can’t explain the problem;When I need help fixing complex or unfamiliar code | FN38: None. All intellectual work will be automated. We'll either all be dead or live under technofeudalism. | FO38: 109438 | FP38: 1
A39: 557 | B39: I am a developer by profession | C39: 35-44 years old | D39: Professional degree (JD, MD, Ph.D, Ed.D, etc.) | E39: Employed | F39: Caring for dependents (children, elderly, etc.) | G39: 13 | H39: No, I am not new to coding and did not learn new coding techniques or programming languages | J39: Yes, I learned how to use AI-enabled tools for my personal curiosity and/or hobbies | K39: AI CodeGen tools or AI-enabled apps;Videos (not associated with specific online course or certification) | L39: 20 | M39: Data engineer | N39: Less than 20 employees | O39: Individual contributor | P39: Remote | Q39: Yes, I influenced the purchase of a substantial addition to the tech stack | R39: Work | S39: 9 | T39: 6 | U39: 2 | V39: 10 | W39: 11 | X39: 3 | Y39: 5 | Z39: 13 | AA39: 4 | AB39: 14 | AD39: 10 | AE39: 14 | AF39: 12 | AG39: 3 | AH39: 11 | AI39: 1 | AJ39: 5 | AK39: 6 | AL39: 7 | AM39: 15 | AO39: Software Development | BF39: I'm not sure | BG39: I have strongly considered changing my career and/or the industry I work in | BH39: 25 | BI39: 20 | BJ39: Germany | BK39: EUR European Euro | BL39: 82000 | BM39: Yes | BN39: Python;SQL | BS39: Yes | BT39: Databricks SQL;DuckDB;MariaDB;MySQL;PostgreSQL;Redis;Clickhouse;Amazon Redshift | BY39: Yes | BZ39: Amazon Web Services (AWS);Ansible;Docker;Kubernetes;Make;Microsoft Azure;Pip;Poetry;Prometheus;Terraform | CE39: No | CL39: Vim;Visual Studio Code | CQ39: Polars;Google Gemini | CV39: Ubuntu | CW39: MacOS;Ubuntu;Pop!_OS | CX39: Azure Devops;Confluence;GitHub;Jira;Markdown File | DC39: Stack Overflow;Stack Exchange;Reddit;GitHub (public projects, not private repos);Slack (public channels, not work);YouTube | DH39: Yes | DI39: Gemini (Flash general purpose models);Gemini (Pro Reasoning models);Mistral AI models | EF39: Yes, I use AI tools daily | EG39: Favorable | EH39: Somewhat distrust | EI39: Neither good or bad at handling complex tasks | EJ39: Debugging or fixing code;Search for answers;Learning new concepts or technologies | EK39: Learning about a codebase;Project planning;Documenting code;Committing and reviewing code;Deployment and monitoring;Predictive analytics;Generating content or synthetic data;Creating or maintaining documentation | EL39: Testing code | EM39: Writing code | EO39: AI solutions that are almost right, but not quite | EQ39: Yes, I use AI agents at work daily | ER39: Not at all or minimally | ES39: Software engineering;IT operations;Data and analytics | FO39: 95132 | FP39: 7
A40: 570 | B40: I am not primarily a developer, but I write code sometimes as part of my work/studies | C40: 55-64 years old | D40: Master’s degree (M.A., M.S., M.Eng., MBA, etc.) | E40: Employed | F40: Caring for dependents (children, elderly, etc.) | G40: 31 | H40: No, I am not new to coding and did not learn new coding techniques or programming languages | J40: No, I learned something that was not related to AI or AI enablement for my personal curiosity and/or hobbies | L40: 38 | M40: Support engineer or analyst | N40: 20 to 99 employees | O40: Individual contributor | P40: Hybrid (some in-person, leans heavy to flexibility) | Q40: No | R40: Work | S40: 13 | T40: 7 | U40: 6 | V40: 8 | W40: 9 | X40: 2 | Y40: 11 | Z40: 3 | AA40: 1 | AB40: 4 | AC40: Good documentation | AD40: 15 | AE40: 4 | AF40: 6 | AG40: 8 | AH40: 1 | AI40: 2 | AJ40: 3 | AK40: 9 | AL40: 13 | AM40: 5 | AN40: Bad documentation | AO40: Computer Systems Design and Services | BF40: I'm not sure | BG40: I have neither consider or transitioned into a new career or industry | BH40: 15 | BI40: 2 | BJ40: Austria | BK40: EUR European Euro | BL40: 92400 | BM40: Yes | BN40: Bash/Shell (all shells);C;HTML/CSS;Java;SQL | BO40: Bash/Shell (all shells);C;HTML/CSS;Java;SQL | BP40: Bash/Shell (all shells);C;HTML/CSS;Java;SQL | BS40: Yes | BT40: Oracle;PostgreSQL | BU40: PostgreSQL | BV40: PostgreSQL | BY40: Yes | BZ40: Digital Ocean;Make;Ninja | CA40: Digital Ocean;Make;Ninja | CB40: Digital Ocean;Make;Ninja | CC40: RPM | CD40: RPM | CE40: Yes | CK40: Yes | CL40: Eclipse;Vim | CM40: Eclipse;Vim | CN40: Eclipse;Vim | CV40: Linux (non-WSL) | CW40: Linux (non-WSL) | CX40: Confluence;GitHub;GitLab;Jira;Markdown File;Wikis | CY40: GitHub;GitLab;Markdown File;Wikis | CZ40: GitHub;GitLab;Markdown File;Wikis | DC40: Stack Overflow;Stack Exchange;GitHub (public projects, not private repos) | DD40: Stack Overflow;Stack Exchange;GitHub (public projects, not private repos) | DE40: Stack Overflow;Stack Exchange;GitHub (public projects, not private repos) | DH40: No | DN40: Yes | DO40: Multiple times per day | DP40: Between 5 and 10 years | DQ40: Multiple times per day | DR40: Long-form articles;Logic games/puzzles;Other (write in): | DS40: 11 | DU40: 13 | DV40: 8 | DW40: 7 | DX40: 1 | DY40: 3 | DZ40: 5 | EA40: 14 | EB40: 15 | ED40: Yes, definitely | EE40: I don't use AI or AI-enabled tools | EF40: No, and I don't plan to | EG40: Very unfavorable | EH40: Highly distrust | EI40: I don't use AI tools for complex tasks / I don't know | EK40: Learning about a codebase;Project planning;Writing code;Documenting code;Debugging or fixing code;Testing code;Committing and reviewing code;Deployment and monitoring;Predictive analytics;Search for answers;Generating content or synthetic data;Creating or maintaining documentation;Learning new concepts or technologies | EO40: I don’t use AI tools regularly | EP40: No | EQ40: No, and I don't plan to | ER40: Not at all or minimally | EZ40: Integrating AI agents with my existing tools and workflows can be difficult.;It takes significant time and effort to learn how to use AI agents effectively.;The cost of using certain AI agent platforms is a barrier. | FB40: I am concerned about the accuracy of the information provided by AI agents. | FC40: I have concerns about the security and privacy of data when using AI agents. | FD40: My company's IT and/or InfoSec teams have strict rules that do not allow me to use AI agent tools or platforms | FM40: When I don’t trust AI’s answers;When I want to fully understand something;When I have ethical or security concerns about code | FN40: true understanding of the world and its problems, creative thinking | FO40: 107198
A41: 601 | B41: I am a developer by profession | C41: 35-44 years old | D41: Professional degree (JD, MD, Ph.D, Ed.D, etc.) | E41: Employed | F41: Engaged in paid work (less than 10 hours per week) | G41: 15 | H41: No, I am not new to coding and did not learn new coding techniques or programming languages | J41: Yes, I learned how to use AI-enabled tools for my personal curiosity and/or hobbies | K41: Technical documentation (is generated for/by the tool or system);Videos (not associated with specific online course or certification);Other online resources (e.g. standard search, forum, online community);Blogs or podcasts | L41: 19 | M41: Data scientist | N41: 20 to 99 employees | O41: Individual contributor | P41: Hybrid (some in-person, leans heavy to flexibility) | Q41: No | R41: Work | S41: 13 | T41: 4 | U41: 3 | V41: 7 | W41: 5 | X41: 2 | Y41: 12 | Z41: 14 | AA41: 10 | AB41: 1 | AC41: open the source license | AD41: 13 | AE41: 1 | AF41: 6 | AG41: 3 | AH41: 12 | AI41: 8 | AJ41: 10 | AK41: 14 | AL41: 5 | AM41: 15 | AO41: Government | AP41: 1 | AQ41: 3 | AR41: 6 | AS41: 7 | AT41: 8 | AU41: 9 | AV41: 10 | AW41: 4 | AX41: 11 | AY41: 12 | AZ41: 2 | BA41: 13 | BB41: 14 | BC41: 15 | BD41: 5 | BF41: No | BG41: I have neither consider or transitioned into a new career or industry | BH41: 3 | BI41: 3 | BJ41: Luxembourg | BK41: EUR European Euro | BL41: 120000 | BM41: Yes | BN41: Bash/Shell (all shells);HTML/CSS;R | BS41: No | BY41: Yes | BZ41: APT;Cargo;Digital Ocean;Docker;Kubernetes;Netlify;Pacman;Podman | CC41: Nix | CE41: No | CK41: Yes | CL41: Aider | CO41: Emacs | CQ41: Polars;Large Language Model | CV41: MacOS;Linux (non-WSL);Arch;NixOS | CW41: Windows;Ubuntu | CX41: Confluence;GitHub;GitLab;Jira | DC41: Stack Overflow;Stack Exchange;Reddit;Dev.to;GitHub (public projects, not private repos);Slack (public channels, not work);Bluesky;X;YouTube;LinkedIn | DH41: Yes | DI41: Anthropic: Claude Sonnet;DeepSeek (R- Reasoning models);Gemini (Flash general purpose models);Gemini (Pro Reasoning models);Mistral AI models;openAI Reasoning models;X Grok models | DN41: Yes | DO41: Less than once per month or monthly | DP41: Between 10 and 15 years | DQ41: Less than once every 2 - 3 months | DR41: Chat (people);Message Boards;Long-form articles;Chat (bot/AI) | DS41: 5 | DU41: 7 | DV41: 3 | DW41: 1 | DX41: 14 | DY41: 10 | DZ41: 12 | EA41: 9 | EB41: 15 | ED41: No, not at all | EE41: Less than half of the time | EF41: Yes, I use AI tools daily | EG41: Favorable | EH41: Somewhat trust | EI41: Good, but not great at handling complex tasks | EJ41: Writing code;Documenting code;Testing code;Committing and reviewing code;Deployment and monitoring;Search for answers;Generating content or synthetic data;Creating or maintaining documentation;Learning new concepts or technologies | EK41: Predictive analytics | EN41: Learning about a codebase;Project planning;Debugging or fixing code | EO41: AI solutions that are almost right, but not quite | EP41: no | EQ41: No, and I don't plan to | ER41: Yes, somewhat | EZ41: I am concerned about the accuracy of the information provided by AI agents.;It takes significant time and effort to learn how to use AI agents effectively. | FB41: The cost of using certain AI agent platforms is a barrier.;My company's IT and/or InfoSec teams have strict rules that do not allow me to use AI agent tools or platforms | FC41: Integrating AI agents with my existing tools and workflows can be difficult.;I have concerns about the security and privacy of data when using AI agents. | FM41: When I don’t trust AI’s answers;When I want to fully understand something;When I want to learn best practices | FN41: statistical modeling and hypothesis testing and validation | FO41: 139218 | FP41: 8
A42: 609 | B42: I am a developer by profession | C42: 55-64 years old | D42: Bachelor’s degree (B.A., B.S., B.Eng., etc.) | E42: Employed | F42: Caring for dependents (children, elderly, etc.) | G42: 25 | H42: Yes, I am not new to coding but am learning new coding techniques or programming language | I42: Other online resources (e.g. standard search, forum, online community);Books / Physical media;Videos (not associated with specific online course or certification);Stack Overflow or Stack Exchange;Technical documentation (is generated for/by the tool or system);AI CodeGen tools or AI-enabled apps;Blogs or podcasts | J42: Yes, I learned how to use AI-enabled tools for my personal curiosity and/or hobbies | K42: AI CodeGen tools or AI-enabled apps;Other online resources (e.g. standard search, forum, online community) | L42: 29 | M42: Data engineer | N42: 10,000 or more employees | O42: Individual contributor | P42: Hybrid (some in-person, leans heavy to flexibility) | Q42: Yes, I endorsed a tool that was open-source and is currently used by more than just myself but no purchase was made | R42: Work | S42: 13 | T42: 3 | U42: 5 | V42: 8 | W42: 1 | X42: 6 | Y42: 12 | Z42: 2 | AA42: 4 | AB42: 14 | AD42: 14 | AE42: 9 | AF42: 11 | AG42: 2 | AH42: 10 | AI42: 1 | AJ42: 4 | AK42: 6 | AL42: 5 | AM42: 15 | AO42: Internet, Telecomm or Information Services | AP42: 1 | AQ42: 2 | AR42: 8 | AS42: 13 | AT42: 11 | AU42: 7 | AV42: 4 | AW42: 9 | AX42: 6 | AY42: 5 | AZ42: 3 | BA42: 10 | BB42: 14 | BC42: 15 | BD42: 12 | BF42: I'm not sure | BG42: I have neither consider or transitioned into a new career or industry | BH42: 15 | BI42: 5 | BJ42: Switzerland | BK42: CHF Swiss franc | BL42: 120000 | BM42: Yes | BN42: Bash/Shell (all shells);Perl;PHP;Python;SQL;TypeScript | BO42: Bash/Shell (all shells);Erlang;Python;Rust;SQL | BP42: Bash/Shell (all shells);Python;SQL | BS42: Yes | BT42: MariaDB;Microsoft SQL Server;PostgreSQL;Redis;SQLite;Amazon Redshift | BU42: DuckDB;PostgreSQL;Redis;Clickhouse | BV42: PostgreSQL;Redis | BW42: Iceberg | BY42: Yes | BZ42: Amazon Web Services (AWS);APT;Cargo;Docker;Homebrew;Kubernetes;Make;npm;Pip;Podman;Splunk | CA42: APT;Docker;Kubernetes;Splunk | CB42: APT;Docker;Kubernetes;Splunk | CC42: uv | CD42: uv | CE42: Yes | CF42: FastAPI;jQuery;Laravel;Node.js | CG42: FastAPI;Flask | CH42: FastAPI | CK42: Yes | CL42: Jupyter Notebook/JupyterLab;PhpStorm;PyCharm;Vim;Visual Studio Code | CM42: Jupyter Notebook/JupyterLab;PyCharm;Vim | CN42: Jupyter Notebook/JupyterLab;PyCharm;Vim | CQ42: Polars;Large Language Model;Amazon Bedrock;RAG | CR42: Polars;Large Language Model | CS42: Polars;Large Language Model | CV42: MacOS;iOS;Debian;Linux (non-WSL) | CW42: MacOS;Debian;Linux (non-WSL);Red Hat | CX42: Confluence;GitLab;Jira;Miro;YouTrack | CY42: Confluence;GitLab | CZ42: Confluence;GitLab | DC42: Stack Overflow;Stack Exchange;Reddit;Hacker News;GitHub (public projects, not private repos);Bluesky;X;YouTube;LinkedIn;Substack;Medium;Company-sponsored forums | DD42: Stack Overflow;Stack Exchange;Reddit;Hacker News;GitHub (public projects, not private repos);YouTube;Company-sponsored forums | DE42: Stack Overflow;Stack Exchange;Reddit;Hacker News;GitHub (public projects, not private repos);YouTube;Company-sponsored forums | DH42: Yes | DI42: Anthropic: Claude Sonnet;Meta Llama (all models);Mistral AI models;openAI GPT (chatbot models) | DJ42: Anthropic: Claude Sonnet;Meta Llama (all models) | DK42: Anthropic: Claude Sonnet;Meta Llama (all models) | DN42: Yes | DO42: Multiple times per day | DP42: More than 15 years, or since Stack Overflow started in 2008 | DQ42: Less than once per month or monthly | DR42: Long-form articles;Day-in-the-life profiles/interviews with experts | DS42: 9 | DU42: 11 | DV42: 1 | DW42: 5 | DX42: 4 | DY42: 6 | DZ42: 3 | EA42: 12 | EB42: 15 | ED42: Yes, somewhat | EE42: Less than half of the time | EF42: Yes, I use AI tools daily | EG42: Favorable | EH42: Somewhat distrust | EI42: Very poor at handling complex tasks | EK42: Learning about a codebase;Project planning;Debugging or fixing code;Committing and reviewing code;Deployment and monitoring;Predictive analytics | EL42: Writing code;Documenting code;Testing code;Search for answers;Generating content or synthetic data;Creating or maintaining documentation;Learning new concepts or technologies | EO42: AI solutions that are almost right, but not quite;I’ve become less confident in my own problem-solving;Other (write in): | EP42: No, I want to understand what is happening; this is more important to me than speed. | EQ42: No, and I don't plan to | ER42: Yes, somewhat | EZ42: My company's IT and/or InfoSec teams have strict rules that do not allow me to use AI agent tools or platforms | FB42: I am concerned about the accuracy of the information provided by AI agents.;Integrating AI agents with my existing tools and workflows can be difficult.;The cost of using certain AI agent platforms is a barrier.;I have concerns about the security and privacy of data when using AI agents. | FC42: It takes significant time and effort to learn how to use AI agents effectively. | FM42: When I don’t trust AI’s answers;When I want to fully understand something;When I have ethical or security concerns about code;When I need help fixing complex or unfamiliar code;Other (please specify): | FN42: Code review. Communication and clarification of requirements specific to the domain or company. Security. Handling new problems for which there are not already a dozen published solutions. | FO42: 148791 | FP42: 8
A43: 619 | B43: I am a developer by profession | C43: 45-54 years old | D43: Professional degree (JD, MD, Ph.D, Ed.D, etc.) | E43: Employed | F43: Volunteering (regularly) | G43: 30 | H43: No, I am not new to coding and did not learn new coding techniques or programming languages | J43: Yes, I learned how to use AI-enabled tools for my personal curiosity and/or hobbies | K43: Technical documentation (is generated for/by the tool or system);Other online resources (e.g. standard search, forum, online community);Books / Physical media | L43: 42 | M43: Data scientist | N43: 20 to 99 employees | O43: People manager | P43: Hybrid (some remote, leans heavy to in-person) | Q43: Yes, I influenced the purchase of a tool that more than five colleagues use but it is not a substantial addition to the tech stack | R43: Work | S43: 7 | T43: 9 | U43: 1 | V43: 12 | W43: 3 | X43: 5 | Y43: 10 | Z43: 4 | AA43: 6 | AB43: 14 | AD43: 13 | AE43: 7 | AF43: 1 | AG43: 6 | AH43: 5 | AI43: 11 | AJ43: 2 | AK43: 3 | AL43: 12 | AM43: 15 | AO43: Retail and Consumer Services | AP43: 3 | AQ43: 1 | AR43: 10 | AS43: 14 | AT43: 5 | AU43: 12 | AV43: 6 | AW43: 4 | AX43: 7 | AY43: 2 | AZ43: 9 | BA43: 11 | BB43: 13 | BC43: 15 | BD43: 8 | BF43: Yes | BG43: I have somewhat considered changing my career and/or the industry I work in | BH43: 3 | BI43: 3 | BJ43: Germany | BK43: EUR European Euro | BL43: 180000 | BM43: Yes | BN43: Bash/Shell (all shells);C;HTML/CSS;PHP;Python;R;SQL | BO43: Bash/Shell (all shells);C;Python;R;SQL | BP43: Bash/Shell (all shells);C;Python;R;SQL | BS43: Yes | BT43: BigQuery;DuckDB;Dynamodb;MariaDB;PostgreSQL;Redis;SQLite | BU43: BigQuery;DuckDB;PostgreSQL;SQLite | BV43: BigQuery;DuckDB;PostgreSQL;SQLite | BY43: Yes | BZ43: Amazon Web Services (AWS);Docker;Google Cloud;Kubernetes;Pip | CA43: Amazon Web Services (AWS);Docker;Google Cloud;Kubernetes;Pip | CB43: Amazon Web Services (AWS);Docker;Google Cloud;Kubernetes;Pip | CE43: Yes | CF43: FastAPI;Flask;Symfony;Vue.js | CG43: FastAPI;Vue.js | CH43: FastAPI;Vue.js | CK43: Yes | CL43: Jupyter Notebook/JupyterLab;Vim;Visual Studio Code | CM43: Jupyter Notebook/JupyterLab;Vim;Visual Studio Code | CN43: Jupyter Notebook/JupyterLab;Vim;Visual Studio Code | CQ43: RAG;Google Gemini | CV43: Ubuntu;Linux (non-WSL) | CW43: MacOS;Linux (non-WSL) | CX43: Confluence;GitHub;GitLab;Google Colab | CY43: GitHub;GitLab;Google Colab | CZ43: GitHub;GitLab;Google Colab | DC43: Stack Overflow;GitHub (public projects, not private repos) | DD43: GitHub (public projects, not private repos) | DE43: GitHub (public projects, not private repos) | DH43: Yes | DI43: Anthropic: Claude Sonnet;DeepSeek (R- Reasoning models);Gemini (Flash general purpose models);Microsoft Phi-4 models;openAI GPT (chatbot models);openAI Reasoning models | DJ43: DeepSeek (R- Reasoning models);Microsoft Phi-4 models;openAI GPT (chatbot models);openAI Reasoning models | DK43: DeepSeek (R- Reasoning models);Microsoft Phi-4 models;openAI GPT (chatbot models);openAI Reasoning models | DN43: Yes | DO43: A few times per month or weekly | DP43: More than 15 years, or since Stack Overflow started in 2008 | DQ43: Less than once every 2 - 3 months | DS43: 10 | DU43: 8 | DV43: 5 | DW43: 12 | DX43: 3 | DY43: 2 | DZ43: 1 | EA43: 13 | EB43: 15 | ED43: Yes, somewhat | EE43: Rarely, almost never | EF43: Yes, I use AI tools daily | EG43: Favorable | EH43: Somewhat trust | EI43: Good, but not great at handling complex tasks | EJ43: Predictive analytics;Generating content or synthetic data;Learning new concepts or technologies | EK43: Project planning;Testing code;Committing and reviewing code | EL43: Learning about a codebase;Debugging or fixing code;Deployment and monitoring | EM43: Writing code;Documenting code | EN43: Search for answers;Creating or maintaining documentation | EO43: AI solutions that are almost right, but not quite;Debugging AI-generated code is more time-consuming | EP43: No | EQ43: Yes, I use AI agents at work daily | ER43: Yes, somewhat | ES43: Business process automation;Data and analytics;Customer service support | ET43: Agent/multi-agent orchestration;Vector databases for AI applications;Integration with external agents and APIs | EU43: AI agents have improved the quality of my code.;AI agents have accelerated my learning about new technologies or codebases. | EV43: AI agents have improved collaboration within my team. | EX43: AI agents have increased my productivity.;AI agents have helped me automate repetitive tasks.;AI agents have helped me solve complex problems more effectively.;AI agents have reduced the time spent on specific development tasks. | FA43: I am concerned about the accuracy of the information provided by AI agents.;Integrating AI agents with my existing tools and workflows can be difficult.;I have concerns about the security and privacy of data when using AI agents. | FD43: It takes significant time and effort to learn how to use AI agents effectively.;The cost of using certain AI agent platforms is a barrier.;My company's IT and/or InfoSec teams have strict rules that do not allow me to use AI agent tools or platforms | FE43: ChromaDB;pgvector;Milvus;Weaviate;Pinecone | FG43: LangChain;LangGraph | FK43: ChatGPT;Google Gemini;Perplexity | FM43: I don’t think I’ll need help from people anymore | FN43: Patience | FO43: 208826 | FP43: 8
A44: 620 | B44: I am a developer by profession | C44: 35-44 years old | D44: Bachelor’s degree (B.A., B.S., B.Eng., etc.) | E44: Employed | F44: Caring for dependents (children, elderly, etc.) | G44: 25 | H44: No, I am not new to coding and did not learn new coding techniques or programming languages | J44: Yes, I learned how to use AI-enabled tools for my personal curiosity and/or hobbies | K44: Technical documentation (is generated for/by the tool or system);Videos (not associated with specific online course or certification);Colleague or on-the-job training;Blogs or podcasts;Books / Physical media | L44: 27 | M44: Developer, AI apps or physical AI | N44: 10,000 or more employees | O44: Individual contributor | P44: Remote | Q44: Yes, I endorsed a tool that was open-source and is currently used by more than just myself but no purchase was made | R44: Work | S44: 11 | T44: 6 | U44: 5 | V44: 7 | W44: 1 | X44: 9 | Y44: 13 | Z44: 3 | AA44: 2 | AB44: 14 | AD44: 14 | AE44: 5 | AF44: 7 | AG44: 8 | AH44: 1 | AI44: 6 | AJ44: 3 | AK44: 11 | AL44: 4 | AM44: 15 | AO44: Software Development | AP44: 2 | AQ44: 4 | AR44: 8 | AS44: 12 | AT44: 7 | AU44: 14 | AV44: 5 | AW44: 13 | AX44: 6 | AY44: 11 | AZ44: 1 | BA44: 10 | BB44: 9 | BC44: 15 | BD44: 3 | BF44: I'm not sure | BG44: I have neither consider or transitioned into a new career or industry | BH44: 12 | BI44: 4 | BJ44: United States of America | BK44: USD United States dollar | BL44: 310000 | BM44: Yes | BN44: Bash/Shell (all shells);Python;Ruby | BO44: Go;Lua;Ruby;Rust;TypeScript | BP44: Ruby | BS44: Yes | BT44: Dynamodb;Elasticsearch;PostgreSQL;Redis;SQLite | BU44: PostgreSQL;Redis;SQLite;Valkey | BV44: PostgreSQL;Redis;SQLite | BY44: Yes | BZ44: Amazon Web Services (AWS);Docker;Google Cloud;Homebrew;Kubernetes;npm;Pip;Poetry;Prometheus | CA44: Amazon Web Services (AWS);Docker;Homebrew;Kubernetes;Prometheus | CB44: Amazon Web Services (AWS);Docker;Homebrew;Kubernetes;Prometheus | CD44: uv | CE44: Yes | CF44: FastAPI | CK44: Yes | CL44: Jupyter Notebook/JupyterLab;Vim;Visual Studio Code | CM44: Vim;Visual Studio Code | CN44: Vim;Visual Studio Code | CQ44: Large Language Model;Amazon Bedrock | CV44: Windows;MacOS | CW44: MacOS;Ubuntu | CX44: Confluence;GitHub;Jira;Miro | CY44: GitHub;Miro | CZ44: GitHub;Miro | DA44: Roam Research | DB44: Roam Research | DC44: Stack Overflow;Discord;Reddit;Hacker News;Twitch;LinkedIn;Medium | DD44: Discord;Reddit;Hacker News;Twitch;Medium | DE44: Discord;Reddit;Hacker News;Twitch;Medium | DH44: Yes | DI44: openAI GPT (chatbot models) | DN44: Yes | DO44: A few times per month or weekly | DP44: More than 15 years, or since Stack Overflow started in 2008 | DQ44: I have never participated in Q&A on Stack Overflow | DR44: Long-form articles;Day-in-the-life profiles/interviews with experts | DS44: 9 | DU44: 10 | DV44: 13 | DW44: 1 | DX44: 4 | DY44: 8 | DZ44: 7 | EA44: 12 | EB44: 15 | ED44: No, not at all | EE44: Rarely, almost never | EF44: Yes, I use AI tools daily | EG44: Favorable | EH44: Neither trust nor distrust | EI44: Good, but not great at handling complex tasks | EK44: Project planning;Committing and reviewing code;Deployment and monitoring;Predictive analytics | EL44: Learning about a codebase;Writing code;Testing code;Search for answers;Generating content or synthetic data;Learning new concepts or technologies | EM44: Documenting code;Debugging or fixing code;Creating or maintaining documentation | EO44: AI solutions that are almost right, but not quite | EP44: No. | EQ44: No, and I don't plan to | ER44: Not at all or minimally | EZ44: Integrating AI agents with my existing tools and workflows can be difficult.;It takes significant time and effort to learn how to use AI agents effectively. | FB44: I am concerned about the accuracy of the information provided by AI agents.;I have concerns about the security and privacy of data when using AI agents. | FC44: The cost of using certain AI agent platforms is a barrier.;My company's IT and/or InfoSec teams have strict rules that do not allow me to use AI agent tools or platforms | FM44: When I don’t trust AI’s answers;When I want to fully understand something;When I want to compare different solutions;When I have ethical or security concerns about code;When I’m stuck and can’t explain the problem;When I need help fixing complex or unfamiliar code;Other (please specify): | FN44: Larger systems design thinking and planning.
A45: Writing quality | B45: well tested code that follows good practices will never completely go ""out of style""
A46: Finding a way to help teach/train AIs to do a better job of producing software." | B46: 310000.0 | C46: 9.0
A47: 623 | B47: I am a developer by profession | C47: 45-54 years old | D47: Associate degree (A.A., A.S., etc.) | E47: Independent contractor, freelancer, or self-employed | F47: None of the above | G47: 30 | H47: No, I am not new to coding and did not learn new coding techniques or programming languages | J47: Yes, I learned how to use AI-enabled tools required for my job or to benefit my career | K47: AI CodeGen tools or AI-enabled apps;Technical documentation (is generated for/by the tool or system);Online Courses or Certification (includes all media types);Books / Physical media | L47: 30 | M47: Data engineer | Q47: Yes, I influenced the purchase of a substantial addition to the tech stack | R47: Work | S47: 7 | T47: 12 | U47: 3 | V47: 10 | W47: 6 | X47: 8 | Y47: 2 | Z47: 9 | AA47: 4 | AB47: 14 | AD47: 11 | AE47: 7 | AF47: 12 | AG47: 5 | AH47: 14 | AI47: 1 | AJ47: 8 | AK47: 4 | AL47: 13 | AM47: 15 | AO47: Healthcare | AP47: 3 | AQ47: 4 | AR47: 8 | AS47: 14 | AT47: 5 | AU47: 6 | AV47: 1 | AW47: 12 | AX47: 7 | AY47: 2 | AZ47: 9 | BA47: 10 | BB47: 11 | BC47: 15 | BD47: 13 | BF47: No | BG47: I have neither consider or transitioned into a new career or industry | BH47: 13 | BI47: 6 | BJ47: United States of America | BK47: USD United States dollar | BL47: 300000 | BM47: Yes | BN47: HTML/CSS;JavaScript;Kotlin;PowerShell;Python;SQL | BO47: R;Scala | BS47: Yes | BT47: Cosmos DB;MariaDB;Microsoft Access;Microsoft SQL Server | BU47: Databricks SQL;DuckDB;PostgreSQL;Snowflake;Amazon Redshift | BY47: Yes | BZ47: Cloudflare;Datadog;Google Cloud;Microsoft Azure;Pip | CA47: Amazon Web Services (AWS);Docker;Kubernetes;Prometheus;Splunk;Terraform;Vercel | CE47: Yes | CF47: Flask;WordPress | CG47: Django | CK47: Yes | CL47: Jupyter Notebook/JupyterLab;Notepad++;Visual Studio Code | CM47: Claude Code;Cursor;VSCodium | CQ47: Polars;Microsoft Fabric | CR47: Amazon Bedrock | CV47: Windows;MacOS;iOS | CW47: Windows;iOS | CX47: GitHub;Google Colab;Markdown File;Notion;YouTrack | CY47: Airtable | DC47: Discord;GitHub (public projects, not private repos);Kaggle;Substack;Medium | DH47: Yes | DI47: openAI GPT (chatbot models);openAI Reasoning models | DJ47: Anthropic: Claude Sonnet | DN47: Yes | DO47: Less than once per month or monthly | DP47: Between 5 and 10 years | DQ47: Infrequently, less than once per year | DR47: Long-form articles;Coding challenges;Lists of recommendations (tools, frameworks, technologies, etc.) | DS47: 5 | DU47: 12 | DV47: 1 | DW47: 11 | DX47: 6 | DY47: 13 | DZ47: 9 | EA47: 7 | EB47: 15 | ED47: No, not at all | EE47: Rarely, almost never | EF47: Yes, I use AI tools daily | EG47: Very favorable | EH47: Somewhat trust | EI47: Good, but not great at handling complex tasks | EJ47: Testing code;Deployment and monitoring;Predictive analytics;Generating content or synthetic data;Creating or maintaining documentation | EL47: Committing and reviewing code | EM47: Project planning | EN47: Learning about a codebase;Writing code;Documenting code;Debugging or fixing code;Search for answers;Learning new concepts or technologies | EO47: AI solutions that are almost right, but not quite;Debugging AI-generated code is more time-consuming | EP47: I start with a specific ask and prompt, receive a initial code, which is about 75% complete / functional. Then through testing and iteration with additional targeted prompts, work toward a working application. | EQ47: No, but I plan to | ER47: Yes, to a great extent | EZ47: It takes significant time and effort to learn how to use AI agents effectively.;My company's IT and/or InfoSec teams have strict rules that do not allow me to use AI agent tools or platforms | FB47: I have concerns about the security and privacy of data when using AI agents. | FC47: I am concerned about the accuracy of the information provided by AI agents.;The cost of using certain AI agent platforms is a barrier. | FD47: Integrating AI agents with my existing tools and workflows can be difficult. | FM47: When I want to fully understand something | FN47: Soft skills communication, understanding business needs and asks. Understanding what the code is doing, security, and how to troubleshoot. | FO47: 300000 | FP47: 8
A48: 631 | B48: I am a developer by profession | C48: 55-64 years old | D48: Professional degree (JD, MD, Ph.D, Ed.D, etc.) | E48: Employed | F48: Caring for dependents (children, elderly, etc.);Volunteering (regularly);Attending school (part-time) | G48: 42 | H48: Yes, I am not new to coding but am learning new coding techniques or programming language | I48: Books / Physical media | J48: No, I learned something that was not related to AI or AI enablement for my personal curiosity and/or hobbies | L48: 42 | M48: Applied scientist | N48: Less than 20 employees | O48: Individual contributor | P48: Hybrid (some in-person, leans heavy to flexibility) | Q48: Yes, I influenced the purchase of a substantial addition to the tech stack | R48: Work | S48: 13 | T48: 6 | U48: 1 | V48: 3 | W48: 5 | X48: 4 | Y48: 8 | Z48: 2 | AA48: 12 | AB48: 14 | AD48: 14 | AE48: 10 | AF48: 4 | AG48: 3 | AH48: 8 | AI48: 1 | AJ48: 2 | AK48: 7 | AL48: 13 | AM48: 15 | AO48: Software Development | AP48: 6 | AQ48: 2 | AR48: 13 | AS48: 10 | AT48: 12 | AU48: 3 | AV48: 4 | AW48: 11 | AX48: 1 | AY48: 5 | AZ48: 7 | BA48: 8 | BB48: 9 | BC48: 15 | BD48: 14 | BF48: No | BG48: I have neither consider or transitioned into a new career or industry | BH48: 12 | BI48: 6 | BJ48: Germany | BK48: EUR European Euro | BL48: 140000 | BM48: Yes | BN48: Ada;Assembly;Bash/Shell (all shells);C;C++;HTML/CSS;Lisp;MATLAB;PHP | BS48: No | BY48: No | CE48: No | CK48: No | CQ48: c++23 | CV48: Ubuntu | CW48: MacOS | CX48: Wikis | DC48: Stack Overflow;Stack Exchange;Discord;Reddit;YouTube;Substack | DH48: No | DN48: Yes | DO48: A few times per month or weekly | DP48: Between 10 and 15 years | DQ48: Less than once every 2 - 3 months | DS48: 4 | DU48: 6 | DV48: 9 | DW48: 1 | DX48: 3 | DY48: 10 | DZ48: 13 | EA48: 12 | EB48: 15 | ED48: Yes, definitely | EE48: More than half the time | EF48: No, and I don't plan to | EG48: Very favorable | EH48: Highly distrust | EI48: Very poor at handling complex tasks | EK48: Learning about a codebase;Project planning;Writing code;Documenting code;Debugging or fixing code;Testing code;Committing and reviewing code;Deployment and monitoring;Predictive analytics;Creating or maintaining documentation;Learning new concepts or technologies | EL48: Search for answers;Generating content or synthetic data | EO48: AI solutions that are almost right, but not quite;Debugging AI-generated code is more time-consuming | EP48: absolutely NO for safety and security reasons. | EQ48: No, and I don't plan to | ER48: Not at all or minimally | EZ48: Integrating AI agents with my existing tools and workflows can be difficult. | FA48: It takes significant time and effort to learn how to use AI agents effectively.;The cost of using certain AI agent platforms is a barrier. | FB48: I am concerned about the accuracy of the information provided by AI agents.;I have concerns about the security and privacy of data when using AI agents. | FC48: My company's IT and/or InfoSec teams have strict rules that do not allow me to use AI agent tools or platforms | FM48: When I don’t trust AI’s answers;When I want to compare different solutions | FN48: thinking, developing new algorithms, and writing+testing code without using the internet :) | FO48: 162421 | FP48: 10
A49: 674 | B49: I am a developer by profession | C49: 35-44 years old | D49: Bachelor’s degree (B.A., B.S., B.Eng., etc.) | E49: Not employed | F49: Engaged in paid work (10-19 hours per week) | G49: 10 | H49: Yes, I am not new to coding but am learning new coding techniques or programming language | I49: Online Courses or Certification (includes all media types);Other online resources (e.g. standard search, forum, online community);Books / Physical media;Videos (not associated with specific online course or certification);Stack Overflow or Stack Exchange;Technical documentation (is generated for/by the tool or system);Blogs or podcasts | J49: No, I learned something that was not related to AI or AI enablement as required for my job or to benefit my career | L49: 10 | M49: Data engineer | N49: Less than 20 employees | O49: Individual contributor | P49: Hybrid (some in-person, leans heavy to flexibility) | Q49: Yes, I influenced the purchase of a substantial addition to the tech stack | R49: Work | S49: 14 | T49: 8 | U49: 5 | V49: 3 | W49: 2 | X49: 9 | Y49: 7 | Z49: 1 | AA49: 6 | AB49: 13 | AD49: 13 | AE49: 5 | AF49: 9 | AG49: 7 | AH49: 3 | AI49: 2 | AJ49: 1 | AK49: 15 | AL49: 10 | AM49: 12 | AO49: Healthcare | AP49: 2 | AQ49: 3 | AR49: 4 | AS49: 14 | AT49: 12 | AU49: 8 | AV49: 7 | AW49: 9 | AX49: 6 | AY49: 5 | AZ49: 1 | BA49: 10 | BB49: 11 | BC49: 15 | BD49: 13 | BF49: I'm not sure | BG49: I have strongly considered changing my career and/or the industry I work in | BH49: 8 | BI49: 8 | BJ49: United States of America | BK49: USD United States dollar | BL49: 210000 | BM49: Yes | BN49: Bash/Shell (all shells);C#;Python;SQL | BO49: C#;C++;Python;SQL | BP49: C#;Python;SQL | BQ49: Julia | BR49: Julia | BS49: Yes | BT49: BigQuery;Databricks SQL;DuckDB;Microsoft SQL Server;MySQL;PostgreSQL;Snowflake | BU49: BigQuery;Databricks SQL;DuckDB;Microsoft SQL Server;PostgreSQL | BV49: BigQuery;Databricks SQL;DuckDB;Microsoft SQL Server;PostgreSQL | BY49: Yes | BZ49: Amazon Web Services (AWS);Docker;Google Cloud;Kubernetes;Microsoft Azure | CA49: Amazon Web Services (AWS);Docker;Google Cloud;Kubernetes;Microsoft Azure | CB49: Amazon Web Services (AWS);Docker;Google Cloud;Kubernetes;Microsoft Azure | CE49: Yes | CF49: ASP.NET Core | CG49: ASP.NET Core | CH49: ASP.NET Core | CK49: Yes | CL49: Notepad++;PyCharm;Visual Studio;Visual Studio Code | CM49: Notepad++;PyCharm;Visual Studio;Visual Studio Code | CN49: Notepad++;PyCharm;Visual Studio;Visual Studio Code | CO49: DataGrip | CP49: DataGrip | CQ49: Polars | CR49: Polars | CS49: Polars | CV49: Windows;Ubuntu;Windows Subsystem for Linux (WSL) | CW49: Windows;Ubuntu;Windows Subsystem for Linux (WSL) | CX49: Azure Devops;GitHub;GitLab | CY49: Azure Devops;GitHub;GitLab | CZ49: Azure Devops;GitHub;GitLab | DC49: Stack Exchange;Reddit;LinkedIn | DD49: Reddit | DE49: Reddit | DH49: No | DN49: Yes | DO49: Daily or almost daily | DP49: Between 10 and 15 years | DQ49: Infrequently, less than once per year | DR49: Chat (people);Long-form articles;Coding challenges;Lists of recommendations (tools, frameworks, technologies, etc.);Job board | DS49: 2 | DU49: 11 | DV49: 1 | DW49: 3 | DX49: 4 | DY49: 7 | DZ49: 12 | EA49: 9 | EB49: 15 | ED49: No, not really | EE49: I don't use AI or AI-enabled tools | EF49: Yes, I use AI tools monthly or infrequently | EG49: Unfavorable | EH49: Somewhat distrust | EI49: Neither good or bad at handling complex tasks | EK49: Learning about a codebase;Project planning;Writing code;Debugging or fixing code;Testing code;Committing and reviewing code;Deployment and monitoring;Predictive analytics;Search for answers;Generating content or synthetic data;Creating or maintaining documentation;Learning new concepts or technologies | EL49: Documenting code | EO49: AI solutions that are almost right, but not quite;Debugging AI-generated code is more time-consuming;I don’t use AI tools regularly;It’s hard to understand how or why the code works | EP49: Fuck No | EQ49: No, and I don't plan to | ER49: Not at all or minimally | FB49: I am concerned about the accuracy of the information provided by AI agents.;I have concerns about the security and privacy of data when using AI agents. | FC49: Integrating AI agents with my existing tools and workflows can be difficult.;It takes significant time and effort to learn how to use AI agents effectively.;The cost of using certain AI agent platforms is a barrier.;My company's IT and/or InfoSec teams have strict rules that do not allow me to use AI agent tools or platforms | FM49: When I don’t trust AI’s answers;When I want to fully understand something;When I want to learn best practices;When I want to compare different solutions;When I have ethical or security concerns about code;When I’m stuck and can’t explain the problem;When I need help fixing complex or unfamiliar code;When I need quick help troubleshooting | FN49: AI needs data to function, data needs to be properly served to be useful. Understanding of data, storage, and processing will be critical | FO49: 210000 | FP49: 5
A50: 697 | B50: I am a developer by profession | C50: 25-34 years old | D50: Master’s degree (M.A., M.S., M.Eng., MBA, etc.) | E50: Employed | G50: 2 | H50: Yes, I am not new to coding but am learning new coding techniques or programming language | I50: Online Courses or Certification (includes all media types);Videos (not associated with specific online course or certification);Stack Overflow or Stack Exchange | J50: Yes, I learned how to use AI-enabled tools for my personal curiosity and/or hobbies | K50: Videos (not associated with specific online course or certification);Other online resources (e.g. standard search, forum, online community);Online Courses or Certification (includes all media types);Stack Overflow or Stack Exchange | L50: 9 | M50: Data scientist | N50: 10,000 or more employees | O50: Individual contributor | P50: Your choice (very flexible, you can come in when you want or just as needed) | Q50: No | R50: Work | S50: 9 | T50: 3 | U50: 6 | V50: 7 | W50: 5 | X50: 11 | Y50: 10 | Z50: 4 | AA50: 1 | AB50: 14 | AD50: 3 | AE50: 1 | AF50: 8 | AG50: 13 | AH50: 12 | AI50: 14 | AJ50: 9 | AK50: 11 | AL50: 2 | AM50: 15 | AO50: Government | AP50: 2 | AQ50: 3 | AR50: 4 | AS50: 9 | AT50: 11 | AU50: 10 | AV50: 1 | AW50: 7 | AX50: 8 | AY50: 5 | AZ50: 14 | BA50: 12 | BB50: 13 | BC50: 15 | BD50: 6 | BF50: No | BG50: I have somewhat considered changing my career and/or the industry I work in | BH50: 15 | BI50: 5 | BJ50: Italy | BK50: EUR European Euro | BL50: 28000 | BM50: Yes | BN50: Python;SQL | BO50: C++;Python;SQL | BP50: Python;SQL | BS50: Yes | BT50: IBM DB2;Oracle | BU50: Dynamodb;Oracle;PostgreSQL | BV50: Oracle | BY50: Yes | BZ50: Amazon Web Services (AWS);Docker;IBM Cloud;Pip | CA50: Amazon Web Services (AWS);Pip | CB50: Amazon Web Services (AWS);Pip | CE50: Yes | CF50: FastAPI;Flask | CG50: FastAPI | CH50: FastAPI | CK50: Yes | CL50: Jupyter Notebook/JupyterLab;PyCharm;Sublime Text;Visual Studio | CM50: Jupyter Notebook/JupyterLab;PyCharm;Sublime Text | CN50: Jupyter Notebook/JupyterLab;PyCharm;Sublime Text | CQ50: Polars;Large Language Model;RAG | CR50: Polars;Large Language Model | CS50: Polars;Large Language Model | CV50: Windows | CW50: Windows;Ubuntu | CX50: Confluence;GitLab;Monday.com;Trello | CY50: GitHub;Monday.com | CZ50: Monday.com | DC50: Stack Overflow;Stack Exchange;Discord;GitHub (public projects, not private repos);Slack (public channels, not work);Kaggle;YouTube;LinkedIn;Medium | DD50: Stack Overflow;Stack Exchange;Discord;GitHub (public projects, not private repos);YouTube;LinkedIn;Medium | DE50: Stack Overflow;Stack Exchange;Discord;GitHub (public projects, not private repos);YouTube;LinkedIn;Medium | DH50: Yes | DI50: DeepSeek (V- General purpose models);Gemini (Flash general purpose models);Meta Llama (all models);Mistral AI models | DJ50: Gemini (Flash general purpose models);Meta Llama (all models);Mistral AI models | DK50: Gemini (Flash general purpose models);Meta Llama (all models);Mistral AI models | DN50: Yes | DO50: Daily or almost daily | DP50: Between 5 and 10 years | DQ50: Daily or almost daily | DR50: Long-form articles;Coding challenges;Logic games/puzzles;Direct messaging of users;Job board | DS50: 8 | DU50: 13 | DV50: 7 | DW50: 14 | DX50: 2 | DY50: 4 | DZ50: 1 | EA50: 9 | EB50: 15 | ED50: Yes, definitely | EE50: Less than half of the time | EF50: Yes, I use AI tools weekly | EG50: Indifferent | EH50: Neither trust nor distrust | EI50: Very poor at handling complex tasks | EJ50: Learning about a codebase;Predictive analytics;Search for answers;Generating content or synthetic data | EK50: Project planning;Writing code;Debugging or fixing code;Testing code;Deployment and monitoring | EL50: Committing and reviewing code | EM50: Documenting code | EN50: Creating or maintaining documentation;Learning new concepts or technologies | EO50: AI solutions that are almost right, but not quite;Debugging AI-generated code is more time-consuming;It’s hard to understand how or why the code works | EP50: no, never | EQ50: No, and I don't plan to | ER50: Not at all or minimally | EZ50: It takes significant time and effort to learn how to use AI agents effectively.;I have concerns about the security and privacy of data when using AI agents.;My company's IT and/or InfoSec teams have strict rules that do not allow me to use AI agent tools or platforms | FC50: I am concerned about the accuracy of the information provided by AI agents.;The cost of using certain AI agent platforms is a barrier. | FD50: Integrating AI agents with my existing tools and workflows can be difficult. | FM50: When I don’t trust AI’s answers;When I want to fully understand something;When I’m stuck and can’t explain the problem;When I need help fixing complex or unfamiliar code | FN50: Creativity in the development of a good solution, given a solution can be the infrastructure of a system. Delegating such task to an AI would result in a mess, even though at first sight the solution might resemble valid and sound. Same issue in 3-5 years likely, not 100% sure. | FO50: 32484 | FP50: 6
